Workbook
Name Button_1: "X2160060266_Sheet3_List"
Name KRT: #REF!
Name Manufacturing: Validation!$C$2:$C$115
Name Obligation: #REF!
Name Product: #REF!
Name Services: Validation!$I$2:$I$50
Name tata: #REF!
Name Teja: '[1]Oblig Details & RTR'!$OQ$1:$OQ$6
Name Trading: Validation!$F$2:$F$118
Name Type: #REF!
Name X2160060266_Sheet3_List: #REF!

Sheet BasicInput
B1: Segment (select from dropdown): | C1: Affordable | E1: Customer Type (select from dropdown): | H1: Self-employed Non-Professional (SENP)
A4: Parties to the Loan
A5: S. No. | B5: Name | C5: Constitution (select from dropdown) | D5: Capacity (Applicant / Co-applicant / Guarantor) | E5: Age at the time of | G5: Relationship with Applicant | H5: CIBIL Score | I5: Income Considered (Y / N) | J5: Property Ownership (Y / N)
E6: Application | F6: Maturity
A7: 1 | B7: KANHAIYA BHARTI | C7: Individual | D7: APPLICANT | E7: =2024-1975 -> 49 | F7: =E7+20 -> 69 | G7: SELF | H7: 781 | I7: Y | J7: Y
A8: 2 | B8: SANDHYA BHARTI | C8: Individual | D8: CO-APPLICANT | E8: =2024-1982 -> 42 | F8: =E8+20 -> 62 | G8: SPOUSE | H8: -1 | I8: N | J8: N
A9: 3
A10: 4
A11: 5
A12: 6
A13: 7
A14: 8
A15: 9
A16: 10
A19: Proposed Loan Break-up
A21: S. No. | B21: Type of Loan | C21: Nature of Transaction | D21: Loan Amount (Rs.) | E21: Tenure (Months) | F21: Proposed ROI | G21: EMI (Rs.)
A22: 1 | B22: Composite Loan (Plot Purchase plus Home Construction) | C22: Purchase from Builder | D22: 3000000 | E22: 240 | F22: 0.12 | G22: =IFERROR(CEILING(PMT(F22/12,E22,-D22),1),0) -> 33033 | H22: Industrial Check | I22: =IF(AND(B22="",B23="",B24="",B25="",B26=""),"",IF(OR(B22=Validation!A29,B22=Validation!A36,B23=Validation!A29,B23=Validation!A36,B24=Validation!A29,B24=Validation!A36,B25=Validation!A29,B25=Validation!A36,B26=Validation!A29,B26=Validation!A36),"Y","N")) -> N | J22: =IF(B22="",0,IF(AND(B22=Validation!$A$37,OR($H$28="IndlGPL",$H$28="IndlGPLIns",$H$28="LAPGPL",$H$28="LAPGPLIns")),60,IF(AND(B22=Validation!$A$37,OR($H$28="HLGPL",$H$28="HLGPLIns",$H$28="GPL",$H$28="GPLIns")),120,IF($H$28="Indl",120,IF($H$28="LAP",240,360))))) -> 360 | K22: =IFERROR(IF(AND(H1="Salaried",OR(B22=Validation!A19,B22=Validation!A22,B22=Validation!A25,B22=Validation!A38)),360,VLOOKUP(B22,Validation!$A$19:$B$38,2,0)),0) -> 240
A23: 2 | G23: =IFERROR(CEILING(PMT(F23/12,E23,-D23),1),0) -> 0 | H23: LAP/Comm Check | I23: =IF(AND(B22="",B23="",B24="",B25="",B26=""),"",IF(OR(B22=Validation!A27,B22=Validation!A28,B22=Validation!A30,B22=Validation!A31,B22=Validation!A32,B22=Validation!A33,B22=Validation!A35,B23=Validation!A27,B23=Validation!A28,B23=Validation!A30,B23=Validation!A31,B23=Validation!A32,B23=Validation!A33,B23=Validation!A35,B24=Validation!A27,B24=Validation!A28,B24=Validation!A30,B24=Validation!A31,B24=Validation!A32,B24=Validation!A33,B24=Validation!A35,B25=Validation!A27,B25=Validation!A28,B25=Validation!A30,B25=Validation!A31,B25=Validation!A32,B25=Validation!A33,B25=Validation!A35,B26=Validation!A27,B26=Validation!A28,B26=Validation!A30,B26=Validation!A31,B26=Validation!A32,B26=Validation!A33,B26=Validation!A35),"Y","N")) -> N | J23: =IF(B23="",0,IF(AND(B23=Validation!$A$37,OR($H$28="IndlGPL",$H$28="IndlGPLIns",$H$28="LAPGPL",$H$28="LAPGPLIns")),60,IF(AND(B23=Validation!$A$37,OR($H$28="HLGPL",$H$28="HLGPLIns",$H$28="GPL",$H$28="GPLIns")),120,IF($H$28="Indl",120,IF($H$28="LAP",240,360))))) -> 0 | K23: =IFERROR(IF(AND(H2="Salaried",OR(B23=Validation!A20,B23=Validation!A23,B23=Validation!A26,B23=Validation!A39)),360,VLOOKUP(B23,Validation!$A$19:$B$38,2,0)),0) -> 0
A24: 3 | G24: =IFERROR(CEILING(PMT(F24/12,E24,-D24),1),0) -> 0 | H24: GPL Check | I24: =IF(AND(B22="",B23="",B24="",B25="",B26=""),"",IF(OR(B22=Validation!A37,B23=Validation!A37,B24=Validation!A37,B25=Validation!A37,B26=Validation!A37),"Y","N")) -> N | J24: =IF(B24="",0,IF(AND(B24=Validation!$A$37,OR($H$28="IndlGPL",$H$28="IndlGPLIns",$H$28="LAPGPL",$H$28="LAPGPLIns")),60,IF(AND(B24=Validation!$A$37,OR($H$28="HLGPL",$H$28="HLGPLIns",$H$28="GPL",$H$28="GPLIns")),120,IF($H$28="Indl",120,IF($H$28="LAP",240,360))))) -> 0 | K24: =IFERROR(IF(AND(H3="Salaried",OR(B24=Validation!A21,B24=Validation!A24,B24=Validation!A27,B24=Validation!A40)),360,VLOOKUP(B24,Validation!$A$19:$B$38,2,0)),0) -> 0
A25: 4 | G25: =IFERROR(CEILING(PMT(F25/12,E25,-D25),1),0) -> 0 | H25: Insurance Check | I25: =IF(AND(B22="",B23="",B24="",B25="",B26=""),"",IF(OR(B22=Validation!A38,B23=Validation!A38,B24=Validation!A38,B25=Validation!A38,B26=Validation!A38),"Y","N")) -> N | J25: =IF(B25="",0,IF(AND(B25=Validation!$A$37,OR($H$28="IndlGPL",$H$28="IndlGPLIns",$H$28="LAPGPL",$H$28="LAPGPLIns")),60,IF(AND(B25=Validation!$A$37,OR($H$28="HLGPL",$H$28="HLGPLIns",$H$28="GPL",$H$28="GPLIns")),120,IF($H$28="Indl",120,IF($H$28="LAP",240,360))))) -> 0 | K25: =IFERROR(IF(AND(H4="Salaried",OR(B25=Validation!A22,B25=Validation!A25,B25=Validation!A28,B25=Validation!A41)),360,VLOOKUP(B25,Validation!$A$19:$B$38,2,0)),0) -> 0
A26: 5 | G26: =IFERROR(CEILING(PMT(F26/12,E26,-D26),1),0) -> 0 | H26: HL Check | I26: =IF(AND(B22="",B23="",B24="",B25="",B26=""),"",IF(OR(B22=Validation!A19,B22=Validation!A20,B22=Validation!A21,B22=Validation!A22,B22=Validation!A23,B22=Validation!A24,B22=Validation!A25,B22=Validation!A26,B23=Validation!A19,B23=Validation!A20,B23=Validation!A21,B23=Validation!A22,B23=Validation!A23,B23=Validation!A24,B23=Validation!A25,B23=Validation!A26,B24=Validation!A19,B24=Validation!A20,B24=Validation!A21,B24=Validation!A22,B24=Validation!A23,B24=Validation!A24,B24=Validation!A25,B24=Validation!A26,B25=Validation!A19,B25=Validation!A20,B25=Validation!A21,B25=Validation!A22,B25=Validation!A23,B25=Validation!A24,B25=Validation!A25,B25=Validation!A26,B26=Validation!A19,B26=Validation!A20,B26=Validation!A21,B26=Validation!A22,B26=Validation!A23,B26=Validation!A24,B26=Validation!A25,B26=Validation!A26),"Y","N")) -> Y | J26: =IF(B26="",0,IF(AND(B26=Validation!$A$37,OR($H$28="IndlGPL",$H$28="IndlGPLIns",$H$28="LAPGPL",$H$28="LAPGPLIns")),60,IF(AND(B26=Validation!$A$37,OR($H$28="HLGPL",$H$28="HLGPLIns",$H$28="GPL",$H$28="GPLIns")),120,IF($H$28="Indl",120,IF($H$28="LAP",240,360))))) -> 0 | K26: =IFERROR(IF(AND(H5="Salaried",OR(B26=Validation!A23,B26=Validation!A26,B26=Validation!A29,B26=Validation!A42)),360,VLOOKUP(B26,Validation!$A$19:$B$38,2,0)),0) -> 0
A27: Total | D27: =SUM(D22:D26) -> 3000000 | E27: =IFERROR(SUMPRODUCT($D$22:$D$26,$E$22:$E$26)/$D$27,0) -> 240 | F27: =IFERROR(SUMPRODUCT($D$22:$D$26,$F$22:$F$26)/$D$27,0) -> 0.12 | G27: =SUM(G22:G26) -> 33033
B28: =COUNTIF($B$22:$B$26,Validation!$A$19)+COUNTIF($B$22:$B$26,Validation!$A$20)+COUNTIF($B$22:$B$26,Validation!$A$21)+COUNTIF($B$22:$B$26,Validation!$A$22)+COUNTIF($B$22:$B$26,Validation!$A$23)+COUNTIF($B$22:$B$26,Validation!$A$24)+COUNTIF($B$22:$B$26,Validation!$A$25)+COUNTIF($B$22:$B$26,Validation!$A$26) -> 1 | C28: Loan (excl GPL & Insurance) | D28: =D27-SUMIF(B22:B26,Validation!A37,D22:D26)-SUMIF(B22:B26,Validation!A38,D22:D26) -> 3000000 | F28: =G27/D27 -> 0.011011 | G28: =G27-SUMIF(B22:B26,Validation!A37,G22:G26)-SUMIF(B22:B26,Validation!A38,G22:G26) -> 33033 | H28: =IF(AND(I22="Y",I24="Y",I25="Y"),"IndlGPLIns",IF(AND(I22="Y",I24="Y"),"IndlGPL",IF(AND(I22="Y",I25="Y"),"IndlIns",IF(I22="Y","Indl",IF(AND(I23="Y",I24="Y",I25="Y"),"LAPGPLIns",IF(AND(I23="Y",I24="Y"),"LAPGPL",IF(AND(I23="Y",I25="Y"),"LAPIns",IF(I23="Y","LAP",IF(AND(I26="Y",I24="Y",I25="Y"),"HLGPLIns",IF(AND(I26="Y",I24="Y"),"HLGPL",IF(AND(I26="Y",I25="Y"),"HLIns",IF(I26="Y","HL",IF(AND(I24="Y",I25="Y"),"GPLIns",IF(I24="Y","GPL",IF(I25="Y","Ins",""))))))))))))))) -> HL
A31: Property Details [Provide estimated details if not finalized]
A33: S. No. | B33: Property Address | C33: Property Type | D33: Owner(s) / Proposed Owner(s) | E33: Area (Sq Ft) | F33: Usage / Proposed Usage | G33: Whether in APF Project? | H33: Our existing exposure against the Property (Rs.) | I33: Valuation 1 (Rs.) | J33: Valuation 2 (Rs.) | K33: Agreement Value / Property Cost (incl Amenities) as may be applicable (Rs.) | L33: Stage of Construction | M33: Difference % in Valuations | N33: Valuation to be considered (Rs.)
A34: 1 | M34: =IF(AND(I34="",J34=""),"",IF(OR(I34="",J34=""),"N.A.",IF(I34>=J34,(I34-J34)/J34,(J34-I34)/I34))) | N34: =IF(AND(G34="Y",OR($H$28="HL",$H$28="HLGPL",$H$28="HLIns",$H$28="HLGPLIns")),IF(K34="","Agreement Value / Property Cost required",IF(AND(I34<>"",J34<>""),MIN(I34,J34,K34),IF(I34<>"",MIN(I34,K34),IF(J34<>"",MIN(J34,K34),"")))),IF(AND(OR(G34="N",G34=""),OR($H$28="HL",$H$28="HLGPL",$H$28="HLIns",$H$28="HLGPLIns")),IF(K34="","Agreement Value / Property Cost required",IF(AND(I34<>"",J34<>""),MIN(I34,J34),IF(AND(I34<>"",$D$27<=5000000),I34,IF(AND(J34<>"",$D$27<=5000000),J34,"")))),IF(AND(OR(I34="",J34=""),$D$27>5000000),"Two Valuations required",IF(AND(I34<>"",J34=""),I34,IF(AND(J34<>"",I34=""),J34,MIN(I34,J34)))))) -> Agreement Value / Property Cost required | O34: =IF(OR(I34="",J34=""),"",IF(M34>15%,"3rd Valuation to be fired if Lowest Valuation not sufficient for Eligibility",""))
A35: 2 | M35: =IF(AND(I35="",J35=""),"",IF(OR(I35="",J35=""),"N.A.",IF(I35>=J35,(I35-J35)/J35,(J35-I35)/I35))) | N35: =IF(AND(G35="Y",OR($H$28="HL",$H$28="HLGPL",$H$28="HLIns",$H$28="HLGPLIns")),IF(K35="","Agreement Value / Property Cost required",IF(AND(I35<>"",J35<>""),MIN(I35,J35,K35),IF(I35<>"",MIN(I35,K35),IF(J35<>"",MIN(J35,K35),"")))),IF(AND(OR(G35="N",G35=""),OR($H$28="HL",$H$28="HLGPL",$H$28="HLIns",$H$28="HLGPLIns")),IF(K35="","Agreement Value / Property Cost required",IF(AND(I35<>"",J35<>""),MIN(I35,J35),IF(AND(I35<>"",$D$27<=5000000),I35,IF(AND(J35<>"",$D$27<=5000000),J35,"")))),IF(AND(OR(I35="",J35=""),$D$27>5000000),"Two Valuations required",IF(AND(I35<>"",J35=""),I35,IF(AND(J35<>"",I35=""),J35,MIN(I35,J35)))))) -> Agreement Value / Property Cost required | O35: =IF(OR(I35="",J35=""),"",IF(M35>15%,"3rd Valuation to be fired if Lowest Valuation not sufficient for Eligibility",""))
A36: 3 | M36: =IF(AND(I36="",J36=""),"",IF(OR(I36="",J36=""),"N.A.",IF(I36>=J36,(I36-J36)/J36,(J36-I36)/I36))) | N36: =IF(AND(G36="Y",OR($H$28="HL",$H$28="HLGPL",$H$28="HLIns",$H$28="HLGPLIns")),IF(K36="","Agreement Value / Property Cost required",IF(AND(I36<>"",J36<>""),MIN(I36,J36,K36),IF(I36<>"",MIN(I36,K36),IF(J36<>"",MIN(J36,K36),"")))),IF(AND(OR(G36="N",G36=""),OR($H$28="HL",$H$28="HLGPL",$H$28="HLIns",$H$28="HLGPLIns")),IF(K36="","Agreement Value / Property Cost required",IF(AND(I36<>"",J36<>""),MIN(I36,J36),IF(AND(I36<>"",$D$27<=5000000),I36,IF(AND(J36<>"",$D$27<=5000000),J36,"")))),IF(AND(OR(I36="",J36=""),$D$27>5000000),"Two Valuations required",IF(AND(I36<>"",J36=""),I36,IF(AND(J36<>"",I36=""),J36,MIN(I36,J36)))))) -> Agreement Value / Property Cost required | O36: =IF(OR(I36="",J36=""),"",IF(M36>15%,"3rd Valuation to be fired if Lowest Valuation not sufficient for Eligibility",""))
A37: 4 | M37: =IF(AND(I37="",J37=""),"",IF(OR(I37="",J37=""),"N.A.",IF(I37>=J37,(I37-J37)/J37,(J37-I37)/I37))) | N37: =IF(AND(G37="Y",OR($H$28="HL",$H$28="HLGPL",$H$28="HLIns",$H$28="HLGPLIns")),IF(K37="","Agreement Value / Property Cost required",IF(AND(I37<>"",J37<>""),MIN(I37,J37,K37),IF(I37<>"",MIN(I37,K37),IF(J37<>"",MIN(J37,K37),"")))),IF(AND(OR(G37="N",G37=""),OR($H$28="HL",$H$28="HLGPL",$H$28="HLIns",$H$28="HLGPLIns")),IF(K37="","Agreement Value / Property Cost required",IF(AND(I37<>"",J37<>""),MIN(I37,J37),IF(AND(I37<>"",$D$27<=5000000),I37,IF(AND(J37<>"",$D$27<=5000000),J37,"")))),IF(AND(OR(I37="",J37=""),$D$27>5000000),"Two Valuations required",IF(AND(I37<>"",J37=""),I37,IF(AND(J37<>"",I37=""),J37,MIN(I37,J37)))))) -> Agreement Value / Property Cost required | O37: =IF(OR(I37="",J37=""),"",IF(M37>15%,"3rd Valuation to be fired if Lowest Valuation not sufficient for Eligibility",""))
A38: 5 | M38: =IF(AND(I38="",J38=""),"",IF(OR(I38="",J38=""),"N.A.",IF(I38>=J38,(I38-J38)/J38,(J38-I38)/I38))) | N38: =IF(AND(G38="Y",OR($H$28="HL",$H$28="HLGPL",$H$28="HLIns",$H$28="HLGPLIns")),IF(K38="","Agreement Value / Property Cost required",IF(AND(I38<>"",J38<>""),MIN(I38,J38,K38),IF(I38<>"",MIN(I38,K38),IF(J38<>"",MIN(J38,K38),"")))),IF(AND(OR(G38="N",G38=""),OR($H$28="HL",$H$28="HLGPL",$H$28="HLIns",$H$28="HLGPLIns")),IF(K38="","Agreement Value / Property Cost required",IF(AND(I38<>"",J38<>""),MIN(I38,J38),IF(AND(I38<>"",$D$27<=5000000),I38,IF(AND(J38<>"",$D$27<=5000000),J38,"")))),IF(AND(OR(I38="",J38=""),$D$27>5000000),"Two Valuations required",IF(AND(I38<>"",J38=""),I38,IF(AND(J38<>"",I38=""),J38,MIN(I38,J38)))))) -> Agreement Value / Property Cost required | O38: =IF(OR(I38="",J38=""),"",IF(M38>15%,"3rd Valuation to be fired if Lowest Valuation not sufficient for Eligibility",""))
A39: Total | H39: =SUM(H34:H38) -> 0 | I39: =SUM(I34:I38) -> 0 | J39: =SUM(J34:J38) -> 0 | K39: =SUM(K34:K38) -> 0 | N39: =SUM(N34:N38) -> 0
F40: =IF(AND(F34="",F35="",F36="",F37="",F38=""),"",IF(OR(F34=Validation!A83,F35=Validation!A83,F36=Validation!A83,F37=Validation!A83,F38=Validation!A83),Validation!A83,IF(OR(F34=Validation!A82,F35=Validation!A82,F36=Validation!A82,F37=Validation!A82,F38=Validation!A82),Validation!A82,Validation!A81))) | I40: Final Valuation as per Norms: | J40: =N39 -> 0
A43: Additional Inputs for Eligibility Computation
D44: (Figs in Rs.)
A45: Particulars | D45: =PrimeConsolidated!C7 -> FY 2023-24 | E45: =PrimeConsolidated!D7 -> FY 2022-23
A46: Extraordinary Income like Profit on Sale of Asset (Capital Gain), One Time Interest, Donation, Insurance Claim, etc if not already excluded while arriving at PBT
A47: Extraordinary Expenses like Loss on Sale of Asset (Capital Loss), Loss on Theft, Donation made, etc deducted while arriving at PBT
A48: Salary Income (as per ITR if not considered while arriving at PBT) [Annualized]
A49: Rental Income {Existing Rentals as per ITR or Regd Lease Deed copy (>=3 months old) with Bank Credits / occupancy verified by Risk Team or in absence of Regd Lease Agreement, Avg of last 2 years Rentals as per ITRs} [Annualized]
A50: Agricultural Income - Avg of last 2 years as per ITRs
A51: Interest / Dividend Income - Avg of last 2 years as per ITRs {such Income should be reflecting in at least past 2 years' ITRs}
A52: Any other Income not included while arriving at PBT but reflecting in at least past 2 years' ITRs - Avg of last 2 years as per ITRs
A53: Rental Income from Property Mortgaged and Rentals escrowed with ABHFL (if not incl above) {Existing Rentals as per Regd Lease Deed copy (>=3 mths old) with Bank Credits (>=6 mths) / occupancy verified by Risk Team or in absence of Regd Lease Agreement, Avg of last 2 years Rentals from such Property as per ITRs} [Annualized]
A54: Type of Professional, if any (select from dropdown) [for Gross Receipts Program]

Sheet SalariedEligibility
A1: Salaried Eligibility
A2: Loan Amount Requested (In INR) | B2: =BasicInput!$D$27 -> 3000000
A3: ROI | B3: =BasicInput!$F$27 -> 0.12
A4: Tenure - Months | B4: =BasicInput!$E$27 -> 240
A5: EMI on requested Loan Amount | B5: =BasicInput!$G$27 -> 33033
A7: Product - Property Type | B7: Home Loan
A8: Valuation Details | B8: Value
A9: Property Value - Valuation-1 | B9: =BasicInput!$I$39 -> 0
A10: Property Value - Valuation-2 | B10: =BasicInput!$J$39 -> 0
A11: Property Value - Final | B11: =IF($B$2<5000000,$B$9,MIN($B$9,$B$10)) -> 0
A13: Obligation Details | B13: Value
A14: Monthly Obligations to be considered in eligibility (excluding those against standalone Pension Income) | B14: ='ExistingLoans&Facilities&RTR'!$N$103 -> 0
A15: Obligations not to be considered in eligibility | B15: ='ExistingLoans&Facilities&RTR'!$N$105 -> 0
A17: Income Details
A18: Parameters | B18: % considered | C18: Previous Year | D18: Current Year | E18: Frequency | F18: Amount Considered
A19: Core Income (excluding Pension Income, if any)
A20: Basic | B20: 1 | D20: =ApplicantSalary!G8+'Co-app1Salary'!G8+'Co-app2Salary'!G8+'Co-app3Salary'!G8 -> 0 | E20: Monthly
A21: DA | B21: 1 | D21: =ApplicantSalary!G9+'Co-app1Salary'!G9+'Co-app2Salary'!G9+'Co-app3Salary'!G9 -> 0 | E21: Monthly
A22: HRA | B22: 1 | D22: =ApplicantSalary!G10+'Co-app1Salary'!G10+'Co-app2Salary'!G10+'Co-app3Salary'!G10 -> 0 | E22: Monthly
A23: Other Allowances | B23: 1 | D23: =SUM(ApplicantSalary!$G$11:$G$14)+SUM('Co-app1Salary'!$G$11:$G$14)+SUM('Co-app2Salary'!$G$11:$G$14)+SUM('Co-app3Salary'!$G$11:$G$14) -> 0 | E23: Monthly
A24: Gross Salary | B24: 1 | D24: =SUM(D20:D23) -> 0 | E24: Monthly
A25: Less - Deductions | B25: 1 | D25: =ApplicantSalary!G22+'Co-app1Salary'!G22+'Co-app2Salary'!G22+'Co-app3Salary'!G22 -> 0 | E25: Monthly
A26: Net Salary | B26: 1 | D26: =D24-D25 -> 0 | E26: Monthly | F26: =IF(E26="Monthly",(D26*B26)*12,(D26*B26)) -> 0
A27: Bonus & LTA
A28: Fixed Bonus | B28: 1 | C28: =ApplicantSalary!C27+'Co-app1Salary'!C27+'Co-app2Salary'!C27+'Co-app3Salary'!C27 -> 0 | D28: =ApplicantSalary!B27+'Co-app1Salary'!B27+'Co-app2Salary'!B27+'Co-app3Salary'!B27 -> 0 | E28: Annual | F28: =IF(E28="Monthly",(D28*B28)*12,(D28*B28)) -> 0
A29: Performance Linked Bonus | B29: 0.5 | C29: =ApplicantSalary!C28+'Co-app1Salary'!C28+'Co-app2Salary'!C28+'Co-app3Salary'!C28 -> 0 | D29: =ApplicantSalary!B28+'Co-app1Salary'!B28+'Co-app2Salary'!B28+'Co-app3Salary'!B28 -> 0 | E29: Annual | F29: =IF(E29="Monthly",(D29*B29)*12,(D29*B29)) -> 0
A30: LTA | B30: 1 | C30: =ApplicantSalary!C29+'Co-app1Salary'!C29+'Co-app2Salary'!C29+'Co-app3Salary'!C29 -> 0 | D30: =ApplicantSalary!B29+'Co-app1Salary'!B29+'Co-app2Salary'!B29+'Co-app3Salary'!B29 -> 0 | E30: Annual | F30: =IF(E30="Monthly",(D30*B30)*12,(D30*B30)) -> 0
A31: Pension Income
A32: Net Monthly Pension Income (not included in Core Income above and capped at 35% of Gross Monthly Income) | B32: 1 | E32: Monthly
A33: - Loan Obligations against Pension Income (not included in Obligations above) | B33: 1 | E33: Monthly
A34: Loan Tenure (months) for Pension Income portion
A35: Other Income
A36: Rental Income | B36: 0.5 | D36: =BasicInput!D49 -> 0 | E36: Annual | F36: =IF(E36="Monthly",(IF(C36=0,D36*B36*12,AVERAGE(C36*B36,D36*B36)*12)),IF(C36=0,D36*B36,(AVERAGE(C36*B36,D36*B36)))) -> 0
A37: Rental Income (Unregistered) | B37: 0.5 | E37: Annual | F37: =IF(E37="Monthly",(IF(C37=0,D37*B37*12,AVERAGE(C37*B37,D37*B37)*12)),IF(C37=0,D37*B37,(AVERAGE(C37*B37,D37*B37)))) -> 0
A38: Agricultural Income | B38: 0.5 | D38: =BasicInput!D50 -> 0 | E38: Annual | F38: =IF(E38="Monthly",AVERAGE(C38*B38,D38*B38)*12,AVERAGE(C38*B38,D38*B38)) -> 0
A39: Interest From FD / Dividend Income | B39: 1 | D39: =BasicInput!D51 -> 0 | E39: Annual | F39: =IF(E39="Monthly",AVERAGE(C39*B39,D39*B39)*12,AVERAGE(C39*B39,D39*B39)) -> 0
A40: Other Income | B40: 1 | D40: =BasicInput!D52 -> 0 | E40: Annual | F40: =IF(E40="Monthly",AVERAGE(C40*B40,D40*B40)*12,AVERAGE(C40*B40,D40*B40)) -> 0
A41: Other Income to be capped at 100% of the Core Income
A42: Rental Income from Property Mortgaged and Rentals escrowed with ABHFL
A43: Escrowed Rental Income | B43: 1 | D43: =BasicInput!D53 -> 0 | E43: Annual | F43: =IF(E43="Monthly",(D43*B43)*12,(D43*B43)) -> 0
A44: Escrowed Rental Income (Unregistered) | B44: 1 | E44: Annual | F44: =IF(E44="Monthly",AVERAGE(C44*B44,D44*B44)*12,AVERAGE(C44*B44,D44*B44)) -> 0
A45: Eligible Income (excluding Pension) | F45: =IF(SUM(F36:F40)<F26,SUM(F26,F28:F30,F36:F40,F43:F44),SUM(F26,F28:F30,F26,F43:F44)) -> 0
A46: Eligible Income (excluding Pension) = Core Income + Bonus & LTA + Other Income + Rental Income from Property Mortgaged with ABHFL
A48: Eligibility Computation
A50: Monthly Income | B50: =F45/12 -> 0
A51: Applicable FOIR | B51: =IF(F45>2400000,75%,IF(F45>1200000,70%,IF(F45>500000,65%,60%))) -> 0.6
A52: Appraised Obligations (excluding those against standalone Pension Income) | B52: =B14 -> 0
A53: Amount Available for EMI Servicing | B53: =(B50*B51)-B52 -> 0
A54: Loan Eligibility - Based on Income (including for Pension portion) | B54: =IF((B53+D32-D33)<=0,"Case Not Eligible",((B53/(PMT(B3/12,B4,-100000)))+(((D32*50%)-D33)/PMT(B3/12,IF(OR(D32="",D32=0),B4,D34),-100000)))*100000) -> Case Not Eligible
A56: Property Value | B56: =B11 -> 0
A57: Applicable LTV | B57: =IF(B7="LAP-Resi",70%,IF(B7="LAP-Resi (Vacant)",65%,IF(B7="LAP-Comm",60%,IF(B7="LAP-Comm (Vacant)",55%,IF(B7="Commerical Purchase",60%,IF(AND(B7="Home Loan",B2<=3000000),90%,IF(AND(B7="Home Loan",B2<=7500000),80%,IF(AND(B7="Home Loan",B2>7500000),75%)))))))) -> 0.9
A58: Loan Eligibility - Based on Property Value | B58: =B56*B57 -> 0
A60: Eligibility | B60: =IF(B54="Case Not Eligible","Case Not Eligible",IF(B58=0,MIN(B54,B2),MIN(B54,B58,B2))) -> Case Not Eligible
A61: EMI | B61: =IF(B60="Case Not Eligible","Case Not Eligible",PMT(B3/12,B4,-B60)) -> Case Not Eligible
A63: FOIR on the Amount Applied | B63: =IFERROR(SUM(PMT(B3/12,B4,-B2),B52)/B50,0) -> 0
A64: LTV on the Amount Applied | B64: =IFERROR(B2/B56,0) -> 0
A66: FOIR Deviation / Delegation | B66: =IF(B63-B51>0%,"Deviation Approval Required","Within Policy Norms") -> Within Policy Norms
A67: LTV Deviation / Delegation | B67: =IF(B7="Home Loan","Deviation not allowed on LTV",IF((B64-B57)<=0%,"Within Policy Norms",IF(B7="LAP-Resi (Vacant)","Deviation Approval Required",IF(B7="LAP-Comm (Vacant)","Deviation Approval Required",IF((B64-B57)<=2.5%,"Deviation Approval Required",IF((B64-B57)<=5%,"Deviation Approval Required","Deviation Approval Required")))))) -> Deviation not allowed on LTV

Sheet ApplicantSalary
A1: Name:
A2: Employer Name:
A3: Designation:
A4: Date of Joining: | C4: Total Experience (Years):
B6: Rs.
A7: Component | B7: 45261 | C7: 45292 | D7: 45323 | E7: Standard Amount for calculation | F7: % to be considered | G7: Eligible Amount (Rs.)
A8: Basic | G8: =E8*F8 -> 0
A9: DA | G9: =E9*F9 -> 0
A10: HRA | G10: =E10*F10 -> 0
A11: Other Allowances | G11: =E11*F11 -> 0
A12: Variable Pay | G12: =E12*F12 -> 0
A13: Bonus | G13: =E13*F13 -> 0
A14: Arrears / Others | G14: =E14*F14 -> 0
A15: Gross Salary | B15: =SUM(B8:B14) -> 0 | C15: =SUM(C8:C14) -> 0 | D15: =SUM(D8:D14) -> 0 | E15: =SUM(E8:E14) -> 0 | G15: =SUM(G8:G14) -> 0
A16: Deductions:
A17: - PF | G17: =E17*F17 -> 0
A18: - Profession Tax | G18: =E18*F18 -> 0
A19: - Income Tax (TDS) | G19: =E19*F19 -> 0
A20: - Loan Deduction | G20: =E20*F20 -> 0
A21: - ESI / Other Deductions | G21: =E21*F21 -> 0
A22: Total Deductions | B22: =SUM(B17:B21) -> 0 | C22: =SUM(C17:C21) -> 0 | D22: =SUM(D17:D21) -> 0 | E22: =SUM(E17:E21) -> 0 | G22: =SUM(G17:G21) -> 0
A23: Net Salary | B23: =B15-B22 -> 0 | C23: =C15-C22 -> 0 | D23: =D15-D22 -> 0 | E23: =E15-E22 -> 0 | G23: =G15-G22 -> 0
A26: Annual Components (if excluded from above) | B26: Latest Year | C26: Previous Year | F26: % to be considered | G26: Eligible Amount (Rs.)
A27: Fixed Bonus | G27: =B27*F27 -> 0
A28: Performance Linked Bonus | G28: =B28*F28 -> 0
A29: LTA | G29: =B29*F29 -> 0
A32: Form 16 Part B Details, if any | G32: Latest Year
A33: Gross Salary as per Form 16
A34: Tax Deducted as per Form 16
A35: Net Salary as per Form 16
A36: Net Salary p.m. (as per Form 16) | G36: =G35/12 -> 0
A39: Salary, Bonus / Incentive, Reimbursement, or other credits from Employer
A41: Month | B41: Date | C41: Amount (Rs.) | D41: Remarks, if any
A42: 45170 | B42: 45171 | D42: SALARY REFLECTED IN BANK
A43: 45200 | B43: 45198 | D43: SALARY REFLECTED IN BANK
A44: 45231 | B44: 45231 | D44: SALARY REFLECTED IN BANK
A45: 45261 | B45: 45261 | D45: SALARY REFLECTED IN BANK
A46: 45292 | B46: 45292 | D46: SALARY REFLECTED IN BANK
A47: 45323 | B47: 45323 | D47: SALARY REFLECTED IN BANK

Sheet Co-app1Salary
A1: Name:
A2: Employer Name:
A3: Designation:
A4: Date of Joining: | C4: Total Experience (Years):
B6: Rs.
A7: Component | B7: 45231 | C7: 45261 | D7: 45292 | E7: Standard Amount for calculation | F7: % to be considered | G7: Eligible Amount (Rs.)
A8: Basic | G8: =E8*F8 -> 0
A9: DA | G9: =E9*F9 -> 0
A10: HRA | G10: =E10*F10 -> 0
A11: Other Allowances | G11: =E11*F11 -> 0
A12: Variable Pay | G12: =E12*F12 -> 0
A13: Bonus | G13: =E13*F13 -> 0
A14: Arrears / Others | G14: =E14*F14 -> 0
A15: Gross Salary | B15: =SUM(B8:B14) -> 0 | C15: =SUM(C8:C14) -> 0 | D15: =SUM(D8:D14) -> 0 | E15: =SUM(E8:E14) -> 0 | G15: =SUM(G8:G14) -> 0
A16: Deductions:
A17: - PF | G17: =E17*F17 -> 0
A18: - Profession Tax | G18: =E18*F18 -> 0
A19: - Income Tax (TDS) | G19: =E19*F19 -> 0
A20: - Loan Deduction | G20: =E20*F20 -> 0
A21: - ESI / Other Deductions | G21: =E21*F21 -> 0
A22: Total Deductions | B22: =SUM(B17:B21) -> 0 | C22: =SUM(C17:C21) -> 0 | D22: =SUM(D17:D21) -> 0 | E22: =SUM(E17:E21) -> 0 | G22: =SUM(G17:G21) -> 0
A23: Net Salary | B23: =B15-B22 -> 0 | C23: =C15-C22 -> 0 | D23: =D15-D22 -> 0 | E23: =E15-E22 -> 0 | G23: =G15-G22 -> 0
A26: Annual Components (if excluded from above) | B26: Latest Year | C26: Previous Year | F26: % to be considered | G26: Eligible Amount (Rs.)
A27: Fixed Bonus | G27: =B27*F27 -> 0
A28: Performance Linked Bonus | G28: =B28*F28 -> 0
A29: LTA | G29: =B29*F29 -> 0
A32: Form 16 Part B Details, if any | G32: Latest Year
A33: Gross Salary as per Form 16
A34: Tax Deducted as per Form 16
A35: Net Salary as per Form 16
A36: Net Salary p.m. (as per Form 16) | G36: =G35/12 -> 0
A39: Salary, Bonus / Incentive, Reimbursement, or other credits from Employer
A41: Month | B41: Date | C41: Amount (Rs.) | D41: Remarks, if any
A42: 45170 | B42: 45175 | D42: SALARY REFLECTED IN BANK
A43: 45200 | B43: 45202 | D43: SALARY REFLECTED IN BANK
A44: 45231 | B44: 45233 | D44: SALARY REFLECTED IN BANK
A45: 45261 | B45: 45263 | D45: SALARY REFLECTED IN BANK
A46: 45292 | B46: 45294 | D46: SALARY REFLECTED IN BANK
A47: 45323 | B47: 45325 | D47: SALARY REFLECTED IN BANK

Sheet Co-app2Salary
A1: Name:
A2: Employer Name:
A3: Designation:
A4: Date of Joining: | B4: 43709 | C4: Total Experience (Years):
B6: Rs.
A7: Component | B7: Latest Month | C7: Previous Month | D7: Previous to previous month | E7: Standard Amount for calculation | F7: % to be considered | G7: Eligible Amount (Rs.)
A8: Basic | G8: =E8*F8 -> 0
A9: DA | G9: =E9*F9 -> 0
A10: HRA | G10: =E10*F10 -> 0
A11: Other Allowances | G11: =E11*F11 -> 0
A12: Variable Pay | G12: =E12*F12 -> 0
A13: Bonus | G13: =E13*F13 -> 0
A14: Arrears / Others | G14: =E14*F14 -> 0
A15: Gross Salary | B15: =SUM(B8:B14) -> 0 | C15: =SUM(C8:C14) -> 0 | D15: =SUM(D8:D14) -> 0 | E15: =SUM(E8:E14) -> 0 | G15: =SUM(G8:G14) -> 0
A16: Deductions:
A17: - PF | G17: =E17*F17 -> 0
A18: - Profession Tax | G18: =E18*F18 -> 0
A19: - Income Tax (TDS) | G19: =E19*F19 -> 0
A20: - Loan Deduction | G20: =E20*F20 -> 0
A21: - ESI / Other Deductions | G21: =E21*F21 -> 0
A22: Total Deductions | B22: =SUM(B17:B21) -> 0 | C22: =SUM(C17:C21) -> 0 | D22: =SUM(D17:D21) -> 0 | E22: =SUM(E17:E21) -> 0 | G22: =SUM(G17:G21) -> 0
A23: Net Salary | B23: =B15-B22 -> 0 | C23: =C15-C22 -> 0 | D23: =D15-D22 -> 0 | E23: =E15-E22 -> 0 | G23: =G15-G22 -> 0
A26: Annual Components (if excluded from above) | B26: Latest Year | C26: Previous Year | F26: % to be considered | G26: Eligible Amount (Rs.)
A27: Fixed Bonus | G27: =B27*F27 -> 0
A28: Performance Linked Bonus | G28: =B28*F28 -> 0
A29: LTA | G29: =B29*F29 -> 0
A32: Form 16 Part B Details, if any | G32: Latest Year
A33: Gross Salary as per Form 16
A34: Tax Deducted as per Form 16
A35: Net Salary as per Form 16
A36: Net Salary p.m. (as per Form 16) | G36: =G35/12 -> 0
A39: Salary, Bonus / Incentive, Reimbursement, or other credits from Employer
A41: Month | B41: Date | C41: Amount (Rs.) | D41: Remarks, if any

Sheet Co-app3Salary
A1: Name:
A2: Employer Name:
A3: Designation:
A4: Date of Joining: | B4: 43709 | C4: Total Experience (Years):
B6: Rs.
A7: Component | B7: Latest Month | C7: Previous Month | D7: Previous to previous month | E7: Standard Amount for calculation | F7: % to be considered | G7: Eligible Amount (Rs.)
A8: Basic | G8: =E8*F8 -> 0
A9: DA | G9: =E9*F9 -> 0
A10: HRA | G10: =E10*F10 -> 0
A11: Other Allowances | G11: =E11*F11 -> 0
A12: Variable Pay | G12: =E12*F12 -> 0
A13: Bonus | G13: =E13*F13 -> 0
A14: Arrears / Others | G14: =E14*F14 -> 0
A15: Gross Salary | B15: =SUM(B8:B14) -> 0 | C15: =SUM(C8:C14) -> 0 | D15: =SUM(D8:D14) -> 0 | E15: =SUM(E8:E14) -> 0 | G15: =SUM(G8:G14) -> 0
A16: Deductions:
A17: - PF | G17: =E17*F17 -> 0
A18: - Profession Tax | G18: =E18*F18 -> 0
A19: - Income Tax (TDS) | G19: =E19*F19 -> 0
A20: - Loan Deduction | G20: =E20*F20 -> 0
A21: - ESI / Other Deductions | G21: =E21*F21 -> 0
A22: Total Deductions | B22: =SUM(B17:B21) -> 0 | C22: =SUM(C17:C21) -> 0 | D22: =SUM(D17:D21) -> 0 | E22: =SUM(E17:E21) -> 0 | G22: =SUM(G17:G21) -> 0
A23: Net Salary | B23: =B15-B22 -> 0 | C23: =C15-C22 -> 0 | D23: =D15-D22 -> 0 | E23: =E15-E22 -> 0 | G23: =G15-G22 -> 0
A26: Annual Components (if excluded from above) | B26: Latest Year | C26: Previous Year | F26: % to be considered | G26: Eligible Amount (Rs.)
A27: Fixed Bonus | G27: =B27*F27 -> 0
A28: Performance Linked Bonus | G28: =B28*F28 -> 0
A29: LTA | G29: =B29*F29 -> 0
A32: Form 16 Part B Details, if any | G32: Latest Year
A33: Gross Salary as per Form 16
A34: Tax Deducted as per Form 16
A35: Net Salary as per Form 16
A36: Net Salary p.m. (as per Form 16) | G36: =G35/12 -> 0
A39: Salary, Bonus / Incentive, Reimbursement, or other credits from Employer
A41: Month | B41: Date | C41: Amount (Rs.) | D41: Remarks, if any

Sheet A3SP&L
A1: Parameter Code | B1: Parameter_Desc | C1: =E1-2 -> 2022 | D1: =E1-1 -> 2023 | E1: =IF(BasicInput!C1="Prime",IF(Prime1!B7="",2020,Prime1!B7),IF(Afford1!B7="",2020,Afford1!B7)) -> 2024 | F1: =E1+1 -> 2025 | G1: =E1+2 -> 2026
A2: GRDOMSAL | B2: Gross Domestic Sales | C2: =IF(BasicInput!$C$1="Prime",PrimeConsolidated!E8,AffordConsolidated!E9)*100000+'44AD,44ADA,44AEIncome'!D116 -> 0 | D2: =IF(BasicInput!$C$1="Prime",PrimeConsolidated!D8,AffordConsolidated!D9)*100000+'44AD,44ADA,44AEIncome'!C116 -> 0 | E2: =IF(BasicInput!$C$1="Prime",PrimeConsolidated!C8,AffordConsolidated!C9)*100000+'44AD,44ADA,44AEIncome'!B116 -> 0 | F2: 0 | G2: 0
A3: EXPSAL | B3: Export Sales | C3: =PrimeConsolidated!E9*100000 -> 0 | D3: =PrimeConsolidated!D9*100000 -> 0 | E3: =PrimeConsolidated!C9*100000 -> 0 | F3: 0 | G3: 0
A4: LESEXCDUT | B4: LESS: Excise duty | C4: =AffordConsolidated!E10*100000 -> 0 | D4: =AffordConsolidated!D10*100000 -> 0 | E4: =AffordConsolidated!C10*100000 -> 0 | F4: 0 | G4: 0
A5: TRDOPRINC | B5: ADD: Trading / Other Operating Income | C5: =IF(BasicInput!$C$1="Prime",SUM(PrimeConsolidated!E10:E19),AffordConsolidated!E12)*100000 -> 0 | D5: =IF(BasicInput!$C$1="Prime",SUM(PrimeConsolidated!D10:D19),AffordConsolidated!D12)*100000 -> 0 | E5: =IF(BasicInput!$C$1="Prime",SUM(PrimeConsolidated!C10:C19),AffordConsolidated!C12)*100000 -> 0 | F5: 0 | G5: 0
A6: EXPINC | B6: Export Incentives | C6: 0 | D6: 0 | E6: 0 | F6: 0 | G6: 0
A7: DUDRAW | B7: Duty Drawback | C7: 0 | D7: 0 | E7: 0 | F7: 0 | G7: 0
A8: OTHER | B8: Others | C8: 0 | D8: 0 | E8: 0 | F8: 0 | G8: 0
A9: IMPORTD | B9: Imported | C9: 0 | D9: 0 | E9: 0 | F9: 0 | G9: 0
A10: INDIGENOUS | B10: Indigenous | C10: 0 | D10: 0 | E10: 0 | F10: 0 | G10: 0
A11: IMPORTED_1 | B11: Imported | C11: 0 | D11: 0 | E11: 0 | F11: 0 | G11: 0
A12: INDIGENOS1 | B12: Indigenous | C12: 0 | D12: 0 | E12: 0 | F12: 0 | G12: 0
A13: POWFUEL | B13: POWER & FUEL | C13: 0 | D13: 0 | E13: 0 | F13: 0 | G13: 0
A14: DIRLABOUR | B14: DIRECT LABOUR | C14: =PrimeConsolidated!E28*100000 -> 0 | D14: =PrimeConsolidated!D28*100000 -> 0 | E14: =PrimeConsolidated!C28*100000 -> 0 | F14: 0 | G14: 0
A15: OTHMANEXP | B15: OTHER MANUFACTURING EXPENSES | C15: =IF(BasicInput!$C$1="Prime",PrimeConsolidated!E25,AffordConsolidated!E16)*100000 -> 0 | D15: =IF(BasicInput!$C$1="Prime",PrimeConsolidated!D25,AffordConsolidated!D16)*100000 -> 0 | E15: =IF(BasicInput!$C$1="Prime",PrimeConsolidated!C25,AffordConsolidated!C16)*100000 -> 0 | F15: 0 | G15: 0
A16: DEPRECIA | B16: DEPRECIATION | C16: =IF(BasicInput!$C$1="Prime",PrimeConsolidated!E32,AffordConsolidated!E23)*100000 -> 0 | D16: =IF(BasicInput!$C$1="Prime",PrimeConsolidated!D32,AffordConsolidated!D23)*100000 -> 0 | E16: =IF(BasicInput!$C$1="Prime",PrimeConsolidated!C32,AffordConsolidated!C23)*100000 -> 0 | F16: 0 | G16: 0
A17: REPMAINT | B17: REPAIRS & MAINTENANCE | C17: 0 | D17: 0 | E17: 0 | F17: 0 | G17: 0
A18: COSTTRDGDS | B18: COST OF TRADING GOODS | C18: =IF(BasicInput!$C$1="Prime",PrimeConsolidated!E21,AffordConsolidated!E15)*100000 -> 0 | D18: =IF(BasicInput!$C$1="Prime",PrimeConsolidated!D21,AffordConsolidated!D15)*100000 -> 0 | E18: =IF(BasicInput!$C$1="Prime",PrimeConsolidated!C21,AffordConsolidated!C15)*100000 -> 0 | F18: 0 | G18: 0
A19: ADOPSTKPRC | B19: ADD: OPENING STOCK IN PROCESS | C19: 0 | D19: 0 | E19: 0 | F19: 0 | G19: 0
A20: DEDCLSTKPR | B20: DEDUCT: CLOSING STOCK IN PROCESS | C20: 0 | D20: 0 | E20: 0 | F20: 0 | G20: 0
A21: ADDOPFIGD | B21: ADD: OPENING STOCK OF FINISHED GOODS | C21: 0 | D21: 0 | E21: 0 | F21: 0 | G21: 0
A22: DEDCLSTFIG | B22: DEDUCT: CLOSING STOCK OF FINISHED GOODS | C22: 0 | D22: 0 | E22: 0 | F22: 0 | G22: 0
A23: SGADMEXP | B23: SELLING, GENERAL & ADM EXPENSES | C23: =IF(BasicInput!$C$1="Prime",SUM(PrimeConsolidated!E29:E30),AffordConsolidated!E19)*100000+'44AD,44ADA,44AEIncome'!D120 -> 0 | D23: =IF(BasicInput!$C$1="Prime",SUM(PrimeConsolidated!D29:D30),AffordConsolidated!D19)*100000+'44AD,44ADA,44AEIncome'!C120 -> 0 | E23: =IF(BasicInput!$C$1="Prime",SUM(PrimeConsolidated!C29:C30),AffordConsolidated!C19)*100000+'44AD,44ADA,44AEIncome'!B120 -> 0 | F23: 0 | G23: 0
A24: INTWC | B24: Interest - WC | C24: =PrimeConsolidated!E37*100000 -> 0 | D24: =PrimeConsolidated!D37*100000 -> 0 | E24: =PrimeConsolidated!C37*100000 -> 0 | F24: 0 | G24: 0
A25: INTTRMLN | B25: Interest - Term Loans | C25: =IF(BasicInput!$C$1="Prime",PrimeConsolidated!E38,AffordConsolidated!E25)*100000 -> 0 | D25: =IF(BasicInput!$C$1="Prime",PrimeConsolidated!D38,AffordConsolidated!D25)*100000 -> 0 | E25: =IF(BasicInput!$C$1="Prime",PrimeConsolidated!C38,AffordConsolidated!C25)*100000 -> 0 | F25: 0 | G25: 0
A26: INTEWC1 | B26: Interest - WC | C26: 0 | D26: 0 | E26: 0 | F26: 0 | G26: 0
A27: INTETRMLN1 | B27: Interest - Term Loans | C27: =PrimeConsolidated!E40*100000 -> 0 | D27: =PrimeConsolidated!D40*100000 -> 0 | E27: =PrimeConsolidated!C40*100000 -> 0 | F27: 0 | G27: 0
A28: BNKCHG | B28: Bank Charges | C28: 0 | D28: 0 | E28: 0 | F28: 0 | G28: 0
A29: INTDEPDIV | B29: (I) Interest On Deposits & Dividend Received | C29: 0 | D29: 0 | E29: 0 | F29: 0 | G29: 0
A30: FORXGAIN | B30: (II) Forex Gains | C30: 0 | D30: 0 | E30: 0 | F30: 0 | G30: 0
A31: NOOPINCSB | B31: (III) Non Operating Income from Subsidiaries | C31: 0 | D31: 0 | E31: 0 | F31: 0 | G31: 0
A32: TXRFND | B32: (IV) Tax Refund | C32: 0 | D32: 0 | E32: 0 | F32: 0 | G32: 0
A33: MISCINC | B33: (V) Misc Income | C33: 0 | D33: 0 | E33: 0 | F33: 0 | G33: 0
A34: PFSALASINV | B34: (VI) Profit on sale of assets & Investments | C34: 0 | D34: 0 | E34: 0 | F34: 0 | G34: 0
A35: OTHINC1 | B35: Other Income | C35: =IF(BasicInput!$C$1="Prime",PrimeConsolidated!E27,AffordConsolidated!E27)*100000 -> 0 | D35: =IF(BasicInput!$C$1="Prime",PrimeConsolidated!D27,AffordConsolidated!D27)*100000 -> 0 | E35: =IF(BasicInput!$C$1="Prime",PrimeConsolidated!C27,AffordConsolidated!C27)*100000 -> 0 | F35: 0 | G35: 0
A36: PRVEXPWRT | B36: (I) Provisions / Expenses Written Back | C36: 0 | D36: 0 | E36: 0 | F36: 0 | G36: 0
A37: LOSSALINV | B37: (I) Loss on sale of Investments | C37: 0 | D37: 0 | E37: 0 | F37: 0 | G37: 0
A38: LOSSALFA | B38: (II) Loss on sale of FA | C38: 0 | D38: 0 | E38: 0 | F38: 0 | G38: 0
A39: DERLOSBKD | B39: (III) Derivative Losses booked | C39: 0 | D39: 0 | E39: 0 | F39: 0 | G39: 0
A40: PREXPWRTOF | B40: (I) Preli.Exp / One Time Expenses Written Off | C40: =PrimeConsolidated!E34*100000 -> 0 | D40: =PrimeConsolidated!D34*100000 -> 0 | E40: =PrimeConsolidated!C34*100000 -> 0 | F40: 0 | G40: 0
A41: MSCEXPWRTF | B41: (II) Misc Exp. Written Off | C41: =IF(BasicInput!$C$1="Prime",PrimeConsolidated!E35,AffordConsolidated!E28)*100000 -> 0 | D41: =IF(BasicInput!$C$1="Prime",PrimeConsolidated!D35,AffordConsolidated!D28)*100000 -> 0 | E41: =IF(BasicInput!$C$1="Prime",PrimeConsolidated!C35,AffordConsolidated!C28)*100000 -> 0 | F41: 0 | G41: 0
A42: PRVDBTINV | B42: (III) Prov. for doub.debts & Dim.in the val. of Inv. | C42: =PrimeConsolidated!E33*100000 -> 0 | D42: =PrimeConsolidated!D33*100000 -> 0 | E42: =PrimeConsolidated!C33*100000 -> 0 | F42: 0 | G42: 0
A43: WLTHTX | B43: (IV) Wealth Tax | C43: 0 | D43: 0 | E43: 0 | F43: 0 | G43: 0
A44: TAXPAID | B44: TAX PAID | C44: =IF(BasicInput!$C$1="Prime",PrimeConsolidated!E43,AffordConsolidated!E30)*100000+'44AD,44ADA,44AEIncome'!D118 -> 0 | D44: =IF(BasicInput!$C$1="Prime",PrimeConsolidated!D43,AffordConsolidated!D30)*100000+'44AD,44ADA,44AEIncome'!C118 -> 0 | E44: =IF(BasicInput!$C$1="Prime",PrimeConsolidated!C43,AffordConsolidated!C30)*100000+'44AD,44ADA,44AEIncome'!B118 -> 0 | F44: 0 | G44: 0
A45: PRVTXCURR | B45: PROVISION FOR TAXES - Current Period | C45: 0 | D45: 0 | E45: 0 | F45: 0 | G45: 0
A46: DEFRDTX | B46: - Deffered Taxes | C46: 0 | D46: 0 | E46: 0 | F46: 0 | G46: 0
A47: EXTINCADJP | B47: Extraordinary Income adjustments (+) | C47: 0 | D47: 0 | E47: 0 | F47: 0 | G47: 0
A48: EXTINCADJM | B48: Extraordinary Expenses adjustments (-) | C48: 0 | D48: 0 | E48: 0 | F48: 0 | G48: 0
A49: EQTDVPDAMT | B49: EQUITY DIVIDEND PAID (I) AMOUNT | C49: =IF(BasicInput!$C$1="Prime",PrimeConsolidated!E45,AffordConsolidated!E33)*100000 -> 0 | D49: =IF(BasicInput!$C$1="Prime",PrimeConsolidated!D45,AffordConsolidated!D33)*100000 -> 0 | E49: =IF(BasicInput!$C$1="Prime",PrimeConsolidated!C45,AffordConsolidated!C33)*100000 -> 0 | F49: 0 | G49: 0
A50: RATE | B50: II RATE | C50: =PrimeConsolidated!E46*100000 -> 0 | D50: =PrimeConsolidated!D46*100000 -> 0 | E50: =PrimeConsolidated!C46*100000 -> 0 | F50: 0 | G50: 0
A51: DIVTAX | B51: Dividend tax | C51: 0 | D51: 0 | E51: 0 | F51: 0 | G51: 0
A52: PRNTWTDRW | B52: Partners withdrawal | C52: =IF(BasicInput!$C$1="Prime",(PrimeConsolidated!E39+PrimeConsolidated!E41),(AffordConsolidated!E34+AffordConsolidated!E35))*100000 -> 0 | D52: =IF(BasicInput!$C$1="Prime",(PrimeConsolidated!D39+PrimeConsolidated!D41),(AffordConsolidated!D34+AffordConsolidated!D35))*100000 -> 0 | E52: =IF(BasicInput!$C$1="Prime",(PrimeConsolidated!C39+PrimeConsolidated!C41),(AffordConsolidated!C34+AffordConsolidated!C35))*100000 -> 0 | F52: 0 | G52: 0
A53: DIVPRF | B53: Dividend -Preference | C53: 0 | D53: 0 | E53: 0 | F53: 0 | G53: 0

Sheet A3SBalSheet
A1: Parameter Code | B1: Parameter_Desc | C1: =E1-2 -> 2022 | D1: =E1-1 -> 2023 | E1: =IF(BasicInput!C1="Prime",IF(Prime1!B7="",2020,Prime1!B7),IF(Afford1!B7="",2020,Afford1!B7)) -> 2024 | F1: =E1+1 -> 2025 | G1: =E1+2 -> 2026
A2: SHTRMBORAB | B2: (i)Short term Borrowings from applicant bank (CC / WCDL) | C2: =IF(BasicInput!C1="Prime",PrimeConsolidated!E86,AffordConsolidated!E58)*100000 -> 0 | D2: =IF(BasicInput!C1="Prime",PrimeConsolidated!D86,AffordConsolidated!D58)*100000 -> 0 | E2: =IF(BasicInput!C1="Prime",PrimeConsolidated!C86,AffordConsolidated!C58)*100000 -> 0 | F2: 0 | G2: 0
A3: SHTRMBOROB | B3: (ii)Short term Borrowingsfrom other banks | C3: =PrimeConsolidated!E87*100000 -> 0 | D3: =PrimeConsolidated!D87*100000 -> 0 | E3: =PrimeConsolidated!C87*100000 -> 0 | F3: 0 | G3: 0
A4: SHTRMBOR12 | B4: Short term Borrowings(of (i) and (ii) in which Bill purchased & disc.) | C4: 0 | D4: 0 | E4: 0 | F4: 0 | G4: 0
A5: SUNDRYCRD | B5: Sundry Creditors (Trade) | C5: =IF(BasicInput!C1="Prime",PrimeConsolidated!E80,AffordConsolidated!E57)*100000 -> 0 | D5: =IF(BasicInput!C1="Prime",PrimeConsolidated!D80,AffordConsolidated!D57)*100000 -> 0 | E5: =IF(BasicInput!C1="Prime",PrimeConsolidated!C80,AffordConsolidated!C57)*100000 -> 0 | F5: 0 | G5: 0
A6: SHTRMBORAG | B6: Short term borrowings from Associates & Group Concerns | C6: =AffordConsolidated!E56*100000 -> 0 | D6: =AffordConsolidated!D56*100000 -> 0 | E6: =AffordConsolidated!C56*100000 -> 0 | F6: 0 | G6: 0
A7: SHTRMBORCP | B7: Short Term borrowings / Commercial Paper | C7: 0 | D7: 0 | E7: 0 | F7: 0 | G7: 0
A8: SHTRMBORO | B8: Short term borrowings from Others | C8: =PrimeConsolidated!E88*100000 -> 0 | D8: =PrimeConsolidated!D88*100000 -> 0 | E8: =PrimeConsolidated!C88*100000 -> 0 | F8: 0 | G8: 0
A9: ADVPCDPDL | B9: Advances/ payments from customers/deposits from dealers. | C9: =PrimeConsolidated!E81*100000 -> 0 | D9: =PrimeConsolidated!D81*100000 -> 0 | E9: =PrimeConsolidated!C81*100000 -> 0 | F9: 0 | G9: 0
A10: PRVFORTAX | B10: Provision for taxation | C10: 0 | D10: 0 | E10: 0 | F10: 0 | G10: 0
A11: PROPDVD | B11: Proposed dividend | C11: 0 | D11: 0 | E11: 0 | F11: 0 | G11: 0
A12: OTHSTALIAB | B12: Other Statutory Liabilities( Due within One Year) | C12: 0 | D12: 0 | E12: 0 | F12: 0 | G12: 0
A13: INSTTRMLNS | B13: Installments of Term loans / Debentures / DPGs etc. (due within 1 year) | C13: =AffordConsolidated!E51 -> 0 | D13: =AffordConsolidated!D51 -> 0 | E13: =AffordConsolidated!C51 -> 0 | F13: 0 | G13: 0
A14: DEPDUEREP | B14: Deposits due for repayment (due within 1 year) | C14: 0 | D14: 0 | E14: 0 | F14: 0 | G14: 0
A15: PREFSHAR | B15: Preference Shares redeemable (within 1 year) | C15: 0 | D15: 0 | E15: 0 | F15: 0 | G15: 0
A16: OTHCURLIA1 | B16: Other Current liabilities & provisions (due within 1 year) | C16: =IF(BasicInput!C1="Prime",PrimeConsolidated!E83,AffordConsolidated!E59)*100000 -> 0 | D16: =IF(BasicInput!C1="Prime",PrimeConsolidated!D83,AffordConsolidated!D59)*100000 -> 0 | E16: =IF(BasicInput!C1="Prime",PrimeConsolidated!C83,AffordConsolidated!C59)*100000 -> 0 | F16: 0 | G16: 0
A17: INTACCNTDU | B17: Interest acc but not due | C17: 0 | D17: 0 | E17: 0 | F17: 0 | G17: 0
A18: PRVNPA | B18: Provision for NPA | C18: 0 | D18: 0 | E18: 0 | F18: 0 | G18: 0
A19: PRVENCASHGT | B19: Provision for leave encashment & gratuity | C19: 0 | D19: 0 | E19: 0 | F19: 0 | G19: 0
A20: UNCLMDVD | B20: Unclaimed dividend | C20: 0 | D20: 0 | E20: 0 | F20: 0 | G20: 0
A21: OTHLIAB | B21: Other Liabilities | C21: =IF(BasicInput!C1="Prime",PrimeConsolidated!E82,AffordConsolidated!E60)*100000 -> 0 | D21: =IF(BasicInput!C1="Prime",PrimeConsolidated!D82,AffordConsolidated!D60)*100000 -> 0 | E21: =IF(BasicInput!C1="Prime",PrimeConsolidated!C82,AffordConsolidated!C60)*100000 -> 0 | F21: 0 | G21: 0
A22: DUESUBAFF | B22: Due to Subsidiary companies/ affiliates | C22: 0 | D22: 0 | E22: 0 | F22: 0 | G22: 0
A23: TAXINTDVDP | B23: Tax on Interim Dividend Payable | C23: 0 | D23: 0 | E23: 0 | F23: 0 | G23: 0
A24: WTCL | B24: WCTL | C24: 0 | D24: 0 | E24: 0 | F24: 0 | G24: 0
A25: PREFSHR1 | B25: Pref. Shares (portion redeemable after 1 Yr) | C25: 0 | D25: 0 | E25: 0 | F25: 0 | G25: 0
A26: TRMLNEX1 | B26: Term Loans (Excluding installments payable within one year) | C26: =AffordConsolidated!E52 -> 0 | D26: =AffordConsolidated!D52 -> 0 | E26: =AffordConsolidated!C52 -> 0 | F26: 0 | G26: 0
A27: TRMLNFIS | B27: Term Loans - From Fis | C27: =IF(BasicInput!C1="Prime",PrimeConsolidated!E60,AffordConsolidated!E53)*100000 -> 0 | D27: =IF(BasicInput!C1="Prime",PrimeConsolidated!D60,AffordConsolidated!D53)*100000 -> 0 | E27: =IF(BasicInput!C1="Prime",PrimeConsolidated!C60,AffordConsolidated!C53)*100000 -> 0 | F27: 0 | G27: 0
A28: DEBENTRS | B28: Debentures | C28: 0 | D28: 0 | E28: 0 | F28: 0 | G28: 0
A29: TERMDEP | B29: Term deposits | C29: 0 | D29: 0 | E29: 0 | F29: 0 | G29: 0
A30: UNSECLNS | B30: Unsecured loans | C30: =PrimeConsolidated!E61*100000 -> 0 | D30: =PrimeConsolidated!D61*100000 -> 0 | E30: =PrimeConsolidated!C61*100000 -> 0 | F30: 0 | G30: 0
A31: BORSSUBAFI | B31: Borrowings from subsidiaries / affiliates (Quasi Equity) | C31: =IF(BasicInput!C1="Prime",PrimeConsolidated!E57,AffordConsolidated!E50+AffordConsolidated!E42)*100000 -> 0 | D31: =IF(BasicInput!C1="Prime",PrimeConsolidated!D57,AffordConsolidated!D50+AffordConsolidated!D42)*100000 -> 0 | E31: =IF(BasicInput!C1="Prime",PrimeConsolidated!C57,AffordConsolidated!C50+AffordConsolidated!C42)*100000 -> 0 | F31: 0 | G31: 0
A32: DEPDEALERS | B32: Deposit from Dealers (only if considered as available for long term) | C32: 0 | D32: 0 | E32: 0 | F32: 0 | G32: 0
A33: OTHTRMLIA | B33: Other term liabilities | C33: 0 | D33: 0 | E33: 0 | F33: 0 | G33: 0
A34: DEFRTXLIA | B34: Deferred Tax Liability | C34: 0 | D34: 0 | E34: 0 | F34: 0 | G34: 0
A35: INTCORPLN | B35: Inter Corporate Loan | C35: 0 | D35: 0 | E35: 0 | F35: 0 | G35: 0
A36: OTHLNADV | B36: Other Loan & Advances | C36: 0 | D36: 0 | E36: 0 | F36: 0 | G36: 0
A37: PRPROCAP | B37: Partners capital / Proprietors capital | C37: =PrimeConsolidated!E53*100000 -> 0 | D37: =PrimeConsolidated!D53*100000 -> 0 | E37: =PrimeConsolidated!C53*100000 -> 0 | F37: 0 | G37: 0
A38: SHARECAP | B38: Share Capital (Paid-up) | C38: =IF(BasicInput!C1="Prime",PrimeConsolidated!E52,AffordConsolidated!E41)*100000 -> 0 | D38: =IF(BasicInput!C1="Prime",PrimeConsolidated!D52,AffordConsolidated!D41)*100000 -> 0 | E38: =IF(BasicInput!C1="Prime",PrimeConsolidated!C52,AffordConsolidated!C41)*100000 -> 0 | F38: 0 | G38: 0
A39: SHAREAPP | B39: Share Application (finalized for allotment) | C39: 0 | D39: 0 | E39: 0 | F39: 0 | G39: 0
A40: SACR | B40: Statutory and Capital Reserves | C40: 0 | D40: 0 | E40: 0 | F40: 0 | G40: 0
A41: GENRESERV | B41: General Reserve | C41: =IF(BasicInput!C1="Prime",PrimeConsolidated!E54,AffordConsolidated!E43)*100000 -> 0 | D41: =IF(BasicInput!C1="Prime",PrimeConsolidated!D54,AffordConsolidated!D43)*100000 -> 0 | E41: =IF(BasicInput!C1="Prime",PrimeConsolidated!C54,AffordConsolidated!C43)*100000 -> 0 | F41: 0 | G41: 0
A42: REVALRESRV | B42: Revaluation Reserve | C42: =AffordConsolidated!E45*100000 -> 0 | D42: =AffordConsolidated!D45*100000 -> 0 | E42: =AffordConsolidated!C45*100000 -> 0 | F42: 0 | G42: 0
A43: OTHRESERV | B43: Other Reserves ( Excluding provisions) | C43: =AffordConsolidated!E46*100000 -> 0 | D43: =AffordConsolidated!D46*100000 -> 0 | E43: =AffordConsolidated!C46*100000 -> 0 | F43: 0 | G43: 0
A44: SDPNL | B44: Surplus (+) or deficit (-) in P & L Account | C44: 0 | D44: 0 | E44: 0 | F44: 0 | G44: 0
A45: SHAREPRM | B45: Share Premium A/c | C45: 0 | D45: 0 | E45: 0 | F45: 0 | G45: 0
A46: CAPSUBSDY | B46: Capital Subsidy | C46: 0 | D46: 0 | E46: 0 | F46: 0 | G46: 0
A47: IAUR | B47: Investment Allowance Utilization Reserve | C47: 0 | D47: 0 | E47: 0 | F47: 0 | G47: 0
A48: ARRCUMDVD | B48: Arrears of cumulative dividends | C48: 0 | D48: 0 | E48: 0 | F48: 0 | G48: 0
A49: DCISL | B49: Disputed excise / customs / Income tax / Sales tax Liabilities | C49: 0 | D49: 0 | E49: 0 | F49: 0 | G49: 0
A50: GRTLIANTPV | B50: Gratuity Liability not provided for | C50: 0 | D50: 0 | E50: 0 | F50: 0 | G50: 0
A51: GURANTISSB | B51: Guarantees issued (relating to business) | C51: 0 | D51: 0 | E51: 0 | F51: 0 | G51: 0
A52: GURANTISSC | B52: Guarantees issued (for group companies) | C52: 0 | D52: 0 | E52: 0 | F52: 0 | G52: 0
A53: LCS | B53: LCs | C53: 0 | D53: 0 | E53: 0 | F53: 0 | G53: 0
A54: ALLCONTLIA | B54: All other contingent liabilities -(incldg. Bills purchased - Under LC) | C54: 0 | D54: 0 | E54: 0 | F54: 0 | G54: 0
A55: CSHBANKBAL | B55: Cash and Bank Balances | C55: =IF(BasicInput!C1="Prime",PrimeConsolidated!E77,AffordConsolidated!E77)*100000 -> 0 | D55: =IF(BasicInput!C1="Prime",PrimeConsolidated!D77,AffordConsolidated!D77)*100000 -> 0 | E55: =IF(BasicInput!C1="Prime",PrimeConsolidated!C77,AffordConsolidated!C77)*100000 -> 0 | F55: 0 | G55: 0
A56: INVSTGOV | B56: Invst Govt. & other securities | C56: 0 | D56: 0 | E56: 0 | F56: 0 | G56: 0
A57: INVSTFIXD | B57: Invst Fixed deposits with banks | C57: 0 | D57: 0 | E57: 0 | F57: 0 | G57: 0
A58: INVSTOTHRS | B58: Invst Others | C58: =IF(BasicInput!C1="Prime",PrimeConsolidated!E66,AffordConsolidated!E70)*100000 -> 0 | D58: =IF(BasicInput!C1="Prime",PrimeConsolidated!D66,AffordConsolidated!D70)*100000 -> 0 | E58: =IF(BasicInput!C1="Prime",PrimeConsolidated!C66,AffordConsolidated!C70)*100000 -> 0 | F58: 0 | G58: 0
A59: RCVDEFEXP | B59: RECEIVABLES other than deferred & exports (Incl. bills purchased & discounted by banks) | C59: =IF(BasicInput!C1="Prime",PrimeConsolidated!E74,AffordConsolidated!E76)*100000 -> 0 | D59: =IF(BasicInput!C1="Prime",PrimeConsolidated!D74,AffordConsolidated!D76)*100000 -> 0 | E59: =IF(BasicInput!C1="Prime",PrimeConsolidated!C74,AffordConsolidated!C76)*100000 -> 0 | F59: 0 | G59: 0
A60: EXPREV | B60: Export Receivables (including bill purchased and discounted) | C60: 0 | D60: 0 | E60: 0 | F60: 0 | G60: 0
A61: RETMONDEP | B61: Retention Money / Security Deposit | C61: 0 | D61: 0 | E61: 0 | F61: 0 | G61: 0
A62: RAWINDIG | B62: Raw Material - Indigenous | C62: =PrimeConsolidated!E69*100000 -> 0 | D62: =PrimeConsolidated!D69*100000 -> 0 | E62: =PrimeConsolidated!C69*100000 -> 0 | F62: 0 | G62: 0
A63: RAWIMP | B63: Raw Material - Imported | C63: 0 | D63: 0 | E63: 0 | F63: 0 | G63: 0
A64: STKINPROC | B64: STOCK IN PROCESS | C64: =PrimeConsolidated!E71*100000 -> 0 | D64: =PrimeConsolidated!D71*100000 -> 0 | E64: =PrimeConsolidated!C71*100000 -> 0 | F64: 0 | G64: 0
A65: FINGOODS | B65: FINISHED GOODS | C65: =IF(BasicInput!C1="Prime",PrimeConsolidated!E72,AffordConsolidated!E73)*100000 -> 0 | D65: =IF(BasicInput!C1="Prime",PrimeConsolidated!D72,AffordConsolidated!D73)*100000 -> 0 | E65: =IF(BasicInput!C1="Prime",PrimeConsolidated!C72,AffordConsolidated!C73)*100000 -> 0 | F65: 0 | G65: 0
A66: OCSINDIG | B66: Other Consumable spares - Indigenous | C66: =PrimeConsolidated!E70*100000 -> 0 | D66: =PrimeConsolidated!D70*100000 -> 0 | E66: =PrimeConsolidated!C70*100000 -> 0 | F66: 0 | G66: 0
A67: OCSIMPORTD | B67: Other Consumable spares - Imported | C67: 0 | D67: 0 | E67: 0 | F67: 0 | G67: 0
A68: OTHSTKS | B68: Other stocks | C68: 0 | D68: 0 | E68: 0 | F68: 0 | G68: 0
A69: ADVSUPRAW | B69: Advances to suppliers of raw material | C69: 0 | D69: 0 | E69: 0 | F69: 0 | G69: 0
A70: ADVPAYTX | B70: Advance payment of tax | C70: =PrimeConsolidated!E78*100000 -> 0 | D70: =PrimeConsolidated!D78*100000 -> 0 | E70: =PrimeConsolidated!C78*100000 -> 0 | F70: 0 | G70: 0
A71: INTACC | B71: Interest Accrued | C71: 0 | D71: 0 | E71: 0 | F71: 0 | G71: 0
A72: ADVRCVCASH | B72: Advance receivable in cash or kind | C72: =IF(BasicInput!C1="Prime",PrimeConsolidated!E76,AffordConsolidated!E80)*100000 -> 0 | D72: =IF(BasicInput!C1="Prime",PrimeConsolidated!D76,AffordConsolidated!D80)*100000 -> 0 | E72: =IF(BasicInput!C1="Prime",PrimeConsolidated!C76,AffordConsolidated!C80)*100000 -> 0 | F72: 0 | G72: 0
A73: SUNDRYDEP | B73: Sundry Deposit | C73: 0 | D73: 0 | E73: 0 | F73: 0 | G73: 0
A74: MODVAT | B74: Modvat Credit Receivable | C74: 0 | D74: 0 | E74: 0 | F74: 0 | G74: 0
A75: OTHCURASS1 | B75: Other current assets | C75: 0 | D75: 0 | E75: 0 | F75: 0 | G75: 0
A76: LAND | B76: (I) Land | C76: 0 | D76: 0 | E76: 0 | F76: 0 | G76: 0
A77: BUILDING | B77: (ii) Building | C77: 0 | D77: 0 | E77: 0 | F77: 0 | G77: 0
A78: VEHICLES | B78: (iii) Vehicles | C78: 0 | D78: 0 | E78: 0 | F78: 0 | G78: 0
A79: PLANTMACH | B79: (IV) Plant & Machinery | C79: 0 | D79: 0 | E79: 0 | F79: 0 | G79: 0
A80: FURNFIXT | B80: (v) Furniture & Fixtures | C80: 0 | D80: 0 | E80: 0 | F80: 0 | G80: 0
A81: OTHFIXASS | B81: (vi) Other Fixed Assets | C81: =IF(BasicInput!C1="Prime",PrimeConsolidated!E65,AffordConsolidated!E67)*100000 -> 0 | D81: =IF(BasicInput!C1="Prime",PrimeConsolidated!D65,AffordConsolidated!D67)*100000 -> 0 | E81: =IF(BasicInput!C1="Prime",PrimeConsolidated!C65,AffordConsolidated!C67)*100000 -> 0 | F81: 0 | G81: 0
A82: CAPWIP | B82: (vii) Capital WIP | C82: =AffordConsolidated!E68*100000 -> 0 | D82: =AffordConsolidated!D68*100000 -> 0 | E82: =AffordConsolidated!C68*100000 -> 0 | F82: 0 | G82: 0
A83: LESSACCDEP | B83: Less: Accumulated Depreciation | C83: 0 | D83: 0 | E83: 0 | F83: 0 | G83: 0
A84: INVSUBCOM | B84: Investments in Subsidiary companies/ affiliates | C84: =IF(BasicInput!C1="Prime",PrimeConsolidated!E58,AffordConsolidated!E79)*100000 -> 0 | D84: =IF(BasicInput!C1="Prime",PrimeConsolidated!D58,AffordConsolidated!D79)*100000 -> 0 | E84: =IF(BasicInput!C1="Prime",PrimeConsolidated!C58,AffordConsolidated!C79)*100000 -> 0 | F84: 0 | G84: 0
A85: OTHINVACQ | B85: Other Investments & Investment for acquisition | C85: 0 | D85: 0 | E85: 0 | F85: 0 | G85: 0
A86: DUEFRMSUB | B86: Due from subsidiaries | C86: 0 | D86: 0 | E86: 0 | F86: 0 | G86: 0
A87: DEFRCV1 | B87: Deferred receivables (maturity exceeding 1 year) | C87: 0 | D87: 0 | E87: 0 | F87: 0 | G87: 0
A88: MARGMON | B88: Margin money kept with banks. | C88: 0 | D88: 0 | E88: 0 | F88: 0 | G88: 0
A89: DEBATORS6 | B89: Debtors more than 6 months | C89: =IF(BasicInput!C1="Prime",PrimeConsolidated!E75,AffordConsolidated!E75)*100000 -> 0 | D89: =IF(BasicInput!C1="Prime",PrimeConsolidated!D75,AffordConsolidated!D75)*100000 -> 0 | E89: =IF(BasicInput!C1="Prime",PrimeConsolidated!C75,AffordConsolidated!C75)*100000 -> 0 | F89: 0 | G89: 0
A90: ADVMORT | B90: Advance against mortgage of house property | C90: 0 | D90: 0 | E90: 0 | F90: 0 | G90: 0
A91: DEFRVNEXP | B91: Deferred Revenue Expenditure | C91: =AffordConsolidated!E69*100000 -> 0 | D91: =AffordConsolidated!D69*100000 -> 0 | E91: =AffordConsolidated!C69*100000 -> 0 | F91: 0 | G91: 0
A92: ONCA1 | B92: Other Non current assets- surplus for Future expansion, Loans & Advances non current in nature, ICDs, Dues from Directors | C92: 0 | D92: 0 | E92: 0 | F92: 0 | G92: 0
A93: APMO | B93: Accumulated Losses, Preliminary expenses, Miscellaneous expenditure not w/off, Other deferred revenue expenses | C93: =IF(BasicInput!C1="Prime",PrimeConsolidated!E55,AffordConsolidated!E47)*100000 -> 0 | D93: =IF(BasicInput!C1="Prime",PrimeConsolidated!D55,AffordConsolidated!D47)*100000 -> 0 | E93: =IF(BasicInput!C1="Prime",PrimeConsolidated!C55,AffordConsolidated!C47)*100000 -> 0 | F93: 0 | G93: 0
A94: DEFTAXASS | B94: Deferred Tax Asset | C94: =IF(BasicInput!C1="Prime",PrimeConsolidated!E90,AffordConsolidated!E72)*100000 -> 0 | D94: =IF(BasicInput!C1="Prime",PrimeConsolidated!D90,AffordConsolidated!D72)*100000 -> 0 | E94: =IF(BasicInput!C1="Prime",PrimeConsolidated!C90,AffordConsolidated!C72)*100000 -> 0 | F94: 0 | G94: 0

Sheet 44AD,44ADA,44AEIncome
A1: Assessee Name:
A2: PAN:
A4: Particulars | B4: Assessment Year
B5: 2023-24 | C5: 2022-23 | D5: 2021-22
A6: ITR Acknowledgment No.
A7: ITR Acknowledgment Date
A8: Gross Turnover / Receipts u/s 44AD (Rs.)
A9: Net Profit (Earnings) reported u/s 44AD (Rs.)
A10: Gross Receipts u/s 44ADA (Rs.) | B10: 0 | C10: 0
A11: Net Profit (Earnings) reported u/s 44ADA (Rs.) | B11: 0 | C11: 0
A12: Gross Receipts u/s 44AE (Rs.) | B12: 0 | C12: 0
A13: Net Profit (Earnings) reported u/s 44AE (Rs.) | B13: 0 | C13: 0
A14: Total Gross Turnover / Receipts (Rs.) | B14: =B8+B10+B12 -> 0 | C14: =C8+C10+C12 -> 0 | D14: =D8+D10+D12 -> 0
A15: Total Net Income (Rs.) | B15: =B9+B11+B13 -> 0 | C15: =C9+C11+C13 -> 0 | D15: =D9+D11+D13 -> 0
A16: Tax Paid (Rs.)
A17: PAT (Rs.) | B17: =B15-B16 -> 0 | C17: =C15-C16 -> 0 | D17: =D15-D16 -> 0
A22: Assessee Name:
A23: PAN:
A25: Particulars | B25: Assessment Year
B26: 2023-24 | C26: 2022-23 | D26: 2021-22
A27: ITR Acknowledgment No.
A28: ITR Acknowledgment Date
A29: Gross Turnover / Receipts u/s 44AD (Rs.)
A30: Net Profit (Earnings) reported u/s 44AD (Rs.)
A31: Gross Receipts u/s 44ADA (Rs.)
A32: Net Profit (Earnings) reported u/s 44ADA (Rs.)
A33: Gross Receipts u/s 44AE (Rs.)
A34: Net Profit (Earnings) reported u/s 44AE (Rs.)
A35: Total Gross Turnover / Receipts (Rs.) | B35: =B29+B31+B33 -> 0 | C35: =C29+C31+C33 -> 0 | D35: =D29+D31+D33 -> 0
A36: Total Net Income (Rs.) | B36: =B30+B32+B34 -> 0 | C36: =C30+C32+C34 -> 0 | D36: =D30+D32+D34 -> 0
A37: Tax Paid (Rs.)
A38: PAT (Rs.) | B38: =B36-B37 -> 0 | C38: =C36-C37 -> 0 | D38: =D36-D37 -> 0
A43: Assessee Name:
A44: PAN:
A46: Particulars | B46: Assessment Year
B47: 2020-21 | C47: 2019-20 | D47: 2018-19
A48: ITR Acknowledgment No.
A49: ITR Acknowledgment Date
A50: Gross Turnover / Receipts u/s 44AD (Rs.)
A51: Net Profit (Earnings) reported u/s 44AD (Rs.)
A52: Gross Receipts u/s 44ADA (Rs.)
A53: Net Profit (Earnings) reported u/s 44ADA (Rs.)
A54: Gross Receipts u/s 44AE (Rs.)
A55: Net Profit (Earnings) reported u/s 44AE (Rs.)
A56: Total Gross Turnover / Receipts (Rs.) | B56: =B50+B52+B54 -> 0 | C56: =C50+C52+C54 -> 0 | D56: =D50+D52+D54 -> 0
A57: Total Net Income (Rs.) | B57: =B51+B53+B55 -> 0 | C57: =C51+C53+C55 -> 0 | D57: =D51+D53+D55 -> 0
A58: Tax Paid (Rs.)
A59: PAT (Rs.) | B59: =B57-B58 -> 0 | C59: =C57-C58 -> 0 | D59: =D57-D58 -> 0
A64: Assessee Name:
A65: PAN:
A67: Particulars | B67: Assessment Year
B68: 2020-21 | C68: 2019-20 | D68: 2018-19
A69: ITR Acknowledgment No.
A70: ITR Acknowledgment Date
A71: Gross Turnover / Receipts u/s 44AD (Rs.)
A72: Net Profit (Earnings) reported u/s 44AD (Rs.)
A73: Gross Receipts u/s 44ADA (Rs.)
A74: Net Profit (Earnings) reported u/s 44ADA (Rs.)
A75: Gross Receipts u/s 44AE (Rs.)
A76: Net Profit (Earnings) reported u/s 44AE (Rs.)
A77: Total Gross Turnover / Receipts (Rs.) | B77: =B71+B73+B75 -> 0 | C77: =C71+C73+C75 -> 0 | D77: =D71+D73+D75 -> 0
A78: Total Net Income (Rs.) | B78: =B72+B74+B76 -> 0 | C78: =C72+C74+C76 -> 0 | D78: =D72+D74+D76 -> 0
A79: Tax Paid (Rs.)
A80: PAT (Rs.) | B80: =B78-B79 -> 0 | C80: =C78-C79 -> 0 | D80: =D78-D79 -> 0
A85: Assessee Name:
A86: PAN:
A88: Particulars | B88: Assessment Year
B89: 2020-21 | C89: 2019-20 | D89: 2018-19
A90: ITR Acknowledgment No.
A91: ITR Acknowledgment Date
A92: Gross Turnover / Receipts u/s 44AD (Rs.)
A93: Net Profit (Earnings) reported u/s 44AD (Rs.)
A94: Gross Receipts u/s 44ADA (Rs.)
A95: Net Profit (Earnings) reported u/s 44ADA (Rs.)
A96: Gross Receipts u/s 44AE (Rs.)
A97: Net Profit (Earnings) reported u/s 44AE (Rs.)
A98: Total Gross Turnover / Receipts (Rs.) | B98: =B92+B94+B96 -> 0 | C98: =C92+C94+C96 -> 0 | D98: =D92+D94+D96 -> 0
A99: Total Net Income (Rs.) | B99: =B93+B95+B97 -> 0 | C99: =C93+C95+C97 -> 0 | D99: =D93+D95+D97 -> 0
A100: Tax Paid (Rs.)
A101: PAT (Rs.) | B101: =B99-B100 -> 0 | C101: =C99-C100 -> 0 | D101: =D99-D100 -> 0
A107: Consolidated
A108: Particulars | B108: Assessment Year
B109: =$B$5 -> 2023-24 | C109: =$C$5 -> 2022-23 | D109: =$D$5 -> 2021-22
A110: Gross Turnover / Receipts u/s 44AD (Rs.) | B110: =B8+B29+B50+B71+B92 -> 0 | C110: =C8+C29+C50+C71+C92 -> 0 | D110: =D8+D29+D50+D71+D92 -> 0
A111: Net Profit (Earnings) reported u/s 44AD (Rs.) | B111: =B9+B30+B51+B72+B93 -> 0 | C111: =C9+C30+C51+C72+C93 -> 0 | D111: =D9+D30+D51+D72+D93 -> 0
A112: Gross Receipts u/s 44ADA (Rs.) | B112: =B10+B31+B52+B73+B94 -> 0 | C112: =C10+C31+C52+C73+C94 -> 0 | D112: =D10+D31+D52+D73+D94 -> 0
A113: Net Profit (Earnings) reported u/s 44ADA (Rs.) | B113: =B11+B32+B53+B74+B95 -> 0 | C113: =C11+C32+C53+C74+C95 -> 0 | D113: =D11+D32+D53+D74+D95 -> 0
A114: Gross Receipts u/s 44AE (Rs.) | B114: =B12+B33+B54+B75+B96 -> 0 | C114: =C12+C33+C54+C75+C96 -> 0 | D114: =D12+D33+D54+D75+D96 -> 0
A115: Net Profit (Earnings) reported u/s 44AE (Rs.) | B115: =B13+B34+B55+B76+B97 -> 0 | C115: =C13+C34+C55+C76+C97 -> 0 | D115: =D13+D34+D55+D76+D97 -> 0
A116: Total Gross Turnover / Receipts (Rs.) | B116: =B110+B112+B114 -> 0 | C116: =C110+C112+C114 -> 0 | D116: =D110+D112+D114 -> 0
A117: Total Net Income (Rs.) | B117: =B111+B113+B115 -> 0 | C117: =C111+C113+C115 -> 0 | D117: =D111+D113+D115 -> 0
A118: Tax Paid (Rs.) | B118: =B16+B37+B58+B79+B100 -> 0 | C118: =C16+C37+C58+C79+C100 -> 0 | D118: =D16+D37+D58+D79+D100 -> 0
A119: PAT (Rs.) | B119: =B117-B118 -> 0 | C119: =C117-C118 -> 0 | D119: =D117-D118 -> 0
A120: Expenses other than Tax (Rs.) | B120: =B116-B117 -> 0 | C120: =C116-C117 -> 0 | D120: =D116-D117 -> 0

Sheet 26ASMapping
A1: Customer / Entity Name:
A2: Financial Year:
A4: S. No. | B4: Party Name | C4: Payment under Section | D4: Amount Credited (Rs.) | E4: Tax Deducted (Rs.)
A5: 1
A6: 2
A7: 3
A8: 4
A9: 5
A10: 6
A11: 7
A12: 8
A13: 9
A14: 10
A15: 11
A16: 12
... A54: 50
A55: Total | D55: =SUM(D27:D54) -> 0 | E55: =SUM(E27:E54) -> 0

Sheet GSTSummary
A1: Name of Entity | B1: GSTIN | C1: Financial Year | D1: Business Location | E1: Month | F1: Outward Taxable Supply (Rs.)
E2: April
E3: May
E4: June
E5: July
E6: August
E7: September
E8: October
E9: November
E10: December
E11: January
E12: February
E13: March
A14: TOTAL VALUE OF OUTWARD TAXABLE SUPPLY | F14: =SUM(F2:F13) -> 0

Sheet Banking - Non PDF
A1: Name of Customer | C1: =IF(PrimeConsolidated!B3="","",CONCATENATE(PrimeConsolidated!B3," (Consolidated Banking in Rs. Lacs)")) -> NARENDRA KUMAR VYAS & Group (Consolidated Banking in Rs. Lacs)
A2: Name of Customer | B2: Balance / Utilization on date (Rs. Lacs) | E2: Min Balance of the month (Rs. Lacs) | F2: Max Balance of the month (Rs. Lacs) | G2: Average (Rs. Lacs) | H2: Total Inflows (Rs. Lacs) | I2: Total Outflows (Rs. Lacs) | J2: Loan Disbursal incl in Inflows (Rs. Lacs) | K2: Interest (debited) / credited (Rs. Lacs) | L2: Intra Group transaction value included (Rs. Lacs) | N2: Cash Entry Value (Rs. Lacs) | P2: Net Flow (Rs. Lacs) | Q2: No. of I/W Return | R2: No. of O/W Return | S2: No. of Credit Entries | T2: No. of Debit Entries | U2: Net Inflows (Rs. Lacs) | V2: Net Outflows (Rs. Lacs)
B3: 10 | C3: 20 | D3: 30 | L3: Debit | M3: Credit | N3: Debit | O3: Credit
A4: =IF($A$27="","",$A$27) -> 44986 | B4: =(B27+B50+B73+B96+B119+B142+B165+B188+B211+B234+B257+B280+B303+B326+B349+B372+B395+B418+B441+B464)/100000 -> 0 | C4: =(C27+C50+C73+C96+C119+C142+C165+C188+C211+C234+C257+C280+C303+C326+C349+C372+C395+C418+C441+C464)/100000 -> 0 | D4: =(D27+D50+D73+D96+D119+D142+D165+D188+D211+D234+D257+D280+D303+D326+D349+D372+D395+D418+D441+D464)/100000 -> 0 | E4: =(E27+E50+E73+E96+E119+E142+E165+E188+E211+E234+E257+E280+E303+E326+E349+E372+E395+E418+E441+E464)/100000 -> 0 | F4: =(F27+F50+F73+F96+F119+F142+F165+F188+F211+F234+F257+F280+F303+F326+F349+F372+F395+F418+F441+F464)/100000 -> 0 | G4: =AVERAGE(B4:D4) -> 0 | H4: =(H27+H50+H73+H96+H119+H142+H165+H188+H211+H234+H257+H280+H303+H326+H349+H372+H395+H418+H441+H464)/100000 -> 0 | I4: =(I27+I50+I73+I96+I119+I142+I165+I188+I211+I234+I257+I280+I303+I326+I349+I372+I395+I418+I441+I464)/100000 -> 0 | J4: =(J27+J50+J73+J96+J119+J142+J165+J188+J211+J234+J257+J280+J303+J326+J349+J372+J395+J418+J441+J464)/100000 -> 0 | K4: =(K27+K50+K73+K96+K119+K142+K165+K188+K211+K234+K257+K280+K303+K326+K349+K372+K395+K418+K441+K464)/100000 -> 0 | L4: =(L27+L50+L73+L96+L119+L142+L165+L188+L211+L234+L257+L280+L303+L326+L349+L372+L395+L418+L441+L464)/100000 -> 0 | M4: =(M27+M50+M73+M96+M119+M142+M165+M188+M211+M234+M257+M280+M303+M326+M349+M372+M395+M418+M441+M464)/100000 -> 0 | N4: =(N27+N50+N73+N96+N119+N142+N165+N188+N211+N234+N257+N280+N303+N326+N349+N372+N395+N418+N441+N464)/100000 -> 0 | O4: =(O27+O50+O73+O96+O119+O142+O165+O188+O211+O234+O257+O280+O303+O326+O349+O372+O395+O418+O441+O464)/100000 -> 0 | P4: =(P27+P50+P73+P96+P119+P142+P165+P188+P211+P234+P257+P280+P303+P326+P349+P372+P395+P418+P441+P464)/100000 -> 0 | Q4: =(Q27+Q50+Q73+Q96+Q119+Q142+Q165+Q188+Q211+Q234+Q257+Q280+Q303+Q326+Q349+Q372+Q395+Q418+Q441+Q464) -> 0 | R4: =(R27+R50+R73+R96+R119+R142+R165+R188+R211+R234+R257+R280+R303+R326+R349+R372+R395+R418+R441+R464) -> 0 | S4: =(S27+S50+S73+S96+S119+S142+S165+S188+S211+S234+S257+S280+S303+S326+S349+S372+S395+S418+S441+S464) -> 0 | T4: =(T27+T50+T73+T96+T119+T142+T165+T188+T211+T234+T257+T280+T303+T326+T349+T372+T395+T418+T441+T464) -> 0 | U4: =(U27+U50+U73+U96+U119+U142+U165+U188+U211+U234+U257+U280+U303+U326+U349+U372+U395+U418+U441+U464)/100000 -> 0 | V4: =(V27+V50+V73+V96+V119+V142+V165+V188+V211+V234+V257+V280+V303+V326+V349+V372+V395+V418+V441+V464)/100000 -> 0
A5: =IF($A$28="","",$A$28) -> 45017 | B5: =(B28+B51+B74+B97+B120+B143+B166+B189+B212+B235+B258+B281+B304+B327+B350+B373+B396+B419+B442+B465)/100000 -> 0 | C5: =(C28+C51+C74+C97+C120+C143+C166+C189+C212+C235+C258+C281+C304+C327+C350+C373+C396+C419+C442+C465)/100000 -> 0 | D5: =(D28+D51+D74+D97+D120+D143+D166+D189+D212+D235+D258+D281+D304+D327+D350+D373+D396+D419+D442+D465)/100000 -> 0 | E5: =(E28+E51+E74+E97+E120+E143+E166+E189+E212+E235+E258+E281+E304+E327+E350+E373+E396+E419+E442+E465)/100000 -> 0 | F5: =(F28+F51+F74+F97+F120+F143+F166+F189+F212+F235+F258+F281+F304+F327+F350+F373+F396+F419+F442+F465)/100000 -> 0 | G5: =AVERAGE(B5:D5) -> 0 | H5: =(H28+H51+H74+H97+H120+H143+H166+H189+H212+H235+H258+H281+H304+H327+H350+H373+H396+H419+H442+H465)/100000 -> 0 | I5: =(I28+I51+I74+I97+I120+I143+I166+I189+I212+I235+I258+I281+I304+I327+I350+I373+I396+I419+I442+I465)/100000 -> 0 | J5: =(J28+J51+J74+J97+J120+J143+J166+J189+J212+J235+J258+J281+J304+J327+J350+J373+J396+J419+J442+J465)/100000 -> 0 | K5: =(K28+K51+K74+K97+K120+K143+K166+K189+K212+K235+K258+K281+K304+K327+K350+K373+K396+K419+K442+K465)/100000 -> 0 | L5: =(L28+L51+L74+L97+L120+L143+L166+L189+L212+L235+L258+L281+L304+L327+L350+L373+L396+L419+L442+L465)/100000 -> 0 | M5: =(M28+M51+M74+M97+M120+M143+M166+M189+M212+M235+M258+M281+M304+M327+M350+M373+M396+M419+M442+M465)/100000 -> 0 | N5: =(N28+N51+N74+N97+N120+N143+N166+N189+N212+N235+N258+N281+N304+N327+N350+N373+N396+N419+N442+N465)/100000 -> 0 | O5: =(O28+O51+O74+O97+O120+O143+O166+O189+O212+O235+O258+O281+O304+O327+O350+O373+O396+O419+O442+O465)/100000 -> 0 | P5: =(P28+P51+P74+P97+P120+P143+P166+P189+P212+P235+P258+P281+P304+P327+P350+P373+P396+P419+P442+P465)/100000 -> 0 | Q5: =(Q28+Q51+Q74+Q97+Q120+Q143+Q166+Q189+Q212+Q235+Q258+Q281+Q304+Q327+Q350+Q373+Q396+Q419+Q442+Q465) -> 0 | R5: =(R28+R51+R74+R97+R120+R143+R166+R189+R212+R235+R258+R281+R304+R327+R350+R373+R396+R419+R442+R465) -> 0 | S5: =(S28+S51+S74+S97+S120+S143+S166+S189+S212+S235+S258+S281+S304+S327+S350+S373+S396+S419+S442+S465) -> 0 | T5: =(T28+T51+T74+T97+T120+T143+T166+T189+T212+T235+T258+T281+T304+T327+T350+T373+T396+T419+T442+T465) -> 0 | U5: =(U28+U51+U74+U97+U120+U143+U166+U189+U212+U235+U258+U281+U304+U327+U350+U373+U396+U419+U442+U465)/100000 -> 0 | V5: =(V28+V51+V74+V97+V120+V143+V166+V189+V212+V235+V258+V281+V304+V327+V350+V373+V396+V419+V442+V465)/100000 -> 0
A6: =IF($A$29="","",$A$29) -> 45047 | B6: =(B29+B52+B75+B98+B121+B144+B167+B190+B213+B236+B259+B282+B305+B328+B351+B374+B397+B420+B443+B466)/100000 -> 0 | C6: =(C29+C52+C75+C98+C121+C144+C167+C190+C213+C236+C259+C282+C305+C328+C351+C374+C397+C420+C443+C466)/100000 -> 0 | D6: =(D29+D52+D75+D98+D121+D144+D167+D190+D213+D236+D259+D282+D305+D328+D351+D374+D397+D420+D443+D466)/100000 -> 0 | E6: =(E29+E52+E75+E98+E121+E144+E167+E190+E213+E236+E259+E282+E305+E328+E351+E374+E397+E420+E443+E466)/100000 -> 0 | F6: =(F29+F52+F75+F98+F121+F144+F167+F190+F213+F236+F259+F282+F305+F328+F351+F374+F397+F420+F443+F466)/100000 -> 0 | G6: =AVERAGE(B6:D6) -> 0 | H6: =(H29+H52+H75+H98+H121+H144+H167+H190+H213+H236+H259+H282+H305+H328+H351+H374+H397+H420+H443+H466)/100000 -> 0 | I6: =(I29+I52+I75+I98+I121+I144+I167+I190+I213+I236+I259+I282+I305+I328+I351+I374+I397+I420+I443+I466)/100000 -> 0 | J6: =(J29+J52+J75+J98+J121+J144+J167+J190+J213+J236+J259+J282+J305+J328+J351+J374+J397+J420+J443+J466)/100000 -> 0 | K6: =(K29+K52+K75+K98+K121+K144+K167+K190+K213+K236+K259+K282+K305+K328+K351+K374+K397+K420+K443+K466)/100000 -> 0 | L6: =(L29+L52+L75+L98+L121+L144+L167+L190+L213+L236+L259+L282+L305+L328+L351+L374+L397+L420+L443+L466)/100000 -> 0 | M6: =(M29+M52+M75+M98+M121+M144+M167+M190+M213+M236+M259+M282+M305+M328+M351+M374+M397+M420+M443+M466)/100000 -> 0 | N6: =(N29+N52+N75+N98+N121+N144+N167+N190+N213+N236+N259+N282+N305+N328+N351+N374+N397+N420+N443+N466)/100000 -> 0 | O6: =(O29+O52+O75+O98+O121+O144+O167+O190+O213+O236+O259+O282+O305+O328+O351+O374+O397+O420+O443+O466)/100000 -> 0 | P6: =(P29+P52+P75+P98+P121+P144+P167+P190+P213+P236+P259+P282+P305+P328+P351+P374+P397+P420+P443+P466)/100000 -> 0 | Q6: =(Q29+Q52+Q75+Q98+Q121+Q144+Q167+Q190+Q213+Q236+Q259+Q282+Q305+Q328+Q351+Q374+Q397+Q420+Q443+Q466) -> 0 | R6: =(R29+R52+R75+R98+R121+R144+R167+R190+R213+R236+R259+R282+R305+R328+R351+R374+R397+R420+R443+R466) -> 0 | S6: =(S29+S52+S75+S98+S121+S144+S167+S190+S213+S236+S259+S282+S305+S328+S351+S374+S397+S420+S443+S466) -> 0 | T6: =(T29+T52+T75+T98+T121+T144+T167+T190+T213+T236+T259+T282+T305+T328+T351+T374+T397+T420+T443+T466) -> 0 | U6: =(U29+U52+U75+U98+U121+U144+U167+U190+U213+U236+U259+U282+U305+U328+U351+U374+U397+U420+U443+U466)/100000 -> 0 | V6: =(V29+V52+V75+V98+V121+V144+V167+V190+V213+V236+V259+V282+V305+V328+V351+V374+V397+V420+V443+V466)/100000 -> 0
A7: =IF($A$30="","",$A$30) -> 45078 | B7: =(B30+B53+B76+B99+B122+B145+B168+B191+B214+B237+B260+B283+B306+B329+B352+B375+B398+B421+B444+B467)/100000 -> 0 | C7: =(C30+C53+C76+C99+C122+C145+C168+C191+C214+C237+C260+C283+C306+C329+C352+C375+C398+C421+C444+C467)/100000 -> 0 | D7: =(D30+D53+D76+D99+D122+D145+D168+D191+D214+D237+D260+D283+D306+D329+D352+D375+D398+D421+D444+D467)/100000 -> 0 | E7: =(E30+E53+E76+E99+E122+E145+E168+E191+E214+E237+E260+E283+E306+E329+E352+E375+E398+E421+E444+E467)/100000 -> 0 | F7: =(F30+F53+F76+F99+F122+F145+F168+F191+F214+F237+F260+F283+F306+F329+F352+F375+F398+F421+F444+F467)/100000 -> 0 | G7: =AVERAGE(B7:D7) -> 0 | H7: =(H30+H53+H76+H99+H122+H145+H168+H191+H214+H237+H260+H283+H306+H329+H352+H375+H398+H421+H444+H467)/100000 -> 0 | I7: =(I30+I53+I76+I99+I122+I145+I168+I191+I214+I237+I260+I283+I306+I329+I352+I375+I398+I421+I444+I467)/100000 -> 0 | J7: =(J30+J53+J76+J99+J122+J145+J168+J191+J214+J237+J260+J283+J306+J329+J352+J375+J398+J421+J444+J467)/100000 -> 0 | K7: =(K30+K53+K76+K99+K122+K145+K168+K191+K214+K237+K260+K283+K306+K329+K352+K375+K398+K421+K444+K467)/100000 -> 0 | L7: =(L30+L53+L76+L99+L122+L145+L168+L191+L214+L237+L260+L283+L306+L329+L352+L375+L398+L421+L444+L467)/100000 -> 0 | M7: =(M30+M53+M76+M99+M122+M145+M168+M191+M214+M237+M260+M283+M306+M329+M352+M375+M398+M421+M444+M467)/100000 -> 0 | N7: =(N30+N53+N76+N99+N122+N145+N168+N191+N214+N237+N260+N283+N306+N329+N352+N375+N398+N421+N444+N467)/100000 -> 0 | O7: =(O30+O53+O76+O99+O122+O145+O168+O191+O214+O237+O260+O283+O306+O329+O352+O375+O398+O421+O444+O467)/100000 -> 0 | P7: =(P30+P53+P76+P99+P122+P145+P168+P191+P214+P237+P260+P283+P306+P329+P352+P375+P398+P421+P444+P467)/100000 -> 0 | Q7: =(Q30+Q53+Q76+Q99+Q122+Q145+Q168+Q191+Q214+Q237+Q260+Q283+Q306+Q329+Q352+Q375+Q398+Q421+Q444+Q467) -> 0 | R7: =(R30+R53+R76+R99+R122+R145+R168+R191+R214+R237+R260+R283+R306+R329+R352+R375+R398+R421+R444+R467) -> 0 | S7: =(S30+S53+S76+S99+S122+S145+S168+S191+S214+S237+S260+S283+S306+S329+S352+S375+S398+S421+S444+S467) -> 0 | T7: =(T30+T53+T76+T99+T122+T145+T168+T191+T214+T237+T260+T283+T306+T329+T352+T375+T398+T421+T444+T467) -> 0 | U7: =(U30+U53+U76+U99+U122+U145+U168+U191+U214+U237+U260+U283+U306+U329+U352+U375+U398+U421+U444+U467)/100000 -> 0 | V7: =(V30+V53+V76+V99+V122+V145+V168+V191+V214+V237+V260+V283+V306+V329+V352+V375+V398+V421+V444+V467)/100000 -> 0
A8: =IF($A$31="","",$A$31) -> 45108 | B8: =(B31+B54+B77+B100+B123+B146+B169+B192+B215+B238+B261+B284+B307+B330+B353+B376+B399+B422+B445+B468)/100000 -> 0 | C8: =(C31+C54+C77+C100+C123+C146+C169+C192+C215+C238+C261+C284+C307+C330+C353+C376+C399+C422+C445+C468)/100000 -> 0 | D8: =(D31+D54+D77+D100+D123+D146+D169+D192+D215+D238+D261+D284+D307+D330+D353+D376+D399+D422+D445+D468)/100000 -> 0 | E8: =(E31+E54+E77+E100+E123+E146+E169+E192+E215+E238+E261+E284+E307+E330+E353+E376+E399+E422+E445+E468)/100000 -> 0 | F8: =(F31+F54+F77+F100+F123+F146+F169+F192+F215+F238+F261+F284+F307+F330+F353+F376+F399+F422+F445+F468)/100000 -> 0 | G8: =AVERAGE(B8:D8) -> 0 | H8: =(H31+H54+H77+H100+H123+H146+H169+H192+H215+H238+H261+H284+H307+H330+H353+H376+H399+H422+H445+H468)/100000 -> 0 | I8: =(I31+I54+I77+I100+I123+I146+I169+I192+I215+I238+I261+I284+I307+I330+I353+I376+I399+I422+I445+I468)/100000 -> 0 | J8: =(J31+J54+J77+J100+J123+J146+J169+J192+J215+J238+J261+J284+J307+J330+J353+J376+J399+J422+J445+J468)/100000 -> 0 | K8: =(K31+K54+K77+K100+K123+K146+K169+K192+K215+K238+K261+K284+K307+K330+K353+K376+K399+K422+K445+K468)/100000 -> 0 | L8: =(L31+L54+L77+L100+L123+L146+L169+L192+L215+L238+L261+L284+L307+L330+L353+L376+L399+L422+L445+L468)/100000 -> 0 | M8: =(M31+M54+M77+M100+M123+M146+M169+M192+M215+M238+M261+M284+M307+M330+M353+M376+M399+M422+M445+M468)/100000 -> 0 | N8: =(N31+N54+N77+N100+N123+N146+N169+N192+N215+N238+N261+N284+N307+N330+N353+N376+N399+N422+N445+N468)/100000 -> 0 | O8: =(O31+O54+O77+O100+O123+O146+O169+O192+O215+O238+O261+O284+O307+O330+O353+O376+O399+O422+O445+O468)/100000 -> 0 | P8: =(P31+P54+P77+P100+P123+P146+P169+P192+P215+P238+P261+P284+P307+P330+P353+P376+P399+P422+P445+P468)/100000 -> 0 | Q8: =(Q31+Q54+Q77+Q100+Q123+Q146+Q169+Q192+Q215+Q238+Q261+Q284+Q307+Q330+Q353+Q376+Q399+Q422+Q445+Q468) -> 0 | R8: =(R31+R54+R77+R100+R123+R146+R169+R192+R215+R238+R261+R284+R307+R330+R353+R376+R399+R422+R445+R468) -> 0 | S8: =(S31+S54+S77+S100+S123+S146+S169+S192+S215+S238+S261+S284+S307+S330+S353+S376+S399+S422+S445+S468) -> 0 | T8: =(T31+T54+T77+T100+T123+T146+T169+T192+T215+T238+T261+T284+T307+T330+T353+T376+T399+T422+T445+T468) -> 0 | U8: =(U31+U54+U77+U100+U123+U146+U169+U192+U215+U238+U261+U284+U307+U330+U353+U376+U399+U422+U445+U468)/100000 -> 0 | V8: =(V31+V54+V77+V100+V123+V146+V169+V192+V215+V238+V261+V284+V307+V330+V353+V376+V399+V422+V445+V468)/100000 -> 0
A9: =IF($A$32="","",$A$32) -> 45139 | B9: =(B32+B55+B78+B101+B124+B147+B170+B193+B216+B239+B262+B285+B308+B331+B354+B377+B400+B423+B446+B469)/100000 -> 0 | C9: =(C32+C55+C78+C101+C124+C147+C170+C193+C216+C239+C262+C285+C308+C331+C354+C377+C400+C423+C446+C469)/100000 -> 0 | D9: =(D32+D55+D78+D101+D124+D147+D170+D193+D216+D239+D262+D285+D308+D331+D354+D377+D400+D423+D446+D469)/100000 -> 0 | E9: =(E32+E55+E78+E101+E124+E147+E170+E193+E216+E239+E262+E285+E308+E331+E354+E377+E400+E423+E446+E469)/100000 -> 0 | F9: =(F32+F55+F78+F101+F124+F147+F170+F193+F216+F239+F262+F285+F308+F331+F354+F377+F400+F423+F446+F469)/100000 -> 0 | G9: =AVERAGE(B9:D9) -> 0 | H9: =(H32+H55+H78+H101+H124+H147+H170+H193+H216+H239+H262+H285+H308+H331+H354+H377+H400+H423+H446+H469)/100000 -> 0 | I9: =(I32+I55+I78+I101+I124+I147+I170+I193+I216+I239+I262+I285+I308+I331+I354+I377+I400+I423+I446+I469)/100000 -> 0 | J9: =(J32+J55+J78+J101+J124+J147+J170+J193+J216+J239+J262+J285+J308+J331+J354+J377+J400+J423+J446+J469)/100000 -> 0 | K9: =(K32+K55+K78+K101+K124+K147+K170+K193+K216+K239+K262+K285+K308+K331+K354+K377+K400+K423+K446+K469)/100000 -> 0 | L9: =(L32+L55+L78+L101+L124+L147+L170+L193+L216+L239+L262+L285+L308+L331+L354+L377+L400+L423+L446+L469)/100000 -> 0 | M9: =(M32+M55+M78+M101+M124+M147+M170+M193+M216+M239+M262+M285+M308+M331+M354+M377+M400+M423+M446+M469)/100000 -> 0 | N9: =(N32+N55+N78+N101+N124+N147+N170+N193+N216+N239+N262+N285+N308+N331+N354+N377+N400+N423+N446+N469)/100000 -> 0 | O9: =(O32+O55+O78+O101+O124+O147+O170+O193+O216+O239+O262+O285+O308+O331+O354+O377+O400+O423+O446+O469)/100000 -> 0 | P9: =(P32+P55+P78+P101+P124+P147+P170+P193+P216+P239+P262+P285+P308+P331+P354+P377+P400+P423+P446+P469)/100000 -> 0 | Q9: =(Q32+Q55+Q78+Q101+Q124+Q147+Q170+Q193+Q216+Q239+Q262+Q285+Q308+Q331+Q354+Q377+Q400+Q423+Q446+Q469) -> 0 | R9: =(R32+R55+R78+R101+R124+R147+R170+R193+R216+R239+R262+R285+R308+R331+R354+R377+R400+R423+R446+R469) -> 0 | S9: =(S32+S55+S78+S101+S124+S147+S170+S193+S216+S239+S262+S285+S308+S331+S354+S377+S400+S423+S446+S469) -> 0 | T9: =(T32+T55+T78+T101+T124+T147+T170+T193+T216+T239+T262+T285+T308+T331+T354+T377+T400+T423+T446+T469) -> 0 | U9: =(U32+U55+U78+U101+U124+U147+U170+U193+U216+U239+U262+U285+U308+U331+U354+U377+U400+U423+U446+U469)/100000 -> 0 | V9: =(V32+V55+V78+V101+V124+V147+V170+V193+V216+V239+V262+V285+V308+V331+V354+V377+V400+V423+V446+V469)/100000 -> 0
A10: =IF($A$33="","",$A$33) -> 45170 | B10: =(B33+B56+B79+B102+B125+B148+B171+B194+B217+B240+B263+B286+B309+B332+B355+B378+B401+B424+B447+B470)/100000 -> 0.30118 | C10: =(C33+C56+C79+C102+C125+C148+C171+C194+C217+C240+C263+C286+C309+C332+C355+C378+C401+C424+C447+C470)/100000 -> 0.12604 | D10: =(D33+D56+D79+D102+D125+D148+D171+D194+D217+D240+D263+D286+D309+D332+D355+D378+D401+D424+D447+D470)/100000 -> 0.1044 | E10: =(E33+E56+E79+E102+E125+E148+E171+E194+E217+E240+E263+E286+E309+E332+E355+E378+E401+E424+E447+E470)/100000 -> 0.10439 | F10: =(F33+F56+F79+F102+F125+F148+F171+F194+F217+F240+F263+F286+F309+F332+F355+F378+F401+F424+F447+F470)/100000 -> 0.39768 | G10: =AVERAGE(B10:D10) -> 0.17720667 | H10: =(H33+H56+H79+H102+H125+H148+H171+H194+H217+H240+H263+H286+H309+H332+H355+H378+H401+H424+H447+H470)/100000 -> 0.00656 | I10: =(I33+I56+I79+I102+I125+I148+I171+I194+I217+I240+I263+I286+I309+I332+I355+I378+I401+I424+I447+I470)/100000 -> 0.25945 | J10: =(J33+J56+J79+J102+J125+J148+J171+J194+J217+J240+J263+J286+J309+J332+J355+J378+J401+J424+J447+J470)/100000 -> 0 | K10: =(K33+K56+K79+K102+K125+K148+K171+K194+K217+K240+K263+K286+K309+K332+K355+K378+K401+K424+K447+K470)/100000 -> 0 | L10: =(L33+L56+L79+L102+L125+L148+L171+L194+L217+L240+L263+L286+L309+L332+L355+L378+L401+L424+L447+L470)/100000 -> 0 | M10: =(M33+M56+M79+M102+M125+M148+M171+M194+M217+M240+M263+M286+M309+M332+M355+M378+M401+M424+M447+M470)/100000 -> 0 | N10: =(N33+N56+N79+N102+N125+N148+N171+N194+N217+N240+N263+N286+N309+N332+N355+N378+N401+N424+N447+N470)/100000 -> 0 | O10: =(O33+O56+O79+O102+O125+O148+O171+O194+O217+O240+O263+O286+O309+O332+O355+O378+O401+O424+O447+O470)/100000 -> 0 | P10: =(P33+P56+P79+P102+P125+P148+P171+P194+P217+P240+P263+P286+P309+P332+P355+P378+P401+P424+P447+P470)/100000 -> -0.25289 | Q10: =(Q33+Q56+Q79+Q102+Q125+Q148+Q171+Q194+Q217+Q240+Q263+Q286+Q309+Q332+Q355+Q378+Q401+Q424+Q447+Q470) -> 0 | R10: =(R33+R56+R79+R102+R125+R148+R171+R194+R217+R240+R263+R286+R309+R332+R355+R378+R401+R424+R447+R470) -> 0 | S10: =(S33+S56+S79+S102+S125+S148+S171+S194+S217+S240+S263+S286+S309+S332+S355+S378+S401+S424+S447+S470) -> 1 | T10: =(T33+T56+T79+T102+T125+T148+T171+T194+T217+T240+T263+T286+T309+T332+T355+T378+T401+T424+T447+T470) -> 69 | U10: =(U33+U56+U79+U102+U125+U148+U171+U194+U217+U240+U263+U286+U309+U332+U355+U378+U401+U424+U447+U470)/100000 -> 0.00656 | V10: =(V33+V56+V79+V102+V125+V148+V171+V194+V217+V240+V263+V286+V309+V332+V355+V378+V401+V424+V447+V470)/100000 -> 0.25945
A11: =IF($A$34="","",$A$34) -> 45200 | B11: =(B34+B57+B80+B103+B126+B149+B172+B195+B218+B241+B264+B287+B310+B333+B356+B379+B402+B425+B448+B471)/100000 -> 0.12128 | C11: =(C34+C57+C80+C103+C126+C149+C172+C195+C218+C241+C264+C287+C310+C333+C356+C379+C402+C425+C448+C471)/100000 -> 0.01682 | D11: =(D34+D57+D80+D103+D126+D149+D172+D195+D218+D241+D264+D287+D310+D333+D356+D379+D402+D425+D448+D471)/100000 -> 0.00158 | E11: =(E34+E57+E80+E103+E126+E149+E172+E195+E218+E241+E264+E287+E310+E333+E356+E379+E402+E425+E448+E471)/100000 -> 0.00085 | F11: =(F34+F57+F80+F103+F126+F149+F172+F195+F218+F241+F264+F287+F310+F333+F356+F379+F402+F425+F448+F471)/100000 -> 0.12532 | G11: =AVERAGE(B11:D11) -> 0.04656 | H11: =(H34+H57+H80+H103+H126+H149+H172+H195+H218+H241+H264+H287+H310+H333+H356+H379+H402+H425+H448+H471)/100000 -> 0.125 | I11: =(I34+I57+I80+I103+I126+I149+I172+I195+I218+I241+I264+I287+I310+I333+I356+I379+I402+I425+I448+I471)/100000 -> 0.39638 | J11: =(J34+J57+J80+J103+J126+J149+J172+J195+J218+J241+J264+J287+J310+J333+J356+J379+J402+J425+J448+J471)/100000 -> 0 | K11: =(K34+K57+K80+K103+K126+K149+K172+K195+K218+K241+K264+K287+K310+K333+K356+K379+K402+K425+K448+K471)/100000 -> 0 | L11: =(L34+L57+L80+L103+L126+L149+L172+L195+L218+L241+L264+L287+L310+L333+L356+L379+L402+L425+L448+L471)/100000 -> 0 | M11: =(M34+M57+M80+M103+M126+M149+M172+M195+M218+M241+M264+M287+M310+M333+M356+M379+M402+M425+M448+M471)/100000 -> 0 | N11: =(N34+N57+N80+N103+N126+N149+N172+N195+N218+N241+N264+N287+N310+N333+N356+N379+N402+N425+N448+N471)/100000 -> 0 | O11: =(O34+O57+O80+O103+O126+O149+O172+O195+O218+O241+O264+O287+O310+O333+O356+O379+O402+O425+O448+O471)/100000 -> 0 | P11: =(P34+P57+P80+P103+P126+P149+P172+P195+P218+P241+P264+P287+P310+P333+P356+P379+P402+P425+P448+P471)/100000 -> -0.27138 | Q11: =(Q34+Q57+Q80+Q103+Q126+Q149+Q172+Q195+Q218+Q241+Q264+Q287+Q310+Q333+Q356+Q379+Q402+Q425+Q448+Q471) -> 0 | R11: =(R34+R57+R80+R103+R126+R149+R172+R195+R218+R241+R264+R287+R310+R333+R356+R379+R402+R425+R448+R471) -> 0 | S11: =(S34+S57+S80+S103+S126+S149+S172+S195+S218+S241+S264+S287+S310+S333+S356+S379+S402+S425+S448+S471) -> 6 | T11: =(T34+T57+T80+T103+T126+T149+T172+T195+T218+T241+T264+T287+T310+T333+T356+T379+T402+T425+T448+T471) -> 95 | U11: =(U34+U57+U80+U103+U126+U149+U172+U195+U218+U241+U264+U287+U310+U333+U356+U379+U402+U425+U448+U471)/100000 -> 0.125 | V11: =(V34+V57+V80+V103+V126+V149+V172+V195+V218+V241+V264+V287+V310+V333+V356+V379+V402+V425+V448+V471)/100000 -> 0.39638
A12: =IF($A$35="","",$A$35) -> 45231 | B12: =(B35+B58+B81+B104+B127+B150+B173+B196+B219+B242+B265+B288+B311+B334+B357+B380+B403+B426+B449+B472)/100000 -> 0.01658 | C12: =(C35+C58+C81+C104+C127+C150+C173+C196+C219+C242+C265+C288+C311+C334+C357+C380+C403+C426+C449+C472)/100000 -> 1.18671 | D12: =(D35+D58+D81+D104+D127+D150+D173+D196+D219+D242+D265+D288+D311+D334+D357+D380+D403+D426+D449+D472)/100000 -> 0.68286 | E12: =(E35+E58+E81+E104+E127+E150+E173+E196+E219+E242+E265+E288+E311+E334+E357+E380+E403+E426+E449+E472)/100000 -> 0.01002 | F12: =(F35+F58+F81+F104+F127+F150+F173+F196+F219+F242+F265+F288+F311+F334+F357+F380+F403+F426+F449+F472)/100000 -> 1.1887 | G12: =AVERAGE(B12:D12) -> 0.62871667 | H12: =(H35+H58+H81+H104+H127+H150+H173+H196+H219+H242+H265+H288+H311+H334+H357+H380+H403+H426+H449+H472)/100000 -> 1.29518 | I12: =(I35+I58+I81+I104+I127+I150+I173+I196+I219+I242+I265+I288+I311+I334+I357+I380+I403+I426+I449+I472)/100000 -> 0.6137 | J12: =(J35+J58+J81+J104+J127+J150+J173+J196+J219+J242+J265+J288+J311+J334+J357+J380+J403+J426+J449+J472)/100000 -> 0 | K12: =(K35+K58+K81+K104+K127+K150+K173+K196+K219+K242+K265+K288+K311+K334+K357+K380+K403+K426+K449+K472)/100000 -> 0 | L12: =(L35+L58+L81+L104+L127+L150+L173+L196+L219+L242+L265+L288+L311+L334+L357+L380+L403+L426+L449+L472)/100000 -> 0 | M12: =(M35+M58+M81+M104+M127+M150+M173+M196+M219+M242+M265+M288+M311+M334+M357+M380+M403+M426+M449+M472)/100000 -> 0 | N12: =(N35+N58+N81+N104+N127+N150+N173+N196+N219+N242+N265+N288+N311+N334+N357+N380+N403+N426+N449+N472)/100000 -> 0 | O12: =(O35+O58+O81+O104+O127+O150+O173+O196+O219+O242+O265+O288+O311+O334+O357+O380+O403+O426+O449+O472)/100000 -> 0 | P12: =(P35+P58+P81+P104+P127+P150+P173+P196+P219+P242+P265+P288+P311+P334+P357+P380+P403+P426+P449+P472)/100000 -> 0.68148 | Q12: =(Q35+Q58+Q81+Q104+Q127+Q150+Q173+Q196+Q219+Q242+Q265+Q288+Q311+Q334+Q357+Q380+Q403+Q426+Q449+Q472) -> 0 | R12: =(R35+R58+R81+R104+R127+R150+R173+R196+R219+R242+R265+R288+R311+R334+R357+R380+R403+R426+R449+R472) -> 0 | S12: =(S35+S58+S81+S104+S127+S150+S173+S196+S219+S242+S265+S288+S311+S334+S357+S380+S403+S426+S449+S472) -> 4 | T12: =(T35+T58+T81+T104+T127+T150+T173+T196+T219+T242+T265+T288+T311+T334+T357+T380+T403+T426+T449+T472) -> 39 | U12: =(U35+U58+U81+U104+U127+U150+U173+U196+U219+U242+U265+U288+U311+U334+U357+U380+U403+U426+U449+U472)/100000 -> 1.29518 | V12: =(V35+V58+V81+V104+V127+V150+V173+V196+V219+V242+V265+V288+V311+V334+V357+V380+V403+V426+V449+V472)/100000 -> 0.6137
A13: =IF($A$36="","",$A$36) -> 45261 | B13: =(B36+B59+B82+B105+B128+B151+B174+B197+B220+B243+B266+B289+B312+B335+B358+B381+B404+B427+B450+B473)/100000 -> 0.28662 | C13: =(C36+C59+C82+C105+C128+C151+C174+C197+C220+C243+C266+C289+C312+C335+C358+C381+C404+C427+C450+C473)/100000 -> 0.11742 | D13: =(D36+D59+D82+D105+D128+D151+D174+D197+D220+D243+D266+D289+D312+D335+D358+D381+D404+D427+D450+D473)/100000 -> 1.03395 | E13: =(E36+E59+E82+E105+E128+E151+E174+E197+E220+E243+E266+E289+E312+E335+E358+E381+E404+E427+E450+E473)/100000 -> 0.09223 | F13: =(F36+F59+F82+F105+F128+F151+F174+F197+F220+F243+F266+F289+F312+F335+F358+F381+F404+F427+F450+F473)/100000 -> 1.03913 | G13: =AVERAGE(B13:D13) -> 0.47933 | H13: =(H36+H59+H82+H105+H128+H151+H174+H197+H220+H243+H266+H289+H312+H335+H358+H381+H404+H427+H450+H473)/100000 -> 0.51236 | I13: =(I36+I59+I82+I105+I128+I151+I174+I197+I220+I243+I266+I289+I312+I335+I358+I381+I404+I427+I450+I473)/100000 -> 0.66342 | J13: =(J36+J59+J82+J105+J128+J151+J174+J197+J220+J243+J266+J289+J312+J335+J358+J381+J404+J427+J450+J473)/100000 -> 0 | K13: =(K36+K59+K82+K105+K128+K151+K174+K197+K220+K243+K266+K289+K312+K335+K358+K381+K404+K427+K450+K473)/100000 -> 0 | L13: =(L36+L59+L82+L105+L128+L151+L174+L197+L220+L243+L266+L289+L312+L335+L358+L381+L404+L427+L450+L473)/100000 -> 0 | M13: =(M36+M59+M82+M105+M128+M151+M174+M197+M220+M243+M266+M289+M312+M335+M358+M381+M404+M427+M450+M473)/100000 -> 0 | N13: =(N36+N59+N82+N105+N128+N151+N174+N197+N220+N243+N266+N289+N312+N335+N358+N381+N404+N427+N450+N473)/100000 -> 0 | O13: =(O36+O59+O82+O105+O128+O151+O174+O197+O220+O243+O266+O289+O312+O335+O358+O381+O404+O427+O450+O473)/100000 -> 0 | P13: =(P36+P59+P82+P105+P128+P151+P174+P197+P220+P243+P266+P289+P312+P335+P358+P381+P404+P427+P450+P473)/100000 -> -0.15106 | Q13: =(Q36+Q59+Q82+Q105+Q128+Q151+Q174+Q197+Q220+Q243+Q266+Q289+Q312+Q335+Q358+Q381+Q404+Q427+Q450+Q473) -> 0 | R13: =(R36+R59+R82+R105+R128+R151+R174+R197+R220+R243+R266+R289+R312+R335+R358+R381+R404+R427+R450+R473) -> 0 | S13: =(S36+S59+S82+S105+S128+S151+S174+S197+S220+S243+S266+S289+S312+S335+S358+S381+S404+S427+S450+S473) -> 5 | T13: =(T36+T59+T82+T105+T128+T151+T174+T197+T220+T243+T266+T289+T312+T335+T358+T381+T404+T427+T450+T473) -> 80 | U13: =(U36+U59+U82+U105+U128+U151+U174+U197+U220+U243+U266+U289+U312+U335+U358+U381+U404+U427+U450+U473)/100000 -> 0.51236 | V13: =(V36+V59+V82+V105+V128+V151+V174+V197+V220+V243+V266+V289+V312+V335+V358+V381+V404+V427+V450+V473)/100000 -> 0.66342
A14: =IF($A$37="","",$A$37) -> 45292 | B14: =(B37+B60+B83+B106+B129+B152+B175+B198+B221+B244+B267+B290+B313+B336+B359+B382+B405+B428+B451+B474)/100000 -> 0.97388 | C14: =(C37+C60+C83+C106+C129+C152+C175+C198+C221+C244+C267+C290+C313+C336+C359+C382+C405+C428+C451+C474)/100000 -> 11.10255 | D14: =(D37+D60+D83+D106+D129+D152+D175+D198+D221+D244+D267+D290+D313+D336+D359+D382+D405+D428+D451+D474)/100000 -> 9.98729 | E14: =(E37+E60+E83+E106+E129+E152+E175+E198+E221+E244+E267+E290+E313+E336+E359+E382+E405+E428+E451+E474)/100000 -> 0.00825 | F14: =(F37+F60+F83+F106+F129+F152+F175+F198+F221+F244+F267+F290+F313+F336+F359+F382+F405+F428+F451+F474)/100000 -> 1.5200591 | G14: =AVERAGE(B14:D14) -> 7.3545733 | H14: =(H37+H60+H83+H106+H129+H152+H175+H198+H221+H244+H267+H290+H313+H336+H359+H382+H405+H428+H451+H474)/100000 -> 13.73901 | I14: =(I37+I60+I83+I106+I129+I152+I175+I198+I221+I244+I267+I290+I313+I336+I359+I382+I405+I428+I451+I474)/100000 -> 2.72157 | J14: =(J37+J60+J83+J106+J129+J152+J175+J198+J221+J244+J267+J290+J313+J336+J359+J382+J405+J428+J451+J474)/100000 -> 0 | K14: =(K37+K60+K83+K106+K129+K152+K175+K198+K221+K244+K267+K290+K313+K336+K359+K382+K405+K428+K451+K474)/100000 -> 0 | L14: =(L37+L60+L83+L106+L129+L152+L175+L198+L221+L244+L267+L290+L313+L336+L359+L382+L405+L428+L451+L474)/100000 -> 0 | M14: =(M37+M60+M83+M106+M129+M152+M175+M198+M221+M244+M267+M290+M313+M336+M359+M382+M405+M428+M451+M474)/100000 -> 0 | N14: =(N37+N60+N83+N106+N129+N152+N175+N198+N221+N244+N267+N290+N313+N336+N359+N382+N405+N428+N451+N474)/100000 -> 0 | O14: =(O37+O60+O83+O106+O129+O152+O175+O198+O221+O244+O267+O290+O313+O336+O359+O382+O405+O428+O451+O474)/100000 -> 0 | P14: =(P37+P60+P83+P106+P129+P152+P175+P198+P221+P244+P267+P290+P313+P336+P359+P382+P405+P428+P451+P474)/100000 -> 11.01744 | Q14: =(Q37+Q60+Q83+Q106+Q129+Q152+Q175+Q198+Q221+Q244+Q267+Q290+Q313+Q336+Q359+Q382+Q405+Q428+Q451+Q474) -> 0 | R14: =(R37+R60+R83+R106+R129+R152+R175+R198+R221+R244+R267+R290+R313+R336+R359+R382+R405+R428+R451+R474) -> 0 | S14: =(S37+S60+S83+S106+S129+S152+S175+S198+S221+S244+S267+S290+S313+S336+S359+S382+S405+S428+S451+S474) -> 15 | T14: =(T37+T60+T83+T106+T129+T152+T175+T198+T221+T244+T267+T290+T313+T336+T359+T382+T405+T428+T451+T474) -> 55 | U14: =(U37+U60+U83+U106+U129+U152+U175+U198+U221+U244+U267+U290+U313+U336+U359+U382+U405+U428+U451+U474)/100000 -> 13.73901 | V14: =(V37+V60+V83+V106+V129+V152+V175+V198+V221+V244+V267+V290+V313+V336+V359+V382+V405+V428+V451+V474)/100000 -> 2.72157
A15: =IF($A$38="","",$A$38) -> 45323 | B15: =(B38+B61+B84+B107+B130+B153+B176+B199+B222+B245+B268+B291+B314+B337+B360+B383+B406+B429+B452+B475)/100000 -> 9.69705 | C15: =(C38+C61+C84+C107+C130+C153+C176+C199+C222+C245+C268+C291+C314+C337+C360+C383+C406+C429+C452+C475)/100000 -> 9.6034 | D15: =(D38+D61+D84+D107+D130+D153+D176+D199+D222+D245+D268+D291+D314+D337+D360+D383+D406+D429+D452+D475)/100000 -> 8.93547 | E15: =(E38+E61+E84+E107+E130+E153+E176+E199+E222+E245+E268+E291+E314+E337+E360+E383+E406+E429+E452+E475)/100000 -> 8.71525 | F15: =(F38+F61+F84+F107+F130+F153+F176+F199+F222+F245+F268+F291+F314+F337+F360+F383+F406+F429+F452+F475)/100000 -> 10.023552 | G15: =AVERAGE(B15:D15) -> 9.4119733 | H15: =(H38+H61+H84+H107+H130+H153+H176+H199+H222+H245+H268+H291+H314+H337+H360+H383+H406+H429+H452+H475)/100000 -> 1.09551 | I15: =(I38+I61+I84+I107+I130+I153+I176+I199+I222+I245+I268+I291+I314+I337+I360+I383+I406+I429+I452+I475)/100000 -> 2.22854 | J15: =(J38+J61+J84+J107+J130+J153+J176+J199+J222+J245+J268+J291+J314+J337+J360+J383+J406+J429+J452+J475)/100000 -> 0 | K15: =(K38+K61+K84+K107+K130+K153+K176+K199+K222+K245+K268+K291+K314+K337+K360+K383+K406+K429+K452+K475)/100000 -> 0 | L15: =(L38+L61+L84+L107+L130+L153+L176+L199+L222+L245+L268+L291+L314+L337+L360+L383+L406+L429+L452+L475)/100000 -> 0 | M15: =(M38+M61+M84+M107+M130+M153+M176+M199+M222+M245+M268+M291+M314+M337+M360+M383+M406+M429+M452+M475)/100000 -> 0 | N15: =(N38+N61+N84+N107+N130+N153+N176+N199+N222+N245+N268+N291+N314+N337+N360+N383+N406+N429+N452+N475)/100000 -> 0 | O15: =(O38+O61+O84+O107+O130+O153+O176+O199+O222+O245+O268+O291+O314+O337+O360+O383+O406+O429+O452+O475)/100000 -> 0 | P15: =(P38+P61+P84+P107+P130+P153+P176+P199+P222+P245+P268+P291+P314+P337+P360+P383+P406+P429+P452+P475)/100000 -> -1.13303 | Q15: =(Q38+Q61+Q84+Q107+Q130+Q153+Q176+Q199+Q222+Q245+Q268+Q291+Q314+Q337+Q360+Q383+Q406+Q429+Q452+Q475) -> 0 | R15: =(R38+R61+R84+R107+R130+R153+R176+R199+R222+R245+R268+R291+R314+R337+R360+R383+R406+R429+R452+R475) -> 0 | S15: =(S38+S61+S84+S107+S130+S153+S176+S199+S222+S245+S268+S291+S314+S337+S360+S383+S406+S429+S452+S475) -> 7 | T15: =(T38+T61+T84+T107+T130+T153+T176+T199+T222+T245+T268+T291+T314+T337+T360+T383+T406+T429+T452+T475) -> 49 | U15: =(U38+U61+U84+U107+U130+U153+U176+U199+U222+U245+U268+U291+U314+U337+U360+U383+U406+U429+U452+U475)/100000 -> 1.09551 | V15: =(V38+V61+V84+V107+V130+V153+V176+V199+V222+V245+V268+V291+V314+V337+V360+V383+V406+V429+V452+V475)/100000 -> 2.22854
A16: Total | B16: =+SUM(B4:B15) -> 11.39659 | C16: =+SUM(C4:C15) -> 22.15294 | D16: =+SUM(D4:D15) -> 20.74555 | E16: =+SUM(E4:E15) -> 8.93099 | F16: =+SUM(F4:F15) -> 14.294441 | G16: =+SUM(G4:G15) -> 18.09836 | H16: =+SUM(H4:H15) -> 16.77362 | I16: =+SUM(I4:I15) -> 6.88306 | ... V16: =+SUM(V4:V15) -> 6.88306
A17: Average | B17: =IFERROR(B16/(COUNTA(A4:A15)-COUNTIF(A4:A15,"")),0) -> 0.94971583 | C17: =IFERROR(C16/(COUNTA(A4:A15)-COUNTIF(A4:A15,"")),0) -> 1.8460783 | D17: =IFERROR(D16/(COUNTA(A4:A15)-COUNTIF(A4:A15,"")),0) -> 1.7287958 | E17: =IFERROR(E16/(COUNTA(A4:A15)-COUNTIF(A4:A15,"")),0) -> 0.74424917 | F17: =IFERROR(F16/(COUNTA(A4:A15)-COUNTIF(A4:A15,"")),0) -> 1.1912034 | G17: =IFERROR(G16/(COUNTA(A4:A15)-COUNTIF(A4:A15,"")),0) -> 1.5081967 | H17: =IFERROR(H16/(COUNTA(A4:A15)-COUNTIF(A4:A15,"")),0) -> 1.3978017 | I17: =IFERROR(I16/(COUNTA(A4:A15)-COUNTIF(A4:A15,"")),0) -> 0.57358833 | J17: =IFERROR(J16/(COUNTA(A4:A15)-COUNTIF(A4:A15,"")),0) -> 0 | K17: =IFERROR(K16/(COUNTA(A4:A15)-COUNTIF(A4:A15,"")),0) -> 0 | L17: =IFERROR(L16/(COUNTA(A4:A15)-COUNTIF(A4:A15,"")),0) -> 0 | M17: =IFERROR(M16/(COUNTA(A4:A15)-COUNTIF(A4:A15,"")),0) -> 0 | N17: =IFERROR(N16/(COUNTA(A4:A15)-COUNTIF(A4:A15,"")),0) -> 0 | O17: =IFERROR(O16/(COUNTA(A4:A15)-COUNTIF(A4:A15,"")),0) -> 0 | P17: =IFERROR(P16/(COUNTA(A4:A15)-COUNTIF(A4:A15,"")),0) -> 0.82421333 | S17: =IFERROR(R16/S16*100,0) -> 0 | T17: =IFERROR(Q16/T16*100,0) -> 0 | U17: =IFERROR(U16/(COUNTA(A4:A15)-COUNTIF(A4:A15,"")),0) -> 1.3978017 | V17: =IFERROR(V16/(COUNTA(A4:A15)-COUNTIF(A4:A15,"")),0) -> 0.57358833
A18: Unutilized Limit (CC/OD) | B18: =IFERROR((B41+B64+B87+B110+B133+B156+B179+B202+B225+B248+B271+B294+B317+B340+B363+B386+B409+B432+B455+B478)/100000,0) -> 0.94971583 | C18: =IFERROR((C41+C64+C87+C110+C133+C156+C179+C202+C225+C248+C271+C294+C317+C340+C363+C386+C409+C432+C455+C478)/100000,0) -> 1.8460783 | D18: =IFERROR((D41+D64+D87+D110+D133+D156+D179+D202+D225+D248+D271+D294+D317+D340+D363+D386+D409+D432+D455+D478)/100000,0) -> 1.7287958 | G18: =IFERROR((G41+G64+G87+G110+G133+G156+G179+G202+G225+G248+G271+G294+G317+G340+G363+G386+G409+G432+G455+G478)/100000,0) -> 1.5081967 | S18: O/w Return Ratio | T18: I/w Return Ratio
A22: Name of Customer | C22: MR. KANHAIYA BHARTI
A23: Name of Bank | C23: STATE BANK OF INDIA | H23: Branch Name
A24: A/c Type (Select from Dropdown) | C24: Savings | E24: A/c Number | F24: 00000031272798836 | J24: Period | N24: Limit (CC/OD)
A25: Month | B25: Balance / Utilization on date (Rs.) | E25: Min Balance of the month (Rs.) | F25: Max Balance of the month (Rs.) | G25: Average (Rs.) | H25: Total Inflows (Rs.) | I25: Total Outflows (Rs.) | J25: Loan Disbursal incl in Inflows (Rs.) | K25: Interest (debited) / credited (Rs.) | L25: Intra Group transaction value included (Rs.) | N25: Cash Entry Value (Rs.) | P25: Net Flow (Rs.) | Q25: No. of I/W Return | R25: No. of O/W Return | S25: No. of Credit Entries | T25: No. of Debit Entries | U25: Net Inflows (Rs.) | V25: Net Outflows (Rs.)
B26: 10 | C26: 20 | D26: 30 | L26: Debit | M26: Credit | N26: Debit | O26: Credit
A27: 44986 | G27: =IFERROR(AVERAGE(B27:D27),0) -> 0 | P27: =+H27-I27-J27-M27+L27 -> 0 | U27: =H27-J27-M27 -> 0 | V27: =I27-L27 -> 0
A28: 45017 | G28: =IFERROR(AVERAGE(B28:D28),0) -> 0 | P28: =+H28-I28-J28-M28+L28 -> 0 | U28: =H28-J28-M28 -> 0 | V28: =I28-L28 -> 0
A29: 45047 | G29: =IFERROR(AVERAGE(B29:D29),0) -> 0 | P29: =+H29-I29-J29-M29+L29 -> 0 | U29: =H29-J29-M29 -> 0 | V29: =I29-L29 -> 0
A30: 45078 | G30: =IFERROR(AVERAGE(B30:D30),0) -> 0 | P30: =+H30-I30-J30-M30+L30 -> 0 | U30: =H30-J30-M30 -> 0 | V30: =I30-L30 -> 0
A31: 45108 | G31: =IFERROR(AVERAGE(B31:D31),0) -> 0 | P31: =+H31-I31-J31-M31+L31 -> 0 | U31: =H31-J31-M31 -> 0 | V31: =I31-L31 -> 0
A32: 45139 | G32: =IFERROR(AVERAGE(B32:D32),0) -> 0 | P32: =+H32-I32-J32-M32+L32 -> 0 | U32: =H32-J32-M32 -> 0 | V32: =I32-L32 -> 0
A33: 45170 | B33: 30118 | C33: 12604 | D33: 10440 | E33: 10439 | F33: 39768 | G33: =IFERROR(AVERAGE(B33:D33),0) -> 17720.667 | H33: =656 -> 656 | I33: =2000+19+140+323+10+180+100+181+70+80+100+3000+312+125+120+70+52+50+180+40+19+105+35+100+200+700+90+30+40+60+1400+4600+160+80+120+130+320+70+90+160+200+200+150+50+700+75+70+70+100+110+140+298+100+200+5000+320+80+20+800+19+185+323+120+104+100+100+350+200+100 -> 25945 | P33: =+H33-I33-J33-M33+L33 -> -25289 | S33: 1 | T33: 69 | U33: =H33-J33-M33 -> 656 | V33: =I33-L33 -> 25945
A34: 45200 | B34: 12128 | C34: 1682 | D34: 158 | E34: 85 | F34: 12532 | G34: =IFERROR(AVERAGE(B34:D34),0) -> 4656 | H34: =2000+5000+2000+3000+100+400 -> 12500 | I34: =150+200+350+140+70+565+30+50+130+40+200+580+19+400+500+200+690+50+5800+112+60+150+60+1500+80+170+50+475+16+55+70+70+40+150+20+7600+70+150+16+7600+70+150+16+30+70+500+19+50+800+30+300+80+800+300+60+140+30+60+610+80+0+16+150+306+500+50+80+25+16+70+19+542+323+19+10+50+300+19+0+60+55+25+70+16+170+2756+40+50+15+165+60+127+100+542+19 -> 39638 | P34: =+H34-I34-J34-M34+L34 -> -27138 | S34: 6 | T34: 95 | U34: =H34-J34-M34 -> 12500 | V34: =I34-L34 -> 39638
A35: 45231 | B35: 1658 | C35: 118671 | D35: 68286 | E35: 1002 | F35: 118870 | G35: =IFERROR(AVERAGE(B35:D35),0) -> 62871.667 | H35: =9500+4500+2000+113518 -> 129518 | I35: =1500+3500+3000+32+70+120+433+340+680+225+105+70+30+700+200+235+4000+800+7600+6000+4200+1500+9700+5000+110+70+9800+50+25+100+40+180+70+300+50+30+120+55+330 -> 61370 | P35: =+H35-I35-J35-M35+L35 -> 68148 | S35: 4 | T35: 39 | U35: =H35-J35-M35 -> 129518 | V35: =I35-L35 -> 61370
A36: 45261 | B36: 28662 | C36: 11742 | D36: 103395 | E36: 9223 | F36: 103913 | G36: =IFERROR(AVERAGE(B36:D36),0) -> 47933 | H36: =1000+300+300+136+49500 -> 51236 | I36: =750+90+50+100+1360+50+50+700+19+150+130+100+120+7000+1650+110+4700+70+50+300+19500+120+385+70+50+280+4600+1360+1226+200+542+353+230+80+70+320+90+45+90+50+4300+1000+81+25+16+542+210+70+542+210+60+10+110+30+60+70+30+140+70+30+40+30+120+410+50+16+12+75+70+220+20+50+50+1+8562+280+50+260+780+430 -> 66342 | P36: =+H36-I36-J36-M36+L36 -> -15106 | S36: 5 | T36: 80 | U36: =H36-J36-M36 -> 51236 | V36: =I36-L36 -> 66342
A37: 45292 | B37: 97388 | C37: 1110255 | D37: 998729 | E37: 825 | F37: 152005.91 | G37: =IFERROR(AVERAGE(B37:D37),0) -> 735457.33 | H37: =400+49500+1500+48500+46000+3000+2500+48500+46000+3000+2500+14500+1+58000+1050000 -> 1373901 | I37: =80+1000+340+100+40+70+125+114+100+80+0+30+70+375+220+70+20+150000+100+45+25+25+25+2120+320+700+90+130+25+25+25+2120+320+700+90+130+351+236+116+200+80+200+120+260+200+2850+5000+19+99000+19+40+3000+10+588+19 -> 272157 | P37: =+H37-I37-J37-M37+L37 -> 1101744 | S37: 15 | T37: 55 | U37: =H37-J37-M37 -> 1373901 | V37: =I37-L37 -> 272157
A38: 45323 | B38: 969705 | C38: 960340 | D38: 893547 | E38: 871525 | F38: 1002355.2 | G38: =IFERROR(AVERAGE(B38:D38),0) -> 941197.33 | H38: =1+8000+50+50000+500+49000+2000 -> 109551 | I38: =1000+7600+149+3000+375+1000+450+95000+60+40+100+80+100+35000+50+1+19+542+500+30+17+280+7600+542+330+350+32+70+30+20+83+19+330+750+180+75+90+40+375+91+60+197+5+50000+375+647+70+15000+100 -> 222854 | P38: =+H38-I38-J38-M38+L38 -> -113303 | S38: 7 | T38: 49 | U38: =H38-J38-M38 -> 109551 | V38: =I38-L38 -> 222854
A39: Total | B39: =+SUM(B27:B38) -> 1139659 | C39: =+SUM(C27:C38) -> 2215294 | D39: =+SUM(D27:D38) -> 2074555 | E39: =+SUM(E27:E38) -> 893099 | F39: =+SUM(F27:F38) -> 1429444.1 | G39: =+SUM(G27:G38) -> 1809836 | H39: =+SUM(H27:H38) -> 1677362 | I39: =+SUM(I27:I38) -> 688306 | ... V39: =+SUM(V27:V38) -> 688306
A40: Average | B40: =IFERROR(B39/(12-COUNTIF(A27:A38,"")),0) -> 94971.583 | C40: =IFERROR(C39/(12-COUNTIF(A27:A38,"")),0) -> 184607.83 | D40: =IFERROR(D39/(12-COUNTIF(A27:A38,"")),0) -> 172879.58 | E40: =IFERROR(E39/(12-COUNTIF(A27:A38,"")),0) -> 74424.917 | F40: =IFERROR(F39/(12-COUNTIF(A27:A38,"")),0) -> 119120.34 | G40: =IFERROR(G39/(12-COUNTIF(A27:A38,"")),0) -> 150819.67 | H40: =IFERROR(H39/(12-COUNTIF(A27:A38,"")),0) -> 139780.17 | I40: =IFERROR(I39/(12-COUNTIF(A27:A38,"")),0) -> 57358.833 | J40: =IFERROR(J39/(12-COUNTIF(A27:A38,"")),0) -> 0 | K40: =IFERROR(K39/(12-COUNTIF(A27:A38,"")),0) -> 0 | L40: =IFERROR(L39/(12-COUNTIF(A27:A38,"")),0) -> 0 | M40: =IFERROR(M39/(12-COUNTIF(A27:A38,"")),0) -> 0 | N40: =IFERROR(N39/(12-COUNTIF(A27:A38,"")),0) -> 0 | O40: =IFERROR(O39/(12-COUNTIF(A27:A38,"")),0) -> 0 | P40: =IFERROR(P39/(12-COUNTIF(A27:A38,"")),0) -> 82421.333 | S40: =IFERROR(R39/S39*100,0) -> 0 | T40: =IFERROR(Q39/T39*100,0) -> 0 | U40: =IFERROR(U39/(12-COUNTIF(A27:A38,"")),0) -> 139780.17 | V40: =IFERROR(V39/(12-COUNTIF(A27:A38,"")),0) -> 57358.833
A41: Unutilized Limit (CC/OD) | B41: =O24+B40 -> 94971.583 | C41: =O24+C40 -> 184607.83 | D41: =O24+D40 -> 172879.58 | G41: =O24+G40 -> 150819.67 | S41: O/w Return Ratio | T41: I/w Return Ratio
A45: Name of Customer
A46: Name of Bank | H46: Branch Name
A47: A/c Type (Select from Dropdown) | E47: A/c Number | J47: Period | N47: Limit (CC/OD)
A48: Month | B48: Balance / Utilization on date (Rs.) | E48: Min Balance of the month (Rs.) | F48: Max Balance of the month (Rs.) | G48: Average (Rs.) | H48: Total Inflows (Rs.) | I48: Total Outflows (Rs.) | J48: Loan Disbursal incl in Inflows (Rs.) | K48: Interest (debited) / credited (Rs.) | L48: Intra Group transaction value included (Rs.) | N48: Cash Entry Value (Rs.) | P48: Net Flow (Rs.) | Q48: No. of I/W Return | R48: No. of O/W Return | S48: No. of Credit Entries | T48: No. of Debit Entries | U48: Net Inflows (Rs.) | V48: Net Outflows (Rs.)
B49: 10 | C49: 20 | D49: 30 | L49: Debit | M49: Credit | N49: Debit | O49: Credit
A50: =IF($A$27="","",$A$27) -> 44986 | G50: =IFERROR(AVERAGE(B50:D50),0) -> 0 | P50: =+H50-I50-J50-M50+L50 -> 0 | U50: =H50-J50-M50 -> 0 | V50: =I50-L50 -> 0
A51: =IF($A$28="","",$A$28) -> 45017 | G51: =IFERROR(AVERAGE(B51:D51),0) -> 0 | P51: =+H51-I51-J51-M51+L51 -> 0 | U51: =H51-J51-M51 -> 0 | V51: =I51-L51 -> 0
A52: =IF($A$29="","",$A$29) -> 45047 | G52: =IFERROR(AVERAGE(B52:D52),0) -> 0 | P52: =+H52-I52-J52-M52+L52 -> 0 | U52: =H52-J52-M52 -> 0 | V52: =I52-L52 -> 0
A53: =IF($A$30="","",$A$30) -> 45078 | G53: =IFERROR(AVERAGE(B53:D53),0) -> 0 | P53: =+H53-I53-J53-M53+L53 -> 0 | U53: =H53-J53-M53 -> 0 | V53: =I53-L53 -> 0
A54: =IF($A$31="","",$A$31) -> 45108 | G54: =IFERROR(AVERAGE(B54:D54),0) -> 0 | P54: =+H54-I54-J54-M54+L54 -> 0 | U54: =H54-J54-M54 -> 0 | V54: =I54-L54 -> 0
A55: =IF($A$32="","",$A$32) -> 45139 | G55: =IFERROR(AVERAGE(B55:D55),0) -> 0 | P55: =+H55-I55-J55-M55+L55 -> 0 | U55: =H55-J55-M55 -> 0 | V55: =I55-L55 -> 0
A56: =IF($A$33="","",$A$33) -> 45170 | G56: =IFERROR(AVERAGE(B56:D56),0) -> 0 | P56: =+H56-I56-J56-M56+L56 -> 0 | U56: =H56-J56-M56 -> 0 | V56: =I56-L56 -> 0
A57: =IF($A$34="","",$A$34) -> 45200 | G57: =IFERROR(AVERAGE(B57:D57),0) -> 0 | P57: =+H57-I57-J57-M57+L57 -> 0 | U57: =H57-J57-M57 -> 0 | V57: =I57-L57 -> 0
A58: =IF($A$35="","",$A$35) -> 45231 | G58: =IFERROR(AVERAGE(B58:D58),0) -> 0 | P58: =+H58-I58-J58-M58+L58 -> 0 | U58: =H58-J58-M58 -> 0 | V58: =I58-L58 -> 0
A59: =IF($A$36="","",$A$36) -> 45261 | G59: =IFERROR(AVERAGE(B59:D59),0) -> 0 | P59: =+H59-I59-J59-M59+L59 -> 0 | U59: =H59-J59-M59 -> 0 | V59: =I59-L59 -> 0
A60: =IF($A$37="","",$A$37) -> 45292 | G60: =IFERROR(AVERAGE(B60:D60),0) -> 0 | P60: =+H60-I60-J60-M60+L60 -> 0 | U60: =H60-J60-M60 -> 0 | V60: =I60-L60 -> 0
A61: =IF($A$38="","",$A$38) -> 45323 | G61: =IFERROR(AVERAGE(B61:D61),0) -> 0 | P61: =+H61-I61-J61-M61+L61 -> 0 | U61: =H61-J61-M61 -> 0 | V61: =I61-L61 -> 0
A62: Total | B62: =+SUM(B50:B61) -> 0 | C62: =+SUM(C50:C61) -> 0 | D62: =+SUM(D50:D61) -> 0 | E62: =+SUM(E50:E61) -> 0 | F62: =+SUM(F50:F61) -> 0 | G62: =+SUM(G50:G61) -> 0 | H62: =+SUM(H50:H61) -> 0 | I62: =+SUM(I50:I61) -> 0 | ... V62: =+SUM(V50:V61) -> 0
A63: Average | B63: =IFERROR(B62/(COUNTA(A50:A61)-COUNTIF(A50:A61,"")),0) -> 0 | C63: =IFERROR(C62/(COUNTA(A50:A61)-COUNTIF(A50:A61,"")),0) -> 0 | D63: =IFERROR(D62/(COUNTA(A50:A61)-COUNTIF(A50:A61,"")),0) -> 0 | E63: =IFERROR(E62/(COUNTA(A50:A61)-COUNTIF(A50:A61,"")),0) -> 0 | F63: =IFERROR(F62/(COUNTA(A50:A61)-COUNTIF(A50:A61,"")),0) -> 0 | G63: =IFERROR(G62/(COUNTA(A50:A61)-COUNTIF(A50:A61,"")),0) -> 0 | H63: =IFERROR(H62/(COUNTA(A50:A61)-COUNTIF(A50:A61,"")),0) -> 0 | I63: =IFERROR(I62/(COUNTA(A50:A61)-COUNTIF(A50:A61,"")),0) -> 0 | J63: =IFERROR(J62/(COUNTA(A50:A61)-COUNTIF(A50:A61,"")),0) -> 0 | K63: =IFERROR(K62/(COUNTA(A50:A61)-COUNTIF(A50:A61,"")),0) -> 0 | L63: =IFERROR(L62/(COUNTA(A50:A61)-COUNTIF(A50:A61,"")),0) -> 0 | M63: =IFERROR(M62/(COUNTA(A50:A61)-COUNTIF(A50:A61,"")),0) -> 0 | N63: =IFERROR(N62/(COUNTA(A50:A61)-COUNTIF(A50:A61,"")),0) -> 0 | O63: =IFERROR(O62/(COUNTA(A50:A61)-COUNTIF(A50:A61,"")),0) -> 0 | P63: =IFERROR(P62/(COUNTA(A50:A61)-COUNTIF(A50:A61,"")),0) -> 0 | S63: =IFERROR(R62/S62*100,0) -> 0 | T63: =IFERROR(Q62/T62*100,0) -> 0 | U63: =IFERROR(U62/COUNTA(A50:A61),0) -> 0 | V63: =IFERROR(V62/COUNTA(A50:A61),0) -> 0
A64: Unutilized Limit (CC/OD) | B64: =O47+B63 -> 0 | C64: =O47+C63 -> 0 | D64: =O47+D63 -> 0 | G64: =O47+G63 -> 0 | S64: O/w Return Ratio | T64: I/w Return Ratio
A68: Name of Customer
A69: Name of Bank | H69: Branch Name
A70: A/c Type (Select from Dropdown) | E70: A/c Number | J70: Period | N70: Limit (CC/OD)
A71: Month | B71: Balance / Utilization on date (Rs.) | E71: Min Balance of the month (Rs.) | F71: Max Balance of the month (Rs.) | G71: Average (Rs.) | H71: Total Inflows (Rs.) | I71: Total Outflows (Rs.) | J71: Loan Disbursal incl in Inflows (Rs.) | K71: Interest (debited) / credited (Rs.) | L71: Intra Group transaction value included (Rs.) | N71: Cash Entry Value (Rs.) | P71: Net Flow (Rs.) | Q71: No. of I/W Return | R71: No. of O/W Return | S71: No. of Credit Entries | T71: No. of Debit Entries | U71: Net Inflows (Rs.) | V71: Net Outflows (Rs.)
B72: 10 | C72: 20 | D72: 30 | L72: Debit | M72: Credit | N72: Debit | O72: Credit
A73: =IF($A$27="","",$A$27) -> 44986 | G73: =IFERROR(AVERAGE(B73:D73),0) -> 0 | P73: =+H73-I73-J73-M73+L73 -> 0 | U73: =H73-J73-M73 -> 0 | V73: =I73-L73 -> 0
A74: =IF($A$28="","",$A$28) -> 45017 | G74: =IFERROR(AVERAGE(B74:D74),0) -> 0 | P74: =+H74-I74-J74-M74+L74 -> 0 | U74: =H74-J74-M74 -> 0 | V74: =I74-L74 -> 0
A75: =IF($A$29="","",$A$29) -> 45047 | G75: =IFERROR(AVERAGE(B75:D75),0) -> 0 | P75: =+H75-I75-J75-M75+L75 -> 0 | U75: =H75-J75-M75 -> 0 | V75: =I75-L75 -> 0
A76: =IF($A$30="","",$A$30) -> 45078 | G76: =IFERROR(AVERAGE(B76:D76),0) -> 0 | P76: =+H76-I76-J76-M76+L76 -> 0 | U76: =H76-J76-M76 -> 0 | V76: =I76-L76 -> 0
A77: =IF($A$31="","",$A$31) -> 45108 | G77: =IFERROR(AVERAGE(B77:D77),0) -> 0 | P77: =+H77-I77-J77-M77+L77 -> 0 | U77: =H77-J77-M77 -> 0 | V77: =I77-L77 -> 0
A78: =IF($A$32="","",$A$32) -> 45139 | G78: =IFERROR(AVERAGE(B78:D78),0) -> 0 | P78: =+H78-I78-J78-M78+L78 -> 0 | U78: =H78-J78-M78 -> 0 | V78: =I78-L78 -> 0
A79: =IF($A$33="","",$A$33) -> 45170 | G79: =IFERROR(AVERAGE(B79:D79),0) -> 0 | P79: =+H79-I79-J79-M79+L79 -> 0 | U79: =H79-J79-M79 -> 0 | V79: =I79-L79 -> 0
A80: =IF($A$34="","",$A$34) -> 45200 | G80: =IFERROR(AVERAGE(B80:D80),0) -> 0 | P80: =+H80-I80-J80-M80+L80 -> 0 | U80: =H80-J80-M80 -> 0 | V80: =I80-L80 -> 0
A81: =IF($A$35="","",$A$35) -> 45231 | G81: =IFERROR(AVERAGE(B81:D81),0) -> 0 | P81: =+H81-I81-J81-M81+L81 -> 0 | U81: =H81-J81-M81 -> 0 | V81: =I81-L81 -> 0
A82: =IF($A$36="","",$A$36) -> 45261 | G82: =IFERROR(AVERAGE(B82:D82),0) -> 0 | P82: =+H82-I82-J82-M82+L82 -> 0 | U82: =H82-J82-M82 -> 0 | V82: =I82-L82 -> 0
A83: =IF($A$37="","",$A$37) -> 45292 | G83: =IFERROR(AVERAGE(B83:D83),0) -> 0 | P83: =+H83-I83-J83-M83+L83 -> 0 | U83: =H83-J83-M83 -> 0 | V83: =I83-L83 -> 0
A84: =IF($A$38="","",$A$38) -> 45323 | G84: =IFERROR(AVERAGE(B84:D84),0) -> 0 | P84: =+H84-I84-J84-M84+L84 -> 0 | U84: =H84-J84-M84 -> 0 | V84: =I84-L84 -> 0
A85: Total | B85: =+SUM(B73:B84) -> 0 | C85: =+SUM(C73:C84) -> 0 | D85: =+SUM(D73:D84) -> 0 | E85: =+SUM(E73:E84) -> 0 | F85: =+SUM(F73:F84) -> 0 | G85: =+SUM(G73:G84) -> 0 | H85: =+SUM(H73:H84) -> 0 | I85: =+SUM(I73:I84) -> 0 | ... V85: =+SUM(V73:V84) -> 0
A86: Average | B86: =IFERROR(B85/(COUNTA(A73:A84)-COUNTIF(A73:A84,"")),0) -> 0 | C86: =IFERROR(C85/(COUNTA(A73:A84)-COUNTIF(A73:A84,"")),0) -> 0 | D86: =IFERROR(D85/(COUNTA(A73:A84)-COUNTIF(A73:A84,"")),0) -> 0 | E86: =IFERROR(E85/(COUNTA(A73:A84)-COUNTIF(A73:A84,"")),0) -> 0 | F86: =IFERROR(F85/(COUNTA(A73:A84)-COUNTIF(A73:A84,"")),0) -> 0 | G86: =IFERROR(G85/(COUNTA(A73:A84)-COUNTIF(A73:A84,"")),0) -> 0 | H86: =IFERROR(H85/(COUNTA(A73:A84)-COUNTIF(A73:A84,"")),0) -> 0 | I86: =IFERROR(I85/(COUNTA(A73:A84)-COUNTIF(A73:A84,"")),0) -> 0 | J86: =IFERROR(J85/(COUNTA(A73:A84)-COUNTIF(A73:A84,"")),0) -> 0 | K86: =IFERROR(K85/(COUNTA(A73:A84)-COUNTIF(A73:A84,"")),0) -> 0 | L86: =IFERROR(L85/(COUNTA(A73:A84)-COUNTIF(A73:A84,"")),0) -> 0 | M86: =IFERROR(M85/(COUNTA(A73:A84)-COUNTIF(A73:A84,"")),0) -> 0 | N86: =IFERROR(N85/(COUNTA(A73:A84)-COUNTIF(A73:A84,"")),0) -> 0 | O86: =IFERROR(O85/(COUNTA(A73:A84)-COUNTIF(A73:A84,"")),0) -> 0 | P86: =IFERROR(P85/(COUNTA(A73:A84)-COUNTIF(A73:A84,"")),0) -> 0 | S86: =IFERROR(R85/S85*100,0) -> 0 | T86: =IFERROR(Q85/T85*100,0) -> 0 | U86: =IFERROR(U85/COUNTA(A73:A84),0) -> 0 | V86: =IFERROR(V85/COUNTA(A73:A84),0) -> 0
A87: Unutilized Limit (CC/OD) | B87: =O70+B86 -> 0 | C87: =O70+C86 -> 0 | D87: =O70+D86 -> 0 | G87: =O70+G86 -> 0 | S87: O/w Return Ratio | T87: I/w Return Ratio
A91: Name of Customer
A92: Name of Bank | H92: Branch Name
A93: A/c Type (Select from Dropdown) | E93: A/c Number | J93: Period | N93: Limit (CC/OD)
A94: Month | B94: Balance / Utilization on date (Rs.) | E94: Min Balance of the month (Rs.) | F94: Max Balance of the month (Rs.) | G94: Average (Rs.) | H94: Total Inflows (Rs.) | I94: Total Outflows (Rs.) | J94: Loan Disbursal incl in Inflows (Rs.) | K94: Interest (debited) / credited (Rs.) | L94: Intra Group transaction value included (Rs.) | N94: Cash Entry Value (Rs.) | P94: Net Flow (Rs.) | Q94: No. of I/W Return | R94: No. of O/W Return | S94: No. of Credit Entries | T94: No. of Debit Entries | U94: Net Inflows (Rs.) | V94: Net Outflows (Rs.)
B95: 10 | C95: 20 | D95: 30 | L95: Debit | M95: Credit | N95: Debit | O95: Credit
A96: =IF($A$27="","",$A$27) -> 44986 | G96: =IFERROR(AVERAGE(B96:D96),0) -> 0 | P96: =+H96-I96-J96-M96+L96 -> 0 | U96: =H96-J96-M96 -> 0 | V96: =I96-L96 -> 0
A97: =IF($A$28="","",$A$28) -> 45017 | G97: =IFERROR(AVERAGE(B97:D97),0) -> 0 | P97: =+H97-I97-J97-M97+L97 -> 0 | U97: =H97-J97-M97 -> 0 | V97: =I97-L97 -> 0
A98: =IF($A$29="","",$A$29) -> 45047 | G98: =IFERROR(AVERAGE(B98:D98),0) -> 0 | P98: =+H98-I98-J98-M98+L98 -> 0 | U98: =H98-J98-M98 -> 0 | V98: =I98-L98 -> 0
A99: =IF($A$30="","",$A$30) -> 45078 | G99: =IFERROR(AVERAGE(B99:D99),0) -> 0 | P99: =+H99-I99-J99-M99+L99 -> 0 | U99: =H99-J99-M99 -> 0 | V99: =I99-L99 -> 0
A100: =IF($A$31="","",$A$31) -> 45108 | G100: =IFERROR(AVERAGE(B100:D100),0) -> 0 | P100: =+H100-I100-J100-M100+L100 -> 0 | U100: =H100-J100-M100 -> 0 | V100: =I100-L100 -> 0
A101: =IF($A$32="","",$A$32) -> 45139 | G101: =IFERROR(AVERAGE(B101:D101),0) -> 0 | P101: =+H101-I101-J101-M101+L101 -> 0 | U101: =H101-J101-M101 -> 0 | V101: =I101-L101 -> 0
A102: =IF($A$33="","",$A$33) -> 45170 | G102: =IFERROR(AVERAGE(B102:D102),0) -> 0 | P102: =+H102-I102-J102-M102+L102 -> 0 | U102: =H102-J102-M102 -> 0 | V102: =I102-L102 -> 0
A103: =IF($A$34="","",$A$34) -> 45200 | G103: =IFERROR(AVERAGE(B103:D103),0) -> 0 | P103: =+H103-I103-J103-M103+L103 -> 0 | U103: =H103-J103-M103 -> 0 | V103: =I103-L103 -> 0
A104: =IF($A$35="","",$A$35) -> 45231 | G104: =IFERROR(AVERAGE(B104:D104),0) -> 0 | P104: =+H104-I104-J104-M104+L104 -> 0 | U104: =H104-J104-M104 -> 0 | V104: =I104-L104 -> 0
A105: =IF($A$36="","",$A$36) -> 45261 | G105: =IFERROR(AVERAGE(B105:D105),0) -> 0 | P105: =+H105-I105-J105-M105+L105 -> 0 | U105: =H105-J105-M105 -> 0 | V105: =I105-L105 -> 0
A106: =IF($A$37="","",$A$37) -> 45292 | G106: =IFERROR(AVERAGE(B106:D106),0) -> 0 | P106: =+H106-I106-J106-M106+L106 -> 0 | U106: =H106-J106-M106 -> 0 | V106: =I106-L106 -> 0
A107: =IF($A$38="","",$A$38) -> 45323 | G107: =IFERROR(AVERAGE(B107:D107),0) -> 0 | P107: =+H107-I107-J107-M107+L107 -> 0 | U107: =H107-J107-M107 -> 0 | V107: =I107-L107 -> 0
A108: Total | B108: =+SUM(B96:B107) -> 0 | C108: =+SUM(C96:C107) -> 0 | D108: =+SUM(D96:D107) -> 0 | E108: =+SUM(E96:E107) -> 0 | F108: =+SUM(F96:F107) -> 0 | G108: =+SUM(G96:G107) -> 0 | H108: =+SUM(H96:H107) -> 0 | I108: =+SUM(I96:I107) -> 0 | ... V108: =+SUM(V96:V107) -> 0
A109: Average | B109: =IFERROR(B108/(COUNTA(A96:A107)-COUNTIF(A96:A107,"")),0) -> 0 | C109: =IFERROR(C108/(COUNTA(A96:A107)-COUNTIF(A96:A107,"")),0) -> 0 | D109: =IFERROR(D108/(COUNTA(A96:A107)-COUNTIF(A96:A107,"")),0) -> 0 | E109: =IFERROR(E108/(COUNTA(A96:A107)-COUNTIF(A96:A107,"")),0) -> 0 | F109: =IFERROR(F108/(COUNTA(A96:A107)-COUNTIF(A96:A107,"")),0) -> 0 | G109: =IFERROR(G108/(COUNTA(A96:A107)-COUNTIF(A96:A107,"")),0) -> 0 | H109: =IFERROR(H108/(COUNTA(A96:A107)-COUNTIF(A96:A107,"")),0) -> 0 | I109: =IFERROR(I108/(COUNTA(A96:A107)-COUNTIF(A96:A107,"")),0) -> 0 | J109: =IFERROR(J108/(COUNTA(A96:A107)-COUNTIF(A96:A107,"")),0) -> 0 | K109: =IFERROR(K108/(COUNTA(A96:A107)-COUNTIF(A96:A107,"")),0) -> 0 | L109: =IFERROR(L108/(COUNTA(A96:A107)-COUNTIF(A96:A107,"")),0) -> 0 | M109: =IFERROR(M108/(COUNTA(A96:A107)-COUNTIF(A96:A107,"")),0) -> 0 | N109: =IFERROR(N108/(COUNTA(A96:A107)-COUNTIF(A96:A107,"")),0) -> 0 | O109: =IFERROR(O108/(COUNTA(A96:A107)-COUNTIF(A96:A107,"")),0) -> 0 | P109: =IFERROR(P108/(COUNTA(A96:A107)-COUNTIF(A96:A107,"")),0) -> 0 | S109: =IFERROR(R108/S108*100,0) -> 0 | T109: =IFERROR(Q108/T108*100,0) -> 0 | U109: =IFERROR(U108/COUNTA(A96:A107),0) -> 0 | V109: =IFERROR(V108/COUNTA(A96:A107),0) -> 0
A110: Unutilized Limit (CC/OD) | B110: =O93+B109 -> 0 | C110: =O93+C109 -> 0 | D110: =O93+D109 -> 0 | G110: =O93+G109 -> 0 | S110: O/w Return Ratio | T110: I/w Return Ratio
A114: Name of Customer
A115: Name of Bank | H115: Branch Name
...

Sheet ExistingLoans&Facilities&RTR
A1: S. No. | B1: Bank / FI Name | C1: Loan / Facility Type (Select from Dropdown) | D1: Loan / Facility Amount (Rs.) | E1: Current Outstanding (Rs.) | F1: Start Date | G1: Tenure (Months) | H1: In case closed, Closure Date | I1: MOB | J1: Borrower name for loan / facility | K1: Loan / Facility A/c No. | L1: Repayment Bank details | M1: Status (Select from Dropdown) | N1: Running EMI (Rs.) | O1: % of EMI to be considered | P1: EMI Amount to be considered (Rs.) | Q1: Remarks | R1: Month-on-month RTR (upto last 12 months) -->
R2: =IF('Banking - Non PDF'!$A$27="","",'Banking - Non PDF'!$A$27) -> 44986 | S2: =IF('Banking - Non PDF'!$A$28="","",'Banking - Non PDF'!$A$28) -> 45017 | T2: =IF('Banking - Non PDF'!$A$29="","",'Banking - Non PDF'!$A$29) -> 45047 | U2: =IF('Banking - Non PDF'!$A$30="","",'Banking - Non PDF'!$A$30) -> 45078 | V2: =IF('Banking - Non PDF'!$A$31="","",'Banking - Non PDF'!$A$31) -> 45108 | W2: =IF('Banking - Non PDF'!$A$32="","",'Banking - Non PDF'!$A$32) -> 45139 | X2: =IF('Banking - Non PDF'!$A$33="","",'Banking - Non PDF'!$A$33) -> 45170 | Y2: =IF('Banking - Non PDF'!$A$34="","",'Banking - Non PDF'!$A$34) -> 45200 | Z2: =IF('Banking - Non PDF'!$A$35="","",'Banking - Non PDF'!$A$35) -> 45231 | AA2: =IF('Banking - Non PDF'!$A$36="","",'Banking - Non PDF'!$A$36) -> 45261 | AB2: =IF('Banking - Non PDF'!$A$37="","",'Banking - Non PDF'!$A$37) -> 45292 | AC2: =IF('Banking - Non PDF'!$A$38="","",'Banking - Non PDF'!$A$38) -> 45323
A3: 1 | I3: =IF(F3="","",IF(H3<>"",DATEDIF(F3,H3,"M"),DATEDIF(F3,TODAY(),"M"))) | P3: =IF(OR(M3="",M3="Active"),N3*IF(O3="",100%,O3),0) -> 0 | R3: 5 | S3: 5 | T3: 5 | U3: 5 | V3: 5 | W3: 5 | X3: 5 | Y3: 5
A4: 2 | I4: =IF(F4="","",IF(H4<>"",DATEDIF(F4,H4,"M"),DATEDIF(F4,TODAY(),"M"))) | P4: =IF(OR(M4="",M4="Active"),N4*IF(O4="",100%,O4),0) -> 0 | X4: 4 | Y4: 4 | Z4: 4 | AA4: 4 | AB4: 4 | AC4: 4
A5: 3 | I5: =IF(F5="","",IF(H5<>"",DATEDIF(F5,H5,"M"),DATEDIF(F5,TODAY(),"M"))) | P5: =IF(OR(M5="",M5="Active"),N5*IF(O5="",100%,O5),0) -> 0 | AA5: 5 | AB5: 5 | AC5: 5
A6: 4 | I6: =IF(F6="","",IF(H6<>"",DATEDIF(F6,H6,"M"),DATEDIF(F6,TODAY(),"M"))) | P6: =IF(OR(M6="",M6="Active"),N6*IF(O6="",100%,O6),0) -> 0 | AA6: 5 | AB6: 5 | AC6: 5
A7: 5 | I7: =IF(F7="","",IF(H7<>"",DATEDIF(F7,H7,"M"),DATEDIF(F7,TODAY(),"M"))) | P7: =IF(OR(M7="",M7="Active"),N7*IF(O7="",100%,O7),0) -> 0
A8: 6 | I8: =IF(F8="","",IF(H8<>"",DATEDIF(F8,H8,"M"),DATEDIF(F8,TODAY(),"M"))) | P8: =IF(OR(M8="",M8="Active"),N8*IF(O8="",100%,O8),0) -> 0
A9: 7 | I9: =IF(F9="","",IF(H9<>"",DATEDIF(F9,H9,"M"),DATEDIF(F9,TODAY(),"M"))) | P9: =IF(OR(M9="",M9="Active"),N9*IF(O9="",100%,O9),0) -> 0
A10: 8 | I10: =IF(F10="","",IF(H10<>"",DATEDIF(F10,H10,"M"),DATEDIF(F10,TODAY(),"M"))) | P10: =IF(OR(M10="",M10="Active"),N10*IF(O10="",100%,O10),0) -> 0
A11: 9 | I11: =IF(F11="","",IF(H11<>"",DATEDIF(F11,H11,"M"),DATEDIF(F11,TODAY(),"M"))) | P11: =IF(OR(M11="",M11="Active"),N11*IF(O11="",100%,O11),0) -> 0
A12: 10 | I12: =IF(F12="","",IF(H12<>"",DATEDIF(F12,H12,"M"),DATEDIF(F12,TODAY(),"M"))) | P12: =IF(OR(M12="",M12="Active"),N12*IF(O12="",100%,O12),0) -> 0
A13: 11 | I13: =IF(F13="","",IF(H13<>"",DATEDIF(F13,H13,"M"),DATEDIF(F13,TODAY(),"M"))) | P13: =IF(OR(M13="",M13="Active"),N13*IF(O13="",100%,O13),0) -> 0
A14: 12 | I14: =IF(F14="","",IF(H14<>"",DATEDIF(F14,H14,"M"),DATEDIF(F14,TODAY(),"M"))) | P14: =IF(OR(M14="",M14="Active"),N14*IF(O14="",100%,O14),0) -> 0
A15: 13 | I15: =IF(F15="","",IF(H15<>"",DATEDIF(F15,H15,"M"),DATEDIF(F15,TODAY(),"M"))) | P15: =IF(OR(M15="",M15="Active"),N15*IF(O15="",100%,O15),0) -> 0
A16: 14 | I16: =IF(F16="","",IF(H16<>"",DATEDIF(F16,H16,"M"),DATEDIF(F16,TODAY(),"M"))) | P16: =IF(OR(M16="",M16="Active"),N16*IF(O16="",100%,O16),0) -> 0
A17: 15 | I17: =IF(F17="","",IF(H17<>"",DATEDIF(F17,H17,"M"),DATEDIF(F17,TODAY(),"M"))) | P17: =IF(OR(M17="",M17="Active"),N17*IF(O17="",100%,O17),0) -> 0
A18: 16 | I18: =IF(F18="","",IF(H18<>"",DATEDIF(F18,H18,"M"),DATEDIF(F18,TODAY(),"M"))) | P18: =IF(OR(M18="",M18="Active"),N18*IF(O18="",100%,O18),0) -> 0
... A102: 100 | I102: =IF(F102="","",IF(H102<>"",DATEDIF(F102,H102,"M"),DATEDIF(F102,TODAY(),"M"))) | P102: =IF(OR(M102="",M102="Active"),N102*IF(O102="",100%,O102),0) -> 0
L103: Obligation to be considered | N103: =SUM(P3:P102) -> 0
L104: Total Obligations | N104: =SUM(N3:N102) -> 0
L105: Obligations not considered | N105: =N104-N103 -> 0

Sheet SelfEmployedEligibility
B2: Loan Amount Requested (In INR) | C2: =BasicInput!$D$27 -> 3000000
B3: ROI | C3: =BasicInput!$F$27 -> 0.12
B4: Tenure - Months | C4: =BasicInput!$E$27 -> 240
B6: Product - Property Type | C6: Home Loan
B7: Valuation Details | C7: Value
B8: Property Value - Valuation-1 | C8: =BasicInput!$I$39 -> 0
B9: Property Value - Valuation-2 | C9: =BasicInput!$J$39 -> 0
B10: Property Value - Valuation-3
B11: Property Value - Final | C11: =IF(C10=0,IF(C9=0,C8,IF(ABS(C9-C8)/MIN(C9,C8)>0.2,"Trigger Third Valuation",AVERAGE(C8,C9))),IF(ABS(C10-C9)<ABS(C10-C8),(IF(ABS(C10-C9)<ABS(C9-C8),AVERAGE(C10,C9),AVERAGE(C9,C8))),(IF(ABS(C10-C8)<ABS(C9-C8),AVERAGE(C10,C8),AVERAGE(C9,C8))))) -> 0
B13: Obligation Details | C13: Value
B14: Monthly Obligations to be considered in eligibility | C14: ='ExistingLoans&Facilities&RTR'!$N$103 -> 0
B15: Obligations not to be considered in eligibility | C15: ='ExistingLoans&Facilities&RTR'!$N$105 -> 0
B17: Income Details
B18: Parameters | C18: % considered | D18: Frequency | E18: Previous Year | F18: Current Year | G18: Amount Considered
B19: Core Income
B20: Net Salary | C20: 1 | D20: Annual | E20: =BasicInput!E48 -> 0 | F20: =BasicInput!D48 -> 0 | G20: =IF(D20="Monthly",C20*F20*12,C20*F20) -> 0
B21: EBITDA
B22: Profit Before Tax | C22: 1 | D22: Annual | E22: =IF(BasicInput!C1="Prime",PrimeCashProfitMethod!C4,AffordConsolidated!D29*100000)+'44AD,44ADA,44AEIncome'!C117 -> 0 | F22: =IF(BasicInput!C1="Prime",PrimeCashProfitMethod!B4,AffordConsolidated!C29*100000)+'44AD,44ADA,44AEIncome'!B117 -> 0 | G22: =IFERROR((IF((K26-J26)/J26<=50%,K26,IF((AVERAGE(K26,J26)-J26)/J26>50%,AVERAGE(J26,K26),J26*150%))),0) -> 0 | J22: =IF(D22="Monthly",C22*E22*12,C22*E22) -> 0 | K22: =IF(D22="Monthly",C22*F22*12,C22*F22) -> 0
B23: Depreciation | C23: 1 | D23: Annual | E23: =IF(BasicInput!C1="Prime",PrimeCashProfitMethod!C5,AffordConsolidated!D23*100000) -> 0 | F23: =IF(BasicInput!C1="Prime",PrimeCashProfitMethod!B5,AffordConsolidated!C23*100000) -> 0 | J23: =IF(D23="Monthly",C23*E23*12,C23*E23) -> 0 | K23: =IF(D23="Monthly",C23*F23*12,C23*F23) -> 0
B24: Salary/Interest paid to partners/directors | C24: 1 | D24: Annual | E24: =IF(BasicInput!C1="Prime",PrimeCashProfitMethod!C6,0) -> 0 | F24: =IF(BasicInput!C1="Prime",PrimeCashProfitMethod!B6,0) -> 0 | J24: =IF(D24="Monthly",C24*E24*12,C24*E24) -> 0 | K24: =IF(D24="Monthly",C24*F24*12,C24*F24) -> 0
B25: Interest Paid | C25: 1 | D25: Annual | E25: =IF(BasicInput!C1="Prime",PrimeCashProfitMethod!C7,AffordConsolidated!D25*100000) -> 0 | F25: =IF(BasicInput!C1="Prime",PrimeCashProfitMethod!B7,AffordConsolidated!C25*100000) -> 0 | J25: =IF(D25="Monthly",C25*E25*12,C25*E25) -> 0 | K25: =IF(D25="Monthly",C25*F25*12,C25*F25) -> 0
B26: Other Income | J26: =IF(SUM(J22:J25)<=0,0.00001,SUM(J22:J25)) -> 1e-05 | K26: =SUM(K22:K25) -> 0
B27: Rental Income | C27: 1 | D27: Annual | F27: =BasicInput!D49 -> 0 | G27: =IF(D27="Annual",F27,F27*12) -> 0
B28: Rental Income (Unregistered) | C28: 1 | D28: Annual | G28: =IF(D28="Monthly",AVERAGE(C28*F28*12,C28*E28*12),AVERAGE(C28*F28,C28*E28)) -> 0
B29: Agricultural Income | C29: 0.5 | D29: Annual | F29: =BasicInput!D50 -> 0 | G29: =IF(D29="Monthly",AVERAGE(C29*F29*12,C29*E29*12),AVERAGE(C29*F29,C29*E29)) -> 0
B30: Interest From FD / Dividend Income | C30: 1 | D30: Annual | F30: =BasicInput!D51 -> 0 | G30: =IF(D30="Monthly",AVERAGE(C30*F30*12,C30*E30*12),AVERAGE(C30*F30,C30*E30)) -> 0
B31: Other Income | C31: 1 | D31: Annual | F31: =BasicInput!D52 -> 0 | G31: =IF(D31="Monthly",AVERAGE(C31*F31*12,C31*E31*12),AVERAGE(C31*F31,C31*E31)) -> 0
B32: Other Income capped at 100% of the (Core Income + EBITDA)
B33: Rental Income from Property Mortgaged and Rentals escrowed with ABHFL
B34: Escrowed Rental Income | C34: 1 | D34: Annual | F34: =BasicInput!D53 -> 0 | G34: =IF(D34="Annual",F34,F34*12) -> 0
B35: Escrowed Rental Income (Unregistered) | C35: 1 | D35: Annual | G35: =IF(D35="Monthly",AVERAGE(C35*F35*12,C35*E35*12),AVERAGE(C35*F35,C35*E35)) -> 0
B36: Eligible Income | G36: =IF(SUM(G27:G31)>SUM(G22,G20),SUM(G20,G22,G22,G20,G34:G35),SUM(G20,G22,G27:G31,G34:G35)) -> 0
B37: Eligible Income = Core Income + EBITDA+ Other Income
B39: Eligibility Computation
B41: Monthly Income | C41: =G36/12 -> 0
B42: Applicable FOIR | C42: 0.8
B43: Appraised Obligations | C43: =C14 -> 0
B44: Amount Available for EMI Servicing | C44: =(C41*C42)-C43 -> 0
B45: Loan Eligibility - Based on Income | C45: =IF(C44<=0,"Case Not Eligible",(C44/(PMT(C3/12,C4,-100000)))*100000) -> Case Not Eligible
B47: Property Value | C47: =+C11 -> 0
B48: Applicable LTV | C48: =IF(C6="LAP-Resi",70%,IF(C6="LAP-Resi (Vacant)",65%,IF(C6="LAP-Comm",60%,IF(C6="LAP-Comm (Vacant)",55%,IF(C6="Commerical Purchase",65%,IF(C6="Home Loan",80%,IF(C6="Industrial Property",50%,0))))))) -> 0.8
B49: Loan Eligibility - Based on Property Value | C49: -
B51: Eligibility | C51: =IF(C45="Case Not Eligible","Case Not Eligible",IF(C49=0,MIN(C45,C2),MIN(C45,C49,C2))) -> Case Not Eligible
B52: EMI | C52: =IF(C51="Case Not Eligible","Case Not Eligible",PMT(C3/12,C4,-C51)) -> Case Not Eligible
B54: FOIR on the Amount Applied | C54: =SUM(PMT(C3/12,C4,-C2),C43)/C41 -> #DIV/0!
B55: LTV on the Amount Applied | C55: =C2/C47 -> #DIV/0!
B57: EBITDA Decline Deviation | C57: =IF(((SUM(F22:F25)-SUM(E22:E25))/SUM(E22:E25))>=-20%,"No Deviation","Deviation Approval required") -> #DIV/0!
B58: FOIR Deviaiton / Delegation | C58: =IF(C54-C42>15%,"Deviation Approval required",IF(C54-C42>10%,"Deviation Approval required",IF(C54-C42>5%,"Deviation Approval required",IF(C54-C42>0%,"Deviation Approval required","Within Policy Norms")))) -> #DIV/0!
B59: LTV Deviaiton / Delegation | C59: =IF(OR(C6="Home Loan",C6="Industrial Property"),"Deviation not allowed on LTV",IF((C55-C48)<=0%,"Within Policy Norms",IF(C6="LAP-Resi (Vacant)","Deviation Approval required",IF(C6="LAP-Comm (Vacant)","Deviation Approval Required",IF((C55-C48)<=2.5%,"Deviation Approval Required",IF((C55-C48)<=5%,"Deviation Approval Required","Deviation Approval Required")))))) -> Deviation not allowed on LTV
B60: Product Cap Deviation | C60: =IF(C2>100000000,"Offering Under this Program for the Applied Loan Amount is Not Permitted"," No Deviation ") -> No Deviation

Sheet AffordableCMAssessedIncome
A1: Name of Customer / Assessee: | B1: Kanhaiya Bhartiya | H1: Highlight the Liquid Funds, Savings, Assets, Investments done by Borrower
A2: Date of Birth / Incorporation (mm/dd/yyyy): | B2: 43102 | H2: Nature | I2: Verification Tool | K2: Amount
A3: Type of Assessee (select from dropdown): | B3: Individual | H3: Savings Account
A4: Qualification (for Individuals only): | B4: Graduate | H4: RD/FD
A5: Industry Category (select from dropdown): | B5: Services | H5: LIC Policy
A6: Industry Sub-classification (select from dropdown): | H6: Mutual Funds
A7: Latest Audited / Reported Financials available for Financial Year ended on 31st March of (Year): | H7: Local Schemes | M7: `
A8: Business Setup Details | B8: Resi-cum-Office Setup | H8: Jewellery
A9: Business Premises Ownership | B9: Self-Owned | H9: Assets Purchased in Last One year
A10: Business Activity observed | B10: Intensive | H10: Others ( Specify)
A11: Business Type | B11: Non - Seasonal | H11: Fixed Asset Created/Owned | I11: Asset Name | K11: Value
H12: Personal Assets
A13: Assessed Sale / Operational income | B13: Peak Business hours | C13: Normal Hours | D13: Daily | E13: Monthly
A14: Books (With Receipts) / Non Books (Without Receipts) | E14: 100000 | H14: Family owned Assets
H15: Two References of Suppliers /Customers/ Landlord / Shops in Vicinity with Tel No.
A16: A. Total Assessed Income | E16: =SUM(E14:E15) -> 100000 | H16: Purpose of Loan
A17: Less- Business Expenses | H17: OCR amount if any and Source
A18: Cost of Goods [Books (With Receipts) / Non Books (Without Receipts)] | E18: 20000 | H18: How much EMI which can customer afford to pay comfortably as acknowledged by the customer | I18: INR
A19: Rent of Business premises if applicable | H19: Details of Family Members | I19: Adults | K19: Children
A20: Salaries and Wages | H20: Number of Dependents
A21: Interest Paid on loans to Local Money lenders | H21: Total Earning Members
A22: Interest Paid to Banks and FIs
A23: Freight Cost
A24: Power Bill
A25: Statutory Taxes if any
A26: Phone Bills
A27: Admin Expenses
A28: Business Promotion Expenses
A29: Others (Specify) | E29: 20000
A30: B. Total Business Expenses | E30: =SUM(E18:E29) -> 40000
A31: C. Net Income from Business (A-B) | E31: =E16-E30 -> 60000
A32: Other Income (Monthly)
A33: Nature of Income | C33: Verification Tool (Specify) | E33: Amount
A34: Rental
A35: Agri. Income
A36: Part Time income
A37: Interest Income
A38: Others
A39: Monthly Income of Applicant’s Family (Mention Relation with Applicant)
A40: Income Source (Salary/Business/others) | C40: Verification Tool (Specify) | E40: Amount
A44: D. Total Other Income (Monthly) | C44: =SUM(E34:E38)+SUM(E41:E43) -> 0
A45: E. Total Family Income (C+D) p.m. | C45: =E31+C44 -> 60000
A46: Household Expenses | C46: Monthly
A47: Food, Clothing and other Household Expenses
A48: Power and Water Bills
A49: Mobile Recharge Expenses
A50: DTH/Cable Recharge Expenses
A51: Medical Expenses
A52: Education/Fees Expenses
A53: Commuting expenses for all family members
A54: Residential Rent Expenses
A55: Loan EMI
A56: Other (Specify)
A57: F. Total Household Expenses | C57: =SUM(C47:E56) -> 0
A58: Net Disposable Income(E-F) | C58: =C45-C57 -> 60000
A61: Eligible Loan Amount as per CM Assessed Income FOIR norms | C61: =IFERROR(((C58+C55)*60%-C55)/PMT(BasicInput!$F$27/12,BasicInput!$E$27,-100000),0)*100000 -> 3269499
A62: Applied Loan Amount | C62: =BasicInput!D27 -> 3000000
A63: EMI for applied Loan Amount | C63: =BasicInput!G27 -> 33033
A64: FOIR for Applied Loan Amount | C64: =IFERROR((C63+C55)/(C58+C55),0) -> 0.55055 | F64: =IF(C63>C61,"Deviation approval required","")

Sheet CAAssessment
A1: Eligibility under CA Assessment Program | H1: =CONCATENATE(Validation!$A$50,"_",BasicInput!$H$28,"_",BasicInput!$F$40) -> CA Assessment_HL_
A3: S. No. | B3: Name of Customer / Entity | C3: Industry Category | D3: Industry Sub-classification | E3: Revenue from Operations (Rs.) | F3: Profit Before Tax (PBT) excl Rent Receipts, Interest and Dividend Income, Speculation Profit and Other Income (Rs.) | G3: Salary to Directors / Partners (Rs.) | H3: Interest to Directors / Partners (Rs.) | I3: Depreciation (Rs.) | J3: Total Audited / Declared Income (Rs.) | K3: Considered for CA Assessed Income Eligibility? | L3: % Stake to be considered | M3: Turnover as per CA Report (Rs.) | N3: Net Profit as per CA Report (Rs.) | O3: Eligible Income (Rs.)
A4: 1 | B4: =IF(BasicInput!$C$1="Prime",IF(Prime1!$B$1="","",Prime1!$B$1),IF(Afford1!$B$1="","",Afford1!$B$1)) -> KANHAIYA BHARTI | C4: =IF(BasicInput!$C$1="Prime",IF(Prime1!$B$5="","",Prime1!$B$5),IF(Afford1!$B$5="","",Afford1!$B$5)) -> Services | D4: =IF(BasicInput!$C$1="Prime",IF(Prime1!$B$6="","",Prime1!$B$6),IF(Afford1!$B$6="","",Afford1!$B$6)) -> Others - Industries not classified elsewhere (Services) | E4: =IF(BasicInput!$C$1="Prime",(Prime1!$C$27-Prime1!$C$25-Prime1!$C$24-Prime1!$C$18),(Afford1!$C$17)) -> 0 | F4: =IF(BasicInput!$C$1="Prime",(Prime1!$C$49-Prime1!$C$25-Prime1!$C$24-Prime1!$C$18-Prime1!$C$34),(Afford1!$C$35-Afford1!$C$18)) -> 0 | G4: =IF(BasicInput!$C$1="Prime",Prime1!$C$48,0) -> 0 | H4: =IF(BasicInput!$C$1="Prime",Prime1!$C$46,0) -> 0 | I4: =IF(BasicInput!$C$1="Prime",Prime1!$C$39,Afford1!$C$29) -> 0 | J4: =SUM(F4:I4) -> 0 | L4: =IF(BasicInput!$C$1="Prime",IF(Prime1!$B$9="","",Prime1!$B$9),IF(Afford1!$B$9="","",Afford1!$B$9)) -> 1 | O4: =IF(K4="Yes",MIN(J4*L4*3.5,N4),0) -> 0
A5: 2 | B5: =IF(BasicInput!$C$1="Prime",IF(Prime2!$B$1="","",Prime2!$B$1),IF(Afford2!$B$1="","",Afford2!$B$1)) -> SANDHYA BHARTI | C5: =IF(BasicInput!$C$1="Prime",IF(Prime2!$B$5="","",Prime2!$B$5),IF(Afford2!$B$5="","",Afford2!$B$5)) -> Services | D5: =IF(BasicInput!$C$1="Prime",IF(Prime2!$B$6="","",Prime2!$B$6),IF(Afford2!$B$6="","",Afford2!$B$6)) -> Others - Industries not classified elsewhere (Services) | E5: =IF(BasicInput!$C$1="Prime",(Prime2!$C$27-Prime2!$C$25-Prime2!$C$24-Prime2!$C$18),(Afford2!$C$17)) -> 0 | F5: =IF(BasicInput!$C$1="Prime",(Prime2!$C$49-Prime2!$C$25-Prime2!$C$24-Prime2!$C$18-Prime2!$C$34),(Afford2!$C$35-Afford2!$C$18)) -> 0 | G5: =IF(BasicInput!$C$1="Prime",Prime2!$C$48,0) -> 0 | H5: =IF(BasicInput!$C$1="Prime",Prime2!$C$46,0) -> 0 | I5: =IF(BasicInput!$C$1="Prime",Prime2!$C$39,Afford2!$C$29) -> 0 | J5: =SUM(F5:I5) -> 0 | L5: =IF(BasicInput!$C$1="Prime",IF(Prime2!$B$9="","",Prime2!$B$9),IF(Afford2!$B$9="","",Afford2!$B$9)) -> 1 | O5: =IF(K5="Yes",MIN(J5*L5*3.5,N5),0) -> 0
A6: 3 | B6: =IF(BasicInput!$C$1="Prime",IF(Prime3!$B$1="","",Prime3!$B$1),IF(Afford3!$B$1="","",Afford3!$B$1)) | C6: =IF(BasicInput!$C$1="Prime",IF(Prime3!$B$5="","",Prime3!$B$5),IF(Afford3!$B$5="","",Afford3!$B$5)) -> Services | D6: =IF(BasicInput!$C$1="Prime",IF(Prime3!$B$6="","",Prime3!$B$6),IF(Afford3!$B$6="","",Afford3!$B$6)) -> Others - Industries not classified elsewhere (Services) | E6: =IF(BasicInput!$C$1="Prime",(Prime3!$C$27-Prime3!$C$25-Prime3!$C$24-Prime3!$C$18),(Afford3!$C$17)) -> 0 | F6: =IF(BasicInput!$C$1="Prime",(Prime3!$C$49-Prime3!$C$25-Prime3!$C$24-Prime3!$C$18-Prime3!$C$34),(Afford3!$C$35-Afford3!$C$18)) -> 0 | G6: =IF(BasicInput!$C$1="Prime",Prime3!$C$48,0) -> 0 | H6: =IF(BasicInput!$C$1="Prime",Prime3!$C$46,0) -> 0 | I6: =IF(BasicInput!$C$1="Prime",Prime3!$C$39,Afford3!$C$29) -> 0 | J6: =SUM(F6:I6) -> 0 | L6: =IF(BasicInput!$C$1="Prime",IF(Prime3!$B$9="","",Prime3!$B$9),IF(Afford3!$B$9="","",Afford3!$B$9)) -> 1 | O6: =IF(K6="Yes",MIN(J6*L6*3.5,N6),0) -> 0
A7: 4 | B7: =IF(BasicInput!$C$1="Prime",IF(Prime4!$B$1="","",Prime4!$B$1),IF(Afford4!$B$1="","",Afford4!$B$1)) | C7: =IF(BasicInput!$C$1="Prime",IF(Prime4!$B$5="","",Prime4!$B$5),IF(Afford4!$B$5="","",Afford4!$B$5)) -> Services | D7: =IF(BasicInput!$C$1="Prime",IF(Prime4!$B$6="","",Prime4!$B$6),IF(Afford4!$B$6="","",Afford4!$B$6)) -> Others - Industries not classified elsewhere (Services) | E7: =IF(BasicInput!$C$1="Prime",(Prime4!$C$27-Prime4!$C$25-Prime4!$C$24-Prime4!$C$18),(Afford4!$C$17)) -> 0 | F7: =IF(BasicInput!$C$1="Prime",(Prime4!$C$49-Prime4!$C$25-Prime4!$C$24-Prime4!$C$18-Prime4!$C$34),(Afford4!$C$35-Afford4!$C$18)) -> 0 | G7: =IF(BasicInput!$C$1="Prime",Prime4!$C$48,0) -> 0 | H7: =IF(BasicInput!$C$1="Prime",Prime4!$C$46,0) -> 0 | I7: =IF(BasicInput!$C$1="Prime",Prime4!$C$39,Afford4!$C$29) -> 0 | J7: =SUM(F7:I7) -> 0 | L7: =IF(BasicInput!$C$1="Prime",IF(Prime4!$B$9="","",Prime4!$B$9),IF(Afford4!$B$9="","",Afford4!$B$9)) -> 1 | O7: =IF(K7="Yes",MIN(J7*L7*3.5,N7),0) -> 0
A8: 5 | B8: =IF(BasicInput!$C$1="Prime",IF(Prime5!$B$1="","",Prime5!$B$1),IF(Afford5!$B$1="","",Afford5!$B$1)) | C8: =IF(BasicInput!$C$1="Prime",IF(Prime5!$B$5="","",Prime5!$B$5),IF(Afford5!$B$5="","",Afford5!$B$5)) | D8: =IF(BasicInput!$C$1="Prime",IF(Prime5!$B$6="","",Prime5!$B$6),IF(Afford5!$B$6="","",Afford5!$B$6)) | E8: =IF(BasicInput!$C$1="Prime",(Prime5!$C$27-Prime5!$C$25-Prime5!$C$24-Prime5!$C$18),(Afford5!$C$17)) -> 0 | F8: =IF(BasicInput!$C$1="Prime",(Prime5!$C$49-Prime5!$C$25-Prime5!$C$24-Prime5!$C$18-Prime5!$C$34),(Afford5!$C$35-Afford5!$C$18)) -> 0 | G8: =IF(BasicInput!$C$1="Prime",Prime5!$C$48,0) -> 0 | H8: =IF(BasicInput!$C$1="Prime",Prime5!$C$46,0) -> 0 | I8: =IF(BasicInput!$C$1="Prime",Prime5!$C$39,Afford5!$C$29) -> 0 | J8: =SUM(F8:I8) -> 0 | L8: =IF(BasicInput!$C$1="Prime",IF(Prime5!$B$9="","",Prime5!$B$9),IF(Afford5!$B$9="","",Afford5!$B$9)) | O8: =IF(K8="Yes",MIN(J8*L8*3.5,N8),0) -> 0
A9: 6 | B9: =IF(Prime6!$B$1="","",Prime6!$B$1) | C9: =IF(Prime6!$B$5="","",Prime6!$B$5) | D9: =IF(Prime6!$B$6="","",Prime6!$B$6) | E9: =Prime6!$C$27-Prime6!$C$25-Prime6!$C$24-Prime6!$C$18 -> 0 | F9: =Prime6!$C$49-Prime6!$C$25-Prime6!$C$24-Prime6!$C$18-Prime6!$C$34 -> 0 | G9: =Prime6!$C$48 -> 0 | H9: =Prime6!$C$46 -> 0 | I9: =Prime6!$C$39 -> 0 | J9: =SUM(F9:I9) -> 0 | L9: =IF(Prime6!$B$9="","",Prime6!$B$9) | O9: =IF(K9="Yes",MIN(J9*L9*3.5,N9),0) -> 0
A10: 7 | B10: =IF(Prime7!$B$1="","",Prime7!$B$1) | C10: =IF(Prime7!$B$5="","",Prime7!$B$5) | D10: =IF(Prime7!$B$6="","",Prime7!$B$6) | E10: =Prime7!$C$27-Prime7!$C$25-Prime7!$C$24-Prime7!$C$18 -> 0 | F10: =Prime7!$C$49-Prime7!$C$25-Prime7!$C$24-Prime7!$C$18-Prime7!$C$34 -> 0 | G10: =Prime7!$C$48 -> 0 | H10: =Prime7!$C$46 -> 0 | I10: =Prime7!$C$39 -> 0 | J10: =SUM(F10:I10) -> 0 | L10: =IF(Prime7!$B$9="","",Prime7!$B$9) | O10: =IF(K10="Yes",MIN(J10*L10*3.5,N10),0) -> 0
A11: 8 | B11: =IF(Prime8!$B$1="","",Prime8!$B$1) | C11: =IF(Prime8!$B$5="","",Prime8!$B$5) | D11: =IF(Prime8!$B$6="","",Prime8!$B$6) | E11: =Prime8!$C$27-Prime8!$C$25-Prime8!$C$24-Prime8!$C$18 -> 0 | F11: =Prime8!$C$49-Prime8!$C$25-Prime8!$C$24-Prime8!$C$18-Prime8!$C$34 -> 0 | G11: =Prime8!$C$48 -> 0 | H11: =Prime8!$C$46 -> 0 | I11: =Prime8!$C$39 -> 0 | J11: =SUM(F11:I11) -> 0 | L11: =IF(Prime8!$B$9="","",Prime8!$B$9) | O11: =IF(K11="Yes",MIN(J11*L11*3.5,N11),0) -> 0
A12: 9 | B12: =IF(Prime9!$B$1="","",Prime9!$B$1) | C12: =IF(Prime9!$B$5="","",Prime9!$B$5) | D12: =IF(Prime9!$B$6="","",Prime9!$B$6) | E12: =Prime9!$C$27-Prime9!$C$25-Prime9!$C$24-Prime9!$C$18 -> 0 | F12: =Prime9!$C$49-Prime9!$C$25-Prime9!$C$24-Prime9!$C$18-Prime9!$C$34 -> 0 | G12: =Prime9!$C$48 -> 0 | H12: =Prime9!$C$46 -> 0 | I12: =Prime9!$C$39 -> 0 | J12: =SUM(F12:I12) -> 0 | L12: =IF(Prime9!$B$9="","",Prime9!$B$9) | O12: =IF(K12="Yes",MIN(J12*L12*3.5,N12),0) -> 0
A13: 10 | B13: =IF(Prime10!$B$1="","",Prime10!$B$1) | C13: =IF(Prime10!$B$5="","",Prime10!$B$5) | D13: =IF(Prime10!$B$6="","",Prime10!$B$6) | E13: =Prime10!$C$27-Prime10!$C$25-Prime10!$C$24-Prime10!$C$18 -> 0 | F13: =Prime10!$C$49-Prime10!$C$25-Prime10!$C$24-Prime10!$C$18-Prime10!$C$34 -> 0 | G13: =Prime10!$C$48 -> 0 | H13: =Prime10!$C$46 -> 0 | I13: =Prime10!$C$39 -> 0 | J13: =SUM(F13:I13) -> 0 | L13: =IF(Prime10!$B$9="","",Prime10!$B$9) | O13: =IF(K13="Yes",MIN(J13*L13*3.5,N13),0) -> 0
A14: Total | E14: =SUM(E4:E13) -> 0 | F14: =SUM(F4:F13) -> 0 | G14: =SUM(G4:G13) -> 0 | H14: =SUM(H4:H13) -> 0 | I14: =SUM(I4:I13) -> 0 | J14: =SUM(J4:J13) -> 0 | M14: =SUM(M4:M13) -> 0 | N14: =SUM(N4:N13) -> 0 | O14: =SUM(O4:O13) -> 0
C16: (Figs in Rs.)
A17: Particulars
A18: FINAL INCOME FOR ELIGIBILITY | C18: =O14 -> 0
A19: Monthly Income | C19: =C18/12 -> 0
A20: APPLIED LOAN AMOUNT | C20: =BasicInput!$D$27 -> 3000000
A21: Existing Obligations | C21: ='ExistingLoans&Facilities&RTR'!$N$103 -> 0
A22: Proposed Loan Obligation (excl GPL and Insurance) | C22: =BasicInput!$G$28 -> 33033
A23: Proposed Insurance Obligation, if any | C23: =SUMIF(BasicInput!$B$22:$B$26,Validation!$A$38,BasicInput!$G$22:$G$26) -> 0
A24: FOIR for Applied Loan Amount (excl GPL and Insurance) | C24: =IF(SUM(C21:C22)=0,0,IFERROR(SUM(C21:C22)/C19,100000%)) -> 1000
A25: Overall FOIR for Applied Loan Amount (incl GPL / Insurance) | C25: =IF(SUM(C21:C23)=0,0,IFERROR(SUM(C21:C23)/C19,100000%)) -> 1000
A26: FOIR for proposed Insurance Loan portion, if any | C26: =IFERROR(SUMIF(BasicInput!$B$22:$B$26,Validation!$A$38,BasicInput!$G$22:$G$26)/C19,0) -> 0
A27: TOTAL EXPOSURE ELIGIBLE AS PER FOIR NORMS | C27: =MAX(IFERROR(((VLOOKUP($H$1,Validation!$O$2:$W$631,6,0)+IF(AND(BasicInput!$H$28<>"Ins",COUNTIF(BasicInput!$B$22:$B$26,Validation!$A$38)>=1),MIN(SUMIF(BasicInput!$B$22:$B$26,Validation!$A$38,BasicInput!$G$22:$G$26)/C19,5%),0%))*C19-C21)/BasicInput!$F$28,0),0) -> 0
A28: LTV on MV for Applied Loan Amount (excl GPL and Insurance) | C28: =IFERROR((BasicInput!$D$28+$G$40)/$M$40,0) -> 0
A29: Overall LTV on MV for Applied Loan Amount (incl GPL / Insurance) | C29: =IFERROR((BasicInput!$D$27+$G$40)/$M$40,0) -> 0
A30: LTV for proposed Insurance Loan portion, if any | C30: =IFERROR(SUMIF(BasicInput!$B$22:$B$26,Validation!$A$38,BasicInput!$D$22:$D$26)/$M$40,0) -> 0
A31: TOTAL EXPOSURE ELIGIBLE AS PER LTV NORMS | C31: =MAX($O$40,0) -> 0
A32: FINAL ELIGIBILITY | C32: =MIN(C20,C27,C31) -> 0
A34: Property Address | B34: Property Type | C34: Owner(s) / Proposed Owner(s) | D34: Area (Sq Ft) | E34: Usage / Proposed Usage | F34: Whether in APF Project? | G34: Our existing exposure against the Property (Rs.) | H34: Valuation 1 (Rs.) | I34: Valuation 2 (Rs.) | J34: Agreement Value / Property Cost (incl Amenities) as may be applicable (Rs.) | K34: Stage of Construction | L34: Difference % in Valuations | M34: Valuation to be considered (Rs.) | N34: LTV Applicable on MV | O34: Eligible Loan basis LTV (Rs.)
A35: =IF(BasicInput!$B$34="","",BasicInput!$B$34) | B35: =IF(BasicInput!$C$34="","",BasicInput!$C$34) | C35: =IF(BasicInput!$D$34="","",BasicInput!$D$34) | D35: =IF(BasicInput!$E$34="","",BasicInput!$E$34) | E35: =IF(BasicInput!$F$34="","",BasicInput!$F$34) | F35: =IF(BasicInput!$G$34="","",BasicInput!$G$34) | G35: =IF(BasicInput!$H$34="",0,BasicInput!$H$34) -> 0 | H35: =IF(BasicInput!$I$34="",0,BasicInput!$I$34) -> 0 | I35: =IF(BasicInput!$J$34="",0,BasicInput!$J$34) -> 0 | J35: =IF(BasicInput!$K$34="",0,BasicInput!$K$34) -> 0 | K35: =IF(BasicInput!$L$34="","",BasicInput!$L$34) | L35: =IF(BasicInput!$M$34="","",BasicInput!$M$34) | M35: =IF(BasicInput!$N$34="",0,BasicInput!$N$34) -> Agreement Value / Property Cost required | N35: =IFERROR(IF(AND(OR(BasicInput!$H$28="HL",BasicInput!$H$28="HLIns"),BasicInput!$B$28>=1),MIN(P35-IF(E35=Validation!$A$83,5%,0%),VLOOKUP($H$1,Validation!$O$2:$X$631,10,0))+IF(AND(BasicInput!$H$28<>"Ins",COUNTIF(BasicInput!$B$22:$B$26,Validation!$A$38)>=1),MIN(SUMIF(BasicInput!$B$22:$B$26,Validation!$A$38,BasicInput!$D$22:$D$26)/BasicInput!$J$40,5%),0%)-IF(B35=Validation!$A$76,10%,0%)-IF(AND(BasicInput!$H$28<>"HL",BasicInput!$H$28<>"HLIns",COUNTIF(BasicInput!$B$22:$B$26,Validation!$A$30)>=1,B35=Validation!$A$75),20%,0%),0)+IF(AND($D$2<>0,B35=Validation!$A$76,K35=100%,COUNTIF(BasicInput!$B$22:$B$26,Validation!$A$33)>=1),5%,0),0) -> 0 | O35: =IFERROR(IF(AND(OR(BasicInput!$H$28="HL",BasicInput!$H$28="HLIns"),COUNTIF(BasicInput!$B$22:$B$26,Validation!$A$23)>=1,B35=Validation!$A$75),MIN(M35*N35,J35*(80%-IF(E35=Validation!$A$83,5%,0%)+IF(AND(BasicInput!$H$28<>"Ins",COUNTIF(BasicInput!$B$22:$B$26,Validation!$A$38)>=1),MIN(SUMIF(BasicInput!$B$22:$B$26,Validation!$A$38,BasicInput!$D$22:$D$26)/BasicInput!$J$40,5%),0%))),M35*N35)-G35,0) -> 0 | P35: =IF(AND(OR(BasicInput!$H$28="HL",BasicInput!$H$28="HLIns"),COUNTIF(BasicInput!$B$22:$B$26,Validation!$A$23)>=1,B35=Validation!$A$75),75%,IF(AND(OR(BasicInput!$H$28="HL",BasicInput!$H$28="HLIns"),BasicInput!$B$28>=1,OR(B35=Validation!$A$73,B35=Validation!$A$74)),IF((BasicInput!$D$28+BasicInput!$H$39)>7500000,75%,IF((BasicInput!$D$28+BasicInput!$H$39)>3000000,80%,90%)))) -> FALSE
A36: =IF(BasicInput!$B$35="","",BasicInput!$B$35) | B36: =IF(BasicInput!$C$35="","",BasicInput!$C$35) | C36: =IF(BasicInput!$D$35="","",BasicInput!$D$35) | D36: =IF(BasicInput!$E$35="","",BasicInput!$E$35) | E36: =IF(BasicInput!$F$35="","",BasicInput!$F$35) | F36: =IF(BasicInput!$G$35="","",BasicInput!$G$35) | G36: =IF(BasicInput!$H$35="",0,BasicInput!$H$35) -> 0 | H36: =IF(BasicInput!$I$35="",0,BasicInput!$I$35) -> 0 | I36: =IF(BasicInput!$J$35="",0,BasicInput!$J$35) -> 0 | J36: =IF(BasicInput!$K$35="",0,BasicInput!$K$35) -> 0 | K36: =IF(BasicInput!$L$35="","",BasicInput!$L$35) | L36: =IF(BasicInput!$M$35="","",BasicInput!$M$35) | M36: =IF(BasicInput!$N$35="",0,BasicInput!$N$35) -> Agreement Value / Property Cost required | N36: =IFERROR(IF(AND(OR(BasicInput!$H$28="HL",BasicInput!$H$28="HLIns"),BasicInput!$B$28>=1),MIN(P36-IF(E36=Validation!$A$83,5%,0%),VLOOKUP($H$1,Validation!$O$2:$X$631,10,0))+IF(AND(BasicInput!$H$28<>"Ins",COUNTIF(BasicInput!$B$22:$B$26,Validation!$A$38)>=1),MIN(SUMIF(BasicInput!$B$22:$B$26,Validation!$A$38,BasicInput!$D$22:$D$26)/BasicInput!$J$40,5%),0%)-IF(B36=Validation!$A$76,10%,0%)-IF(AND(BasicInput!$H$28<>"HL",BasicInput!$H$28<>"HLIns",COUNTIF(BasicInput!$B$22:$B$26,Validation!$A$30)>=1,B36=Validation!$A$75),20%,0%),0)+IF(AND($D$2<>0,B36=Validation!$A$76,K36=100%,COUNTIF(BasicInput!$B$22:$B$26,Validation!$A$33)>=1),5%,0),0) -> 0 | O36: =IFERROR(IF(AND(OR(BasicInput!$H$28="HL",BasicInput!$H$28="HLIns"),COUNTIF(BasicInput!$B$22:$B$26,Validation!$A$23)>=1,B36=Validation!$A$75),MIN(M36*N36,J36*(80%-IF(E36=Validation!$A$83,5%,0%)+IF(AND(BasicInput!$H$28<>"Ins",COUNTIF(BasicInput!$B$22:$B$26,Validation!$A$38)>=1),MIN(SUMIF(BasicInput!$B$22:$B$26,Validation!$A$38,BasicInput!$D$22:$D$26)/BasicInput!$J$40,5%),0%))),M36*N36)-G36,0) -> 0 | P36: =IF(AND(OR(BasicInput!$H$28="HL",BasicInput!$H$28="HLIns"),COUNTIF(BasicInput!$B$22:$B$26,Validation!$A$23)>=1,B36=Validation!$A$75),75%,IF(AND(OR(BasicInput!$H$28="HL",BasicInput!$H$28="HLIns"),BasicInput!$B$28>=1,OR(B36=Validation!$A$73,B36=Validation!$A$74)),IF((BasicInput!$D$28+BasicInput!$H$39)>7500000,75%,IF((BasicInput!$D$28+BasicInput!$H$39)>3000000,80%,90%)))) -> FALSE
A37: =IF(BasicInput!$B$36="","",BasicInput!$B$36) | B37: =IF(BasicInput!$C$36="","",BasicInput!$C$36) | C37: =IF(BasicInput!$D$36="","",BasicInput!$D$36) | D37: =IF(BasicInput!$E$36="","",BasicInput!$E$36) | E37: =IF(BasicInput!$F$36="","",BasicInput!$F$36) | F37: =IF(BasicInput!$G$36="","",BasicInput!$G$36) | G37: =IF(BasicInput!$H$36="",0,BasicInput!$H$36) -> 0 | H37: =IF(BasicInput!$I$36="",0,BasicInput!$I$36) -> 0 | I37: =IF(BasicInput!$J$36="",0,BasicInput!$J$36) -> 0 | J37: =IF(BasicInput!$K$36="",0,BasicInput!$K$36) -> 0 | K37: =IF(BasicInput!$L$36="","",BasicInput!$L$36) | L37: =IF(BasicInput!$M$36="","",BasicInput!$M$36) | M37: =IF(BasicInput!$N$36="",0,BasicInput!$N$36) -> Agreement Value / Property Cost required | N37: =IFERROR(IF(AND(OR(BasicInput!$H$28="HL",BasicInput!$H$28="HLIns"),BasicInput!$B$28>=1),MIN(P37-IF(E37=Validation!$A$83,5%,0%),VLOOKUP($H$1,Validation!$O$2:$X$631,10,0))+IF(AND(BasicInput!$H$28<>"Ins",COUNTIF(BasicInput!$B$22:$B$26,Validation!$A$38)>=1),MIN(SUMIF(BasicInput!$B$22:$B$26,Validation!$A$38,BasicInput!$D$22:$D$26)/BasicInput!$J$40,5%),0%)-IF(B37=Validation!$A$76,10%,0%)-IF(AND(BasicInput!$H$28<>"HL",BasicInput!$H$28<>"HLIns",COUNTIF(BasicInput!$B$22:$B$26,Validation!$A$30)>=1,B37=Validation!$A$75),20%,0%),0)+IF(AND($D$2<>0,B37=Validation!$A$76,K37=100%,COUNTIF(BasicInput!$B$22:$B$26,Validation!$A$33)>=1),5%,0),0) -> 0 | O37: =IFERROR(IF(AND(OR(BasicInput!$H$28="HL",BasicInput!$H$28="HLIns"),COUNTIF(BasicInput!$B$22:$B$26,Validation!$A$23)>=1,B37=Validation!$A$75),MIN(M37*N37,J37*(80%-IF(E37=Validation!$A$83,5%,0%)+IF(AND(BasicInput!$H$28<>"Ins",COUNTIF(BasicInput!$B$22:$B$26,Validation!$A$38)>=1),MIN(SUMIF(BasicInput!$B$22:$B$26,Validation!$A$38,BasicInput!$D$22:$D$26)/BasicInput!$J$40,5%),0%))),M37*N37)-G37,0) -> 0 | P37: =IF(AND(OR(BasicInput!$H$28="HL",BasicInput!$H$28="HLIns"),COUNTIF(BasicInput!$B$22:$B$26,Validation!$A$23)>=1,B37=Validation!$A$75),75%,IF(AND(OR(BasicInput!$H$28="HL",BasicInput!$H$28="HLIns"),BasicInput!$B$28>=1,OR(B37=Validation!$A$73,B37=Validation!$A$74)),IF((BasicInput!$D$28+BasicInput!$H$39)>7500000,75%,IF((BasicInput!$D$28+BasicInput!$H$39)>3000000,80%,90%)))) -> FALSE
A38: =IF(BasicInput!$B$37="","",BasicInput!$B$37) | B38: =IF(BasicInput!$C$37="","",BasicInput!$C$37) | C38: =IF(BasicInput!$D$37="","",BasicInput!$D$37) | D38: =IF(BasicInput!$E$37="","",BasicInput!$E$37) | E38: =IF(BasicInput!$F$37="","",BasicInput!$F$37) | F38: =IF(BasicInput!$G$37="","",BasicInput!$G$37) | G38: =IF(BasicInput!$H$37="",0,BasicInput!$H$37) -> 0 | H38: =IF(BasicInput!$I$37="",0,BasicInput!$I$37) -> 0 | I38: =IF(BasicInput!$J$37="",0,BasicInput!$J$37) -> 0 | J38: =IF(BasicInput!$K$37="",0,BasicInput!$K$37) -> 0 | K38: =IF(BasicInput!$L$37="","",BasicInput!$L$37) | L38: =IF(BasicInput!$M$37="","",BasicInput!$M$37) | M38: =IF(BasicInput!$N$37="",0,BasicInput!$N$37) -> Agreement Value / Property Cost required | N38: =IFERROR(IF(AND(OR(BasicInput!$H$28="HL",BasicInput!$H$28="HLIns"),BasicInput!$B$28>=1),MIN(P38-IF(E38=Validation!$A$83,5%,0%),VLOOKUP($H$1,Validation!$O$2:$X$631,10,0))+IF(AND(BasicInput!$H$28<>"Ins",COUNTIF(BasicInput!$B$22:$B$26,Validation!$A$38)>=1),MIN(SUMIF(BasicInput!$B$22:$B$26,Validation!$A$38,BasicInput!$D$22:$D$26)/BasicInput!$J$40,5%),0%)-IF(B38=Validation!$A$76,10%,0%)-IF(AND(BasicInput!$H$28<>"HL",BasicInput!$H$28<>"HLIns",COUNTIF(BasicInput!$B$22:$B$26,Validation!$A$30)>=1,B38=Validation!$A$75),20%,0%),0)+IF(AND($D$2<>0,B38=Validation!$A$76,K38=100%,COUNTIF(BasicInput!$B$22:$B$26,Validation!$A$33)>=1),5%,0),0) -> 0 | O38: =IFERROR(IF(AND(OR(BasicInput!$H$28="HL",BasicInput!$H$28="HLIns"),COUNTIF(BasicInput!$B$22:$B$26,Validation!$A$23)>=1,B38=Validation!$A$75),MIN(M38*N38,J38*(80%-IF(E38=Validation!$A$83,5%,0%)+IF(AND(BasicInput!$H$28<>"Ins",COUNTIF(BasicInput!$B$22:$B$26,Validation!$A$38)>=1),MIN(SUMIF(BasicInput!$B$22:$B$26,Validation!$A$38,BasicInput!$D$22:$D$26)/BasicInput!$J$40,5%),0%))),M38*N38)-G38,0) -> 0 | P38: =IF(AND(OR(BasicInput!$H$28="HL",BasicInput!$H$28="HLIns"),COUNTIF(BasicInput!$B$22:$B$26,Validation!$A$23)>=1,B38=Validation!$A$75),75%,IF(AND(OR(BasicInput!$H$28="HL",BasicInput!$H$28="HLIns"),BasicInput!$B$28>=1,OR(B38=Validation!$A$73,B38=Validation!$A$74)),IF((BasicInput!$D$28+BasicInput!$H$39)>7500000,75%,IF((BasicInput!$D$28+BasicInput!$H$39)>3000000,80%,90%)))) -> FALSE
A39: =IF(BasicInput!$B$38="","",BasicInput!$B$38) | B39: =IF(BasicInput!$C$38="","",BasicInput!$C$38) | C39: =IF(BasicInput!$D$38="","",BasicInput!$D$38) | D39: =IF(BasicInput!$E$38="","",BasicInput!$E$38) | E39: =IF(BasicInput!$F$38="","",BasicInput!$F$38) | F39: =IF(BasicInput!$G$38="","",BasicInput!$G$38) | G39: =IF(BasicInput!$H$38="",0,BasicInput!$H$38) -> 0 | H39: =IF(BasicInput!$I$38="",0,BasicInput!$I$38) -> 0 | I39: =IF(BasicInput!$J$38="",0,BasicInput!$J$38) -> 0 | J39: =IF(BasicInput!$K$38="",0,BasicInput!$K$38) -> 0 | K39: =IF(BasicInput!$L$38="","",BasicInput!$L$38) | L39: =IF(BasicInput!$M$38="","",BasicInput!$M$38) | M39: =IF(BasicInput!$N$38="",0,BasicInput!$N$38) -> Agreement Value / Property Cost required | N39: =IFERROR(IF(AND(OR(BasicInput!$H$28="HL",BasicInput!$H$28="HLIns"),BasicInput!$B$28>=1),MIN(P39-IF(E39=Validation!$A$83,5%,0%),VLOOKUP($H$1,Validation!$O$2:$X$631,10,0))+IF(AND(BasicInput!$H$28<>"Ins",COUNTIF(BasicInput!$B$22:$B$26,Validation!$A$38)>=1),MIN(SUMIF(BasicInput!$B$22:$B$26,Validation!$A$38,BasicInput!$D$22:$D$26)/BasicInput!$J$40,5%),0%)-IF(B39=Validation!$A$76,10%,0%)-IF(AND(BasicInput!$H$28<>"HL",BasicInput!$H$28<>"HLIns",COUNTIF(BasicInput!$B$22:$B$26,Validation!$A$30)>=1,B39=Validation!$A$75),20%,0%),0)+IF(AND($D$2<>0,B39=Validation!$A$76,K39=100%,COUNTIF(BasicInput!$B$22:$B$26,Validation!$A$33)>=1),5%,0),0) -> 0 | O39: =IFERROR(IF(AND(OR(BasicInput!$H$28="HL",BasicInput!$H$28="HLIns"),COUNTIF(BasicInput!$B$22:$B$26,Validation!$A$23)>=1,B39=Validation!$A$75),MIN(M39*N39,J39*(80%-IF(E39=Validation!$A$83,5%,0%)+IF(AND(BasicInput!$H$28<>"Ins",COUNTIF(BasicInput!$B$22:$B$26,Validation!$A$38)>=1),MIN(SUMIF(BasicInput!$B$22:$B$26,Validation!$A$38,BasicInput!$D$22:$D$26)/BasicInput!$J$40,5%),0%))),M39*N39)-G39,0) -> 0 | P39: =IF(AND(OR(BasicInput!$H$28="HL",BasicInput!$H$28="HLIns"),COUNTIF(BasicInput!$B$22:$B$26,Validation!$A$23)>=1,B39=Validation!$A$75),75%,IF(AND(OR(BasicInput!$H$28="HL",BasicInput!$H$28="HLIns"),BasicInput!$B$28>=1,OR(B39=Validation!$A$73,B39=Validation!$A$74)),IF((BasicInput!$D$28+BasicInput!$H$39)>7500000,75%,IF((BasicInput!$D$28+BasicInput!$H$39)>3000000,80%,90%)))) -> FALSE
A40: Total | G40: =SUM(G35:G39) -> 0 | M40: =SUM(M35:M39) -> 0 | O40: =SUM(O35:O39) -> 0

Sheet AverageBankingProgram
A1: Eligibility under Average Banking Program | H1: =CONCATENATE(Validation!$A$46,"_",BasicInput!$H$28,"_",BasicInput!$F$40) -> Average Banking Program_HL_
A3: S. No. | B3: Name of Customer | C3: Name of Bank | D3: A/c Type | E3: A/c Number | F3: Period | G3: Net Inflows (Rs.) | H3: Net Outflows (Rs.) | I3: Average Bank Balance, i.e., ABB (Rs.) | J3: No. of I/W Return | K3: Considered for ABP Eligibility? | L3: No. of Credit Entries | M3: No. of Debit Entries | N3: Total No. of Transactions | O3: I/w Return Ratio
A4: 1 | B4: =IF('Banking - Non PDF'!$C$22="","",'Banking - Non PDF'!$C$22) -> MR. KANHAIYA BHARTI | C4: =IF('Banking - Non PDF'!$C$23="","",'Banking - Non PDF'!$C$23) -> STATE BANK OF INDIA | D4: =IF('Banking - Non PDF'!$C$24="","",'Banking - Non PDF'!$C$24) -> Savings | E4: =IF('Banking - Non PDF'!$F$24="","",'Banking - Non PDF'!$F$24) -> 00000031272798836 | F4: =IF('Banking - Non PDF'!$K$24="","",'Banking - Non PDF'!$K$24) | G4: ='Banking - Non PDF'!$U$39 -> 1677362 | H4: ='Banking - Non PDF'!$V$39 -> 688306 | I4: ='Banking - Non PDF'!$G$40 -> 150819.67 | J4: ='Banking - Non PDF'!$Q$39 -> 0 | L4: ='Banking - Non PDF'!$S$39 -> 38 | M4: ='Banking - Non PDF'!$T$39 -> 387 | N4: =SUM(L4:M4) -> 425 | O4: =IFERROR(J4/M4,0) -> 0
A5: 2 | B5: =IF('Banking - Non PDF'!$C$45="","",'Banking - Non PDF'!$C$45) | C5: =IF('Banking - Non PDF'!$C$46="","",'Banking - Non PDF'!$C$46) | D5: =IF('Banking - Non PDF'!$C$47="","",'Banking - Non PDF'!$C$47) | E5: =IF('Banking - Non PDF'!$F$47="","",'Banking - Non PDF'!$F$47) | F5: =IF('Banking - Non PDF'!$K$47="","",'Banking - Non PDF'!$K$47) | G5: ='Banking - Non PDF'!$U$62 -> 0 | H5: ='Banking - Non PDF'!$V$62 -> 0 | I5: ='Banking - Non PDF'!$G$63 -> 0 | J5: ='Banking - Non PDF'!$Q$62 -> 0 | L5: ='Banking - Non PDF'!$S$62 -> 0 | M5: ='Banking - Non PDF'!$T$62 -> 0 | N5: =SUM(L5:M5) -> 0 | O5: =IFERROR(J5/M5,0) -> 0
A6: 3 | B6: =IF('Banking - Non PDF'!$C$68="","",'Banking - Non PDF'!$C$68) | C6: =IF('Banking - Non PDF'!$C$69="","",'Banking - Non PDF'!$C$69) | D6: =IF('Banking - Non PDF'!$C$70="","",'Banking - Non PDF'!$C$70) | E6: =IF('Banking - Non PDF'!$F$70="","",'Banking - Non PDF'!$F$70) | F6: =IF('Banking - Non PDF'!$K$70="","",'Banking - Non PDF'!$K$70) | G6: ='Banking - Non PDF'!$U$85 -> 0 | H6: ='Banking - Non PDF'!$V$85 -> 0 | I6: ='Banking - Non PDF'!$G$86 -> 0 | J6: ='Banking - Non PDF'!$Q$85 -> 0 | L6: ='Banking - Non PDF'!$S$85 -> 0 | M6: ='Banking - Non PDF'!$T$85 -> 0 | N6: =SUM(L6:M6) -> 0 | O6: =IFERROR(J6/M6,0) -> 0
A7: 4 | B7: =IF('Banking - Non PDF'!$C$91="","",'Banking - Non PDF'!$C$91) | C7: =IF('Banking - Non PDF'!$C$92="","",'Banking - Non PDF'!$C$92) | D7: =IF('Banking - Non PDF'!$C$93="","",'Banking - Non PDF'!$C$93) | E7: =IF('Banking - Non PDF'!$F$93="","",'Banking - Non PDF'!$F$93) | F7: =IF('Banking - Non PDF'!$K$93="","",'Banking - Non PDF'!$K$93) | G7: ='Banking - Non PDF'!$U$108 -> 0 | H7: ='Banking - Non PDF'!$V$108 -> 0 | I7: ='Banking - Non PDF'!$G$109 -> 0 | J7: ='Banking - Non PDF'!$Q$108 -> 0 | L7: ='Banking - Non PDF'!$S$108 -> 0 | M7: ='Banking - Non PDF'!$T$108 -> 0 | N7: =SUM(L7:M7) -> 0 | O7: =IFERROR(J7/M7,0) -> 0
A8: 5 | B8: =IF('Banking - Non PDF'!$C$114="","",'Banking - Non PDF'!$C$114) | C8: =IF('Banking - Non PDF'!$C$115="","",'Banking - Non PDF'!$C$115) | D8: =IF('Banking - Non PDF'!$C$116="","",'Banking - Non PDF'!$C$116) | E8: =IF('Banking - Non PDF'!$F$116="","",'Banking - Non PDF'!$F$116) | F8: =IF('Banking - Non PDF'!$K$116="","",'Banking - Non PDF'!$K$116) | G8: ='Banking - Non PDF'!$U$131 -> 0 | H8: ='Banking - Non PDF'!$V$131 -> 0 | I8: ='Banking - Non PDF'!$G$132 -> 0 | J8: ='Banking - Non PDF'!$Q$131 -> 0 | L8: ='Banking - Non PDF'!$S$131 -> 0 | M8: ='Banking - Non PDF'!$T$131 -> 0 | N8: =SUM(L8:M8) -> 0 | O8: =IFERROR(J8/M8,0) -> 0
A9: 6 | B9: =IF('Banking - Non PDF'!$C$137="","",'Banking - Non PDF'!$C$137) | C9: =IF('Banking - Non PDF'!$C$138="","",'Banking - Non PDF'!$C$138) | D9: =IF('Banking - Non PDF'!$C$139="","",'Banking - Non PDF'!$C$139) | E9: =IF('Banking - Non PDF'!$F$139="","",'Banking - Non PDF'!$F$139) | F9: =IF('Banking - Non PDF'!$K$139="","",'Banking - Non PDF'!$K$139) | G9: ='Banking - Non PDF'!$U$154 -> 0 | H9: ='Banking - Non PDF'!$V$154 -> 0 | I9: ='Banking - Non PDF'!$G$155 -> 0 | J9: ='Banking - Non PDF'!$Q$154 -> 0 | L9: ='Banking - Non PDF'!$S$154 -> 0 | M9: ='Banking - Non PDF'!$T$154 -> 0 | N9: =SUM(L9:M9) -> 0 | O9: =IFERROR(J9/M9,0) -> 0
A10: 7 | B10: =IF('Banking - Non PDF'!$C$160="","",'Banking - Non PDF'!$C$160) | C10: =IF('Banking - Non PDF'!$C$161="","",'Banking - Non PDF'!$C$161) | D10: =IF('Banking - Non PDF'!$C$162="","",'Banking - Non PDF'!$C$162) | E10: =IF('Banking - Non PDF'!$F$162="","",'Banking - Non PDF'!$F$162) | F10: =IF('Banking - Non PDF'!$K$162="","",'Banking - Non PDF'!$K$162) | G10: ='Banking - Non PDF'!$U$177 -> 0 | H10: ='Banking - Non PDF'!$V$177 -> 0 | I10: ='Banking - Non PDF'!$G$178 -> 0 | J10: ='Banking - Non PDF'!$Q$177 -> 0 | L10: ='Banking - Non PDF'!$S$177 -> 0 | M10: ='Banking - Non PDF'!$T$177 -> 0 | N10: =SUM(L10:M10) -> 0 | O10: =IFERROR(J10/M10,0) -> 0
A11: 8 | B11: =IF('Banking - Non PDF'!$C$183="","",'Banking - Non PDF'!$C$183) | C11: =IF('Banking - Non PDF'!$C$184="","",'Banking - Non PDF'!$C$184) | D11: =IF('Banking - Non PDF'!$C$185="","",'Banking - Non PDF'!$C$185) | E11: =IF('Banking - Non PDF'!$F$185="","",'Banking - Non PDF'!$F$185) | F11: =IF('Banking - Non PDF'!$K$185="","",'Banking - Non PDF'!$K$185) | G11: ='Banking - Non PDF'!$U$200 -> 0 | H11: ='Banking - Non PDF'!$V$200 -> 0 | I11: ='Banking - Non PDF'!$G$201 -> 0 | J11: ='Banking - Non PDF'!$Q$200 -> 0 | L11: ='Banking - Non PDF'!$S$200 -> 0 | M11: ='Banking - Non PDF'!$T$200 -> 0 | N11: =SUM(L11:M11) -> 0 | O11: =IFERROR(J11/M11,0) -> 0
A12: 9 | B12: =IF('Banking - Non PDF'!$C$206="","",'Banking - Non PDF'!$C$206) | C12: =IF('Banking - Non PDF'!$C$207="","",'Banking - Non PDF'!$C$207) | D12: =IF('Banking - Non PDF'!$C$208="","",'Banking - Non PDF'!$C$208) | E12: =IF('Banking - Non PDF'!$F$208="","",'Banking - Non PDF'!$F$208) | F12: =IF('Banking - Non PDF'!$K$208="","",'Banking - Non PDF'!$K$208) | G12: ='Banking - Non PDF'!$U$223 -> 0 | H12: ='Banking - Non PDF'!$V$223 -> 0 | I12: ='Banking - Non PDF'!$G$224 -> 0 | J12: ='Banking - Non PDF'!$Q$223 -> 0 | L12: ='Banking - Non PDF'!$S$223 -> 0 | M12: ='Banking - Non PDF'!$T$223 -> 0 | N12: =SUM(L12:M12) -> 0 | O12: =IFERROR(J12/M12,0) -> 0
A13: 10 | B13: =IF('Banking - Non PDF'!$C$229="","",'Banking - Non PDF'!$C$229) | C13: =IF('Banking - Non PDF'!$C$230="","",'Banking - Non PDF'!$C$230) | D13: =IF('Banking - Non PDF'!$C$231="","",'Banking - Non PDF'!$C$231) | E13: =IF('Banking - Non PDF'!$F$231="","",'Banking - Non PDF'!$F$231) | F13: =IF('Banking - Non PDF'!$K$231="","",'Banking - Non PDF'!$K$231) | G13: ='Banking - Non PDF'!$U$246 -> 0 | H13: ='Banking - Non PDF'!$V$246 -> 0 | I13: ='Banking - Non PDF'!$G$247 -> 0 | J13: ='Banking - Non PDF'!$Q$246 -> 0 | L13: ='Banking - Non PDF'!$S$246 -> 0 | M13: ='Banking - Non PDF'!$T$246 -> 0 | N13: =SUM(L13:M13) -> 0 | O13: =IFERROR(J13/M13,0) -> 0
A14: 11 | B14: =IF('Banking - Non PDF'!$C$252="","",'Banking - Non PDF'!$C$252) | C14: =IF('Banking - Non PDF'!$C$253="","",'Banking - Non PDF'!$C$253) | D14: =IF('Banking - Non PDF'!$C$254="","",'Banking - Non PDF'!$C$254) | E14: =IF('Banking - Non PDF'!$F$254="","",'Banking - Non PDF'!$F$254) | F14: =IF('Banking - Non PDF'!$K$254="","",'Banking - Non PDF'!$K$254) | G14: ='Banking - Non PDF'!$U$269 -> 0 | H14: ='Banking - Non PDF'!$V$269 -> 0 | I14: ='Banking - Non PDF'!$G$270 -> 0 | J14: ='Banking - Non PDF'!$Q$269 -> 0 | L14: ='Banking - Non PDF'!$S$269 -> 0 | M14: ='Banking - Non PDF'!$T$269 -> 0 | N14: =SUM(L14:M14) -> 0 | O14: =IFERROR(J14/M14,0) -> 0
A15: 12 | B15: =IF('Banking - Non PDF'!$C$275="","",'Banking - Non PDF'!$C$275) | C15: =IF('Banking - Non PDF'!$C$276="","",'Banking - Non PDF'!$C$276) | D15: =IF('Banking - Non PDF'!$C$277="","",'Banking - Non PDF'!$C$277) | E15: =IF('Banking - Non PDF'!$F$277="","",'Banking - Non PDF'!$F$277) | F15: =IF('Banking - Non PDF'!$K$277="","",'Banking - Non PDF'!$K$277) | G15: ='Banking - Non PDF'!$U$292 -> 0 | H15: ='Banking - Non PDF'!$V$292 -> 0 | I15: ='Banking - Non PDF'!$G$293 -> 0 | J15: ='Banking - Non PDF'!$Q$292 -> 0 | L15: ='Banking - Non PDF'!$S$292 -> 0 | M15: ='Banking - Non PDF'!$T$292 -> 0 | N15: =SUM(L15:M15) -> 0 | O15: =IFERROR(J15/M15,0) -> 0
A16: 13 | B16: =IF('Banking - Non PDF'!$C$298="","",'Banking - Non PDF'!$C$298) | C16: =IF('Banking - Non PDF'!$C$299="","",'Banking - Non PDF'!$C$299) | D16: =IF('Banking - Non PDF'!$C$300="","",'Banking - Non PDF'!$C$300) | E16: =IF('Banking - Non PDF'!$F$300="","",'Banking - Non PDF'!$F$300) | F16: =IF('Banking - Non PDF'!$K$300="","",'Banking - Non PDF'!$K$300) | G16: ='Banking - Non PDF'!$U$315 -> 0 | H16: ='Banking - Non PDF'!$V$315 -> 0 | I16: ='Banking - Non PDF'!$G$316 -> 0 | J16: ='Banking - Non PDF'!$Q$315 -> 0 | L16: ='Banking - Non PDF'!$S$315 -> 0 | M16: ='Banking - Non PDF'!$T$315 -> 0 | N16: =SUM(L16:M16) -> 0 | O16: =IFERROR(J16/M16,0) -> 0
A17: 14 | B17: =IF('Banking - Non PDF'!$C$321="","",'Banking - Non PDF'!$C$321) | C17: =IF('Banking - Non PDF'!$C$322="","",'Banking - Non PDF'!$C$322) | D17: =IF('Banking - Non PDF'!$C$323="","",'Banking - Non PDF'!$C$323) | E17: =IF('Banking - Non PDF'!$F$323="","",'Banking - Non PDF'!$F$323) | F17: =IF('Banking - Non PDF'!$K$323="","",'Banking - Non PDF'!$K$323) | G17: ='Banking - Non PDF'!$U$338 -> 0 | H17: ='Banking - Non PDF'!$V$338 -> 0 | I17: ='Banking - Non PDF'!$G$339 -> 0 | J17: ='Banking - Non PDF'!$Q$338 -> 0 | L17: ='Banking - Non PDF'!$S$338 -> 0 | M17: ='Banking - Non PDF'!$T$338 -> 0 | N17: =SUM(L17:M17) -> 0 | O17: =IFERROR(J17/M17,0) -> 0
A18: 15 | B18: =IF('Banking - Non PDF'!$C$344="","",'Banking - Non PDF'!$C$344) | C18: =IF('Banking - Non PDF'!$C$345="","",'Banking - Non PDF'!$C$345) | D18: =IF('Banking - Non PDF'!$C$346="","",'Banking - Non PDF'!$C$346) | E18: =IF('Banking - Non PDF'!$F$346="","",'Banking - Non PDF'!$F$346) | F18: =IF('Banking - Non PDF'!$K$346="","",'Banking - Non PDF'!$K$346) | G18: ='Banking - Non PDF'!$U$361 -> 0 | H18: ='Banking - Non PDF'!$V$361 -> 0 | I18: ='Banking - Non PDF'!$G$362 -> 0 | J18: ='Banking - Non PDF'!$Q$361 -> 0 | L18: ='Banking - Non PDF'!$S$361 -> 0 | M18: ='Banking - Non PDF'!$T$361 -> 0 | N18: =SUM(L18:M18) -> 0 | O18: =IFERROR(J18/M18,0) -> 0
A19: 16 | B19: =IF('Banking - Non PDF'!$C$367="","",'Banking - Non PDF'!$C$367) | C19: =IF('Banking - Non PDF'!$C$368="","",'Banking - Non PDF'!$C$368) | D19: =IF('Banking - Non PDF'!$C$369="","",'Banking - Non PDF'!$C$369) | E19: =IF('Banking - Non PDF'!$F$369="","",'Banking - Non PDF'!$F$369) | F19: =IF('Banking - Non PDF'!$K$369="","",'Banking - Non PDF'!$K$369) | G19: ='Banking - Non PDF'!$U$384 -> 0 | H19: ='Banking - Non PDF'!$V$384 -> 0 | I19: ='Banking - Non PDF'!$G$385 -> 0 | J19: ='Banking - Non PDF'!$Q$384 -> 0 | L19: ='Banking - Non PDF'!$S$384 -> 0 | M19: ='Banking - Non PDF'!$T$384 -> 0 | N19: =SUM(L19:M19) -> 0 | O19: =IFERROR(J19/M19,0) -> 0
A20: 17 | B20: =IF('Banking - Non PDF'!$C$390="","",'Banking - Non PDF'!$C$390) | C20: =IF('Banking - Non PDF'!$C$391="","",'Banking - Non PDF'!$C$391) | D20: =IF('Banking - Non PDF'!$C$392="","",'Banking - Non PDF'!$C$392) | E20: =IF('Banking - Non PDF'!$F$392="","",'Banking - Non PDF'!$F$392) | F20: =IF('Banking - Non PDF'!$K$392="","",'Banking - Non PDF'!$K$392) | G20: ='Banking - Non PDF'!$U$407 -> 0 | H20: ='Banking - Non PDF'!$V$407 -> 0 | I20: ='Banking - Non PDF'!$G$408 -> 0 | J20: ='Banking - Non PDF'!$Q$407 -> 0 | L20: ='Banking - Non PDF'!$S$407 -> 0 | M20: ='Banking - Non PDF'!$T$407 -> 0 | N20: =SUM(L20:M20) -> 0 | O20: =IFERROR(J20/M20,0) -> 0
A21: 18 | B21: =IF('Banking - Non PDF'!$C$413="","",'Banking - Non PDF'!$C$413) | C21: =IF('Banking - Non PDF'!$C$414="","",'Banking - Non PDF'!$C$414) | D21: =IF('Banking - Non PDF'!$C$415="","",'Banking - Non PDF'!$C$415) | E21: =IF('Banking - Non PDF'!$F$415="","",'Banking - Non PDF'!$F$415) | F21: =IF('Banking - Non PDF'!$K$415="","",'Banking - Non PDF'!$K$415) | G21: ='Banking - Non PDF'!$U$430 -> 0 | H21: ='Banking - Non PDF'!$V$430 -> 0 | I21: ='Banking - Non PDF'!$G$431 -> 0 | J21: ='Banking - Non PDF'!$Q$430 -> 0 | L21: ='Banking - Non PDF'!$S$430 -> 0 | M21: ='Banking - Non PDF'!$T$430 -> 0 | N21: =SUM(L21:M21) -> 0 | O21: =IFERROR(J21/M21,0) -> 0
A22: 19 | B22: =IF('Banking - Non PDF'!$C$436="","",'Banking - Non PDF'!$C$436) | C22: =IF('Banking - Non PDF'!$C$437="","",'Banking - Non PDF'!$C$437) | D22: =IF('Banking - Non PDF'!$C$438="","",'Banking - Non PDF'!$C$438) | E22: =IF('Banking - Non PDF'!$F$438="","",'Banking - Non PDF'!$F$438) | F22: =IF('Banking - Non PDF'!$K$438="","",'Banking - Non PDF'!$K$438) | G22: ='Banking - Non PDF'!$U$453 -> 0 | H22: ='Banking - Non PDF'!$V$453 -> 0 | I22: ='Banking - Non PDF'!$G$454 -> 0 | J22: ='Banking - Non PDF'!$Q$453 -> 0 | L22: ='Banking - Non PDF'!$S$453 -> 0 | M22: ='Banking - Non PDF'!$T$453 -> 0 | N22: =SUM(L22:M22) -> 0 | O22: =IFERROR(J22/M22,0) -> 0
A23: 20 | B23: =IF('Banking - Non PDF'!$C$459="","",'Banking - Non PDF'!$C$459) | C23: =IF('Banking - Non PDF'!$C$460="","",'Banking - Non PDF'!$C$460) | D23: =IF('Banking - Non PDF'!$C$461="","",'Banking - Non PDF'!$C$461) | E23: =IF('Banking - Non PDF'!$F$461="","",'Banking - Non PDF'!$F$461) | F23: =IF('Banking - Non PDF'!$K$461="","",'Banking - Non PDF'!$K$461) | G23: ='Banking - Non PDF'!$U$476 -> 0 | H23: ='Banking - Non PDF'!$V$476 -> 0 | I23: ='Banking - Non PDF'!$G$477 -> 0 | J23: ='Banking - Non PDF'!$Q$476 -> 0 | L23: ='Banking - Non PDF'!$S$476 -> 0 | M23: ='Banking - Non PDF'!$T$476 -> 0 | N23: =SUM(L23:M23) -> 0 | O23: =IFERROR(J23/M23,0) -> 0
A24: Total | G24: =SUM(G4:G23) -> 1677362 | H24: =SUM(H4:H23) -> 688306 | I24: =SUM(I4:I23) -> 150819.67 | J24: =SUM(J4:J23) -> 0 | L24: =SUM(L4:L23) -> 38 | M24: =SUM(M4:M23) -> 387 | N24: =SUM(N4:N23) -> 425 | O24: =IFERROR(J24/M24,0) -> 0
C26: (Figs in Rs.)
A27: Particulars
A28: FINAL MONTHLY INCOME FOR ELIGIBILITY | C28: =SUMIF($K$4:$K$23,"Yes",$I$4:$I$23)*50% -> 0
A29: APPLIED LOAN AMOUNT | C29: =BasicInput!$D$27 -> 3000000
A30: Existing Obligations | C30: ='ExistingLoans&Facilities&RTR'!$N$103 -> 0
A31: Proposed Loan Obligation (excl GPL and Insurance) | C31: =BasicInput!$G$28 -> 33033
A32: Proposed Insurance Obligation, if any | C32: =SUMIF(BasicInput!$B$22:$B$26,Validation!$A$38,BasicInput!$G$22:$G$26) -> 0
A33: FOIR for Applied Loan Amount (excl GPL and Insurance) | C33: =IF(SUM(C30:C31)=0,0,IFERROR(SUM(C30:C31)/C28,100000%)) -> 1000
A34: Overall FOIR for Applied Loan Amount (incl GPL / Insurance) | C34: =IF(SUM(C30:C32)=0,0,IFERROR(SUM(C30:C32)/C28,100000%)) -> 1000
A35: FOIR for proposed Insurance Loan portion, if any | C35: =IFERROR(SUMIF(BasicInput!$B$22:$B$26,Validation!$A$38,BasicInput!$G$22:$G$26)/C28,0) -> 0
A36: TOTAL EXPOSURE ELIGIBLE AS PER FOIR NORMS | C36: =MAX(IFERROR(((VLOOKUP($H$1,Validation!$O$2:$W$631,6,0)+IF(AND(BasicInput!$H$28<>"Ins",COUNTIF(BasicInput!$B$22:$B$26,Validation!$A$38)>=1),MIN(SUMIF(BasicInput!$B$22:$B$26,Validation!$A$38,BasicInput!$G$22:$G$26)/C28,5%),0%))*C28-C30)/BasicInput!$F$28,0),0) -> 0
A37: LTV on MV for Applied Loan Amount (excl GPL and Insurance) | C37: =IFERROR((BasicInput!$D$28+$G$49)/$M$49,0) -> 0
A38: Overall LTV on MV for Applied Loan Amount (incl GPL / Insurance) | C38: =IFERROR((BasicInput!$D$27+$G$49)/$M$49,0) -> 0
A39: LTV for proposed Insurance Loan portion, if any | C39: =IFERROR(SUMIF(BasicInput!$B$22:$B$26,Validation!$A$38,BasicInput!$D$22:$D$26)/$M$49,0) -> 0
A40: TOTAL EXPOSURE ELIGIBLE AS PER LTV NORMS | C40: =MAX($O$49,0) -> 0
A41: FINAL ELIGIBILITY | C41: =MIN(C29,C36,C40) -> 0
A43: Property Address | B43: Property Type | C43: Owner(s) / Proposed Owner(s) | D43: Area (Sq Ft) | E43: Usage / Proposed Usage | F43: Whether in APF Project? | G43: Our existing exposure against the Property (Rs.) | H43: Valuation 1 (Rs.) | I43: Valuation 2 (Rs.) | J43: Agreement Value / Property Cost (incl Amenities) as may be applicable (Rs.) | K43: Stage of Construction | L43: Difference % in Valuations | M43: Valuation to be considered (Rs.) | N43: LTV Applicable on MV | O43: Eligible Loan basis LTV (Rs.)
A44: =IF(BasicInput!$B$34="","",BasicInput!$B$34) | B44: =IF(BasicInput!$C$34="","",BasicInput!$C$34) | C44: =IF(BasicInput!$D$34="","",BasicInput!$D$34) | D44: =IF(BasicInput!$E$34="","",BasicInput!$E$34) | E44: =IF(BasicInput!$F$34="","",BasicInput!$F$34) | F44: =IF(BasicInput!$G$34="","",BasicInput!$G$34) | G44: =IF(BasicInput!$H$34="",0,BasicInput!$H$34) -> 0 | H44: =IF(BasicInput!$I$34="",0,BasicInput!$I$34) -> 0 | I44: =IF(BasicInput!$J$34="",0,BasicInput!$J$34) -> 0 | J44: =IF(BasicInput!$K$34="",0,BasicInput!$K$34) -> 0 | K44: =IF(BasicInput!$L$34="","",BasicInput!$L$34) | L44: =IF(BasicInput!$M$34="","",BasicInput!$M$34) | M44: =IF(BasicInput!$N$34="",0,BasicInput!$N$34) -> Agreement Value / Property Cost required | N44: =IFERROR(IF(AND(OR(BasicInput!$H$28="HL",BasicInput!$H$28="HLIns"),BasicInput!$B$28>=1),MIN(P44-IF(E44=Validation!$A$83,5%,0%),VLOOKUP($H$1,Validation!$O$2:$X$631,10,0))+IF(AND(BasicInput!$H$28<>"Ins",COUNTIF(BasicInput!$B$22:$B$26,Validation!$A$38)>=1),MIN(SUMIF(BasicInput!$B$22:$B$26,Validation!$A$38,BasicInput!$D$22:$D$26)/BasicInput!$J$40,5%),0%)-IF(B44=Validation!$A$76,10%,0%)-IF(AND(BasicInput!$H$28<>"HL",BasicInput!$H$28<>"HLIns",COUNTIF(BasicInput!$B$22:$B$26,Validation!$A$30)>=1,B44=Validation!$A$75),20%,0%),0)+IF(AND($D$2<>0,B44=Validation!$A$76,K44=100%,COUNTIF(BasicInput!$B$22:$B$26,Validation!$A$33)>=1),5%,0),0) -> 0 | O44: =IFERROR(IF(AND(OR(BasicInput!$H$28="HL",BasicInput!$H$28="HLIns"),COUNTIF(BasicInput!$B$22:$B$26,Validation!$A$23)>=1,B44=Validation!$A$75),MIN(M44*N44,J44*(80%-IF(E44=Validation!$A$83,5%,0%)+IF(AND(BasicInput!$H$28<>"Ins",COUNTIF(BasicInput!$B$22:$B$26,Validation!$A$38)>=1),MIN(SUMIF(BasicInput!$B$22:$B$26,Validation!$A$38,BasicInput!$D$22:$D$26)/BasicInput!$J$40,5%),0%))),M44*N44)-G44,0) -> 0 | P44: =IF(AND(OR(BasicInput!$H$28="HL",BasicInput!$H$28="HLIns"),COUNTIF(BasicInput!$B$22:$B$26,Validation!$A$23)>=1,B44=Validation!$A$75),75%,IF(AND(OR(BasicInput!$H$28="HL",BasicInput!$H$28="HLIns"),BasicInput!$B$28>=1,OR(B44=Validation!$A$73,B44=Validation!$A$74)),IF((BasicInput!$D$28+BasicInput!$H$39)>7500000,75%,IF((BasicInput!$D$28+BasicInput!$H$39)>3000000,80%,90%)))) -> FALSE
A45: =IF(BasicInput!$B$35="","",BasicInput!$B$35) | B45: =IF(BasicInput!$C$35="","",BasicInput!$C$35) | C45: =IF(BasicInput!$D$35="","",BasicInput!$D$35) | D45: =IF(BasicInput!$E$35="","",BasicInput!$E$35) | E45: =IF(BasicInput!$F$35="","",BasicInput!$F$35) | F45: =IF(BasicInput!$G$35="","",BasicInput!$G$35) | G45: =IF(BasicInput!$H$35="",0,BasicInput!$H$35) -> 0 | H45: =IF(BasicInput!$I$35="",0,BasicInput!$I$35) -> 0 | I45: =IF(BasicInput!$J$35="",0,BasicInput!$J$35) -> 0 | J45: =IF(BasicInput!$K$35="",0,BasicInput!$K$35) -> 0 | K45: =IF(BasicInput!$L$35="","",BasicInput!$L$35) | L45: =IF(BasicInput!$M$35="","",BasicInput!$M$35) | M45: =IF(BasicInput!$N$35="",0,BasicInput!$N$35) -> Agreement Value / Property Cost required | N45: =IFERROR(IF(AND(OR(BasicInput!$H$28="HL",BasicInput!$H$28="HLIns"),BasicInput!$B$28>=1),MIN(P45-IF(E45=Validation!$A$83,5%,0%),VLOOKUP($H$1,Validation!$O$2:$X$631,10,0))+IF(AND(BasicInput!$H$28<>"Ins",COUNTIF(BasicInput!$B$22:$B$26,Validation!$A$38)>=1),MIN(SUMIF(BasicInput!$B$22:$B$26,Validation!$A$38,BasicInput!$D$22:$D$26)/BasicInput!$J$40,5%),0%)-IF(B45=Validation!$A$76,10%,0%)-IF(AND(BasicInput!$H$28<>"HL",BasicInput!$H$28<>"HLIns",COUNTIF(BasicInput!$B$22:$B$26,Validation!$A$30)>=1,B45=Validation!$A$75),20%,0%),0)+IF(AND($D$2<>0,B45=Validation!$A$76,K45=100%,COUNTIF(BasicInput!$B$22:$B$26,Validation!$A$33)>=1),5%,0),0) -> 0 | O45: =IFERROR(IF(AND(OR(BasicInput!$H$28="HL",BasicInput!$H$28="HLIns"),COUNTIF(BasicInput!$B$22:$B$26,Validation!$A$23)>=1,B45=Validation!$A$75),MIN(M45*N45,J45*(80%-IF(E45=Validation!$A$83,5%,0%)+IF(AND(BasicInput!$H$28<>"Ins",COUNTIF(BasicInput!$B$22:$B$26,Validation!$A$38)>=1),MIN(SUMIF(BasicInput!$B$22:$B$26,Validation!$A$38,BasicInput!$D$22:$D$26)/BasicInput!$J$40,5%),0%))),M45*N45)-G45,0) -> 0 | P45: =IF(AND(OR(BasicInput!$H$28="HL",BasicInput!$H$28="HLIns"),COUNTIF(BasicInput!$B$22:$B$26,Validation!$A$23)>=1,B45=Validation!$A$75),75%,IF(AND(OR(BasicInput!$H$28="HL",BasicInput!$H$28="HLIns"),BasicInput!$B$28>=1,OR(B45=Validation!$A$73,B45=Validation!$A$74)),IF((BasicInput!$D$28+BasicInput!$H$39)>7500000,75%,IF((BasicInput!$D$28+BasicInput!$H$39)>3000000,80%,90%)))) -> FALSE
A46: =IF(BasicInput!$B$36="","",BasicInput!$B$36) | B46: =IF(BasicInput!$C$36="","",BasicInput!$C$36) | C46: =IF(BasicInput!$D$36="","",BasicInput!$D$36) | D46: =IF(BasicInput!$E$36="","",BasicInput!$E$36) | E46: =IF(BasicInput!$F$36="","",BasicInput!$F$36) | F46: =IF(BasicInput!$G$36="","",BasicInput!$G$36) | G46: =IF(BasicInput!$H$36="",0,BasicInput!$H$36) -> 0 | H46: =IF(BasicInput!$I$36="",0,BasicInput!$I$36) -> 0 | I46: =IF(BasicInput!$J$36="",0,BasicInput!$J$36) -> 0 | J46: =IF(BasicInput!$K$36="",0,BasicInput!$K$36) -> 0 | K46: =IF(BasicInput!$L$36="","",BasicInput!$L$36) | L46: =IF(BasicInput!$M$36="","",BasicInput!$M$36) | M46: =IF(BasicInput!$N$36="",0,BasicInput!$N$36) -> Agreement Value / Property Cost required | N46: =IFERROR(IF(AND(OR(BasicInput!$H$28="HL",BasicInput!$H$28="HLIns"),BasicInput!$B$28>=1),MIN(P46-IF(E46=Validation!$A$83,5%,0%),VLOOKUP($H$1,Validation!$O$2:$X$631,10,0))+IF(AND(BasicInput!$H$28<>"Ins",COUNTIF(BasicInput!$B$22:$B$26,Validation!$A$38)>=1),MIN(SUMIF(BasicInput!$B$22:$B$26,Validation!$A$38,BasicInput!$D$22:$D$26)/BasicInput!$J$40,5%),0%)-IF(B46=Validation!$A$76,10%,0%)-IF(AND(BasicInput!$H$28<>"HL",BasicInput!$H$28<>"HLIns",COUNTIF(BasicInput!$B$22:$B$26,Validation!$A$30)>=1,B46=Validation!$A$75),20%,0%),0)+IF(AND($D$2<>0,B46=Validation!$A$76,K46=100%,COUNTIF(BasicInput!$B$22:$B$26,Validation!$A$33)>=1),5%,0),0) -> 0 | O46: =IFERROR(IF(AND(OR(BasicInput!$H$28="HL",BasicInput!$H$28="HLIns"),COUNTIF(BasicInput!$B$22:$B$26,Validation!$A$23)>=1,B46=Validation!$A$75),MIN(M46*N46,J46*(80%-IF(E46=Validation!$A$83,5%,0%)+IF(AND(BasicInput!$H$28<>"Ins",COUNTIF(BasicInput!$B$22:$B$26,Validation!$A$38)>=1),MIN(SUMIF(BasicInput!$B$22:$B$26,Validation!$A$38,BasicInput!$D$22:$D$26)/BasicInput!$J$40,5%),0%))),M46*N46)-G46,0) -> 0 | P46: =IF(AND(OR(BasicInput!$H$28="HL",BasicInput!$H$28="HLIns"),COUNTIF(BasicInput!$B$22:$B$26,Validation!$A$23)>=1,B46=Validation!$A$75),75%,IF(AND(OR(BasicInput!$H$28="HL",BasicInput!$H$28="HLIns"),BasicInput!$B$28>=1,OR(B46=Validation!$A$73,B46=Validation!$A$74)),IF((BasicInput!$D$28+BasicInput!$H$39)>7500000,75%,IF((BasicInput!$D$28+BasicInput!$H$39)>3000000,80%,90%)))) -> FALSE
A47: =IF(BasicInput!$B$37="","",BasicInput!$B$37) | B47: =IF(BasicInput!$C$37="","",BasicInput!$C$37) | C47: =IF(BasicInput!$D$37="","",BasicInput!$D$37) | D47: =IF(BasicInput!$E$37="","",BasicInput!$E$37) | E47: =IF(BasicInput!$F$37="","",BasicInput!$F$37) | F47: =IF(BasicInput!$G$37="","",BasicInput!$G$37) | G47: =IF(BasicInput!$H$37="",0,BasicInput!$H$37) -> 0 | H47: =IF(BasicInput!$I$37="",0,BasicInput!$I$37) -> 0 | I47: =IF(BasicInput!$J$37="",0,BasicInput!$J$37) -> 0 | J47: =IF(BasicInput!$K$37="",0,BasicInput!$K$37) -> 0 | K47: =IF(BasicInput!$L$37="","",BasicInput!$L$37) | L47: =IF(BasicInput!$M$37="","",BasicInput!$M$37) | M47: =IF(BasicInput!$N$37="",0,BasicInput!$N$37) -> Agreement Value / Property Cost required | N47: =IFERROR(IF(AND(OR(BasicInput!$H$28="HL",BasicInput!$H$28="HLIns"),BasicInput!$B$28>=1),MIN(P47-IF(E47=Validation!$A$83,5%,0%),VLOOKUP($H$1,Validation!$O$2:$X$631,10,0))+IF(AND(BasicInput!$H$28<>"Ins",COUNTIF(BasicInput!$B$22:$B$26,Validation!$A$38)>=1),MIN(SUMIF(BasicInput!$B$22:$B$26,Validation!$A$38,BasicInput!$D$22:$D$26)/BasicInput!$J$40,5%),0%)-IF(B47=Validation!$A$76,10%,0%)-IF(AND(BasicInput!$H$28<>"HL",BasicInput!$H$28<>"HLIns",COUNTIF(BasicInput!$B$22:$B$26,Validation!$A$30)>=1,B47=Validation!$A$75),20%,0%),0)+IF(AND($D$2<>0,B47=Validation!$A$76,K47=100%,COUNTIF(BasicInput!$B$22:$B$26,Validation!$A$33)>=1),5%,0),0) -> 0 | O47: =IFERROR(IF(AND(OR(BasicInput!$H$28="HL",BasicInput!$H$28="HLIns"),COUNTIF(BasicInput!$B$22:$B$26,Validation!$A$23)>=1,B47=Validation!$A$75),MIN(M47*N47,J47*(80%-IF(E47=Validation!$A$83,5%,0%)+IF(AND(BasicInput!$H$28<>"Ins",COUNTIF(BasicInput!$B$22:$B$26,Validation!$A$38)>=1),MIN(SUMIF(BasicInput!$B$22:$B$26,Validation!$A$38,BasicInput!$D$22:$D$26)/BasicInput!$J$40,5%),0%))),M47*N47)-G47,0) -> 0 | P47: =IF(AND(OR(BasicInput!$H$28="HL",BasicInput!$H$28="HLIns"),COUNTIF(BasicInput!$B$22:$B$26,Validation!$A$23)>=1,B47=Validation!$A$75),75%,IF(AND(OR(BasicInput!$H$28="HL",BasicInput!$H$28="HLIns"),BasicInput!$B$28>=1,OR(B47=Validation!$A$73,B47=Validation!$A$74)),IF((BasicInput!$D$28+BasicInput!$H$39)>7500000,75%,IF((BasicInput!$D$28+BasicInput!$H$39)>3000000,80%,90%)))) -> FALSE
A48: =IF(BasicInput!$B$38="","",BasicInput!$B$38) | B48: =IF(BasicInput!$C$38="","",BasicInput!$C$38) | C48: =IF(BasicInput!$D$38="","",BasicInput!$D$38) | D48: =IF(BasicInput!$E$38="","",BasicInput!$E$38) | E48: =IF(BasicInput!$F$38="","",BasicInput!$F$38) | F48: =IF(BasicInput!$G$38="","",BasicInput!$G$38) | G48: =IF(BasicInput!$H$38="",0,BasicInput!$H$38) -> 0 | H48: =IF(BasicInput!$I$38="",0,BasicInput!$I$38) -> 0 | I48: =IF(BasicInput!$J$38="",0,BasicInput!$J$38) -> 0 | J48: =IF(BasicInput!$K$38="",0,BasicInput!$K$38) -> 0 | K48: =IF(BasicInput!$L$38="","",BasicInput!$L$38) | L48: =IF(BasicInput!$M$38="","",BasicInput!$M$38) | M48: =IF(BasicInput!$N$38="",0,BasicInput!$N$38) -> Agreement Value / Property Cost required | N48: =IFERROR(IF(AND(OR(BasicInput!$H$28="HL",BasicInput!$H$28="HLIns"),BasicInput!$B$28>=1),MIN(P48-IF(E48=Validation!$A$83,5%,0%),VLOOKUP($H$1,Validation!$O$2:$X$631,10,0))+IF(AND(BasicInput!$H$28<>"Ins",COUNTIF(BasicInput!$B$22:$B$26,Validation!$A$38)>=1),MIN(SUMIF(BasicInput!$B$22:$B$26,Validation!$A$38,BasicInput!$D$22:$D$26)/BasicInput!$J$40,5%),0%)-IF(B48=Validation!$A$76,10%,0%)-IF(AND(BasicInput!$H$28<>"HL",BasicInput!$H$28<>"HLIns",COUNTIF(BasicInput!$B$22:$B$26,Validation!$A$30)>=1,B48=Validation!$A$75),20%,0%),0)+IF(AND($D$2<>0,B48=Validation!$A$76,K48=100%,COUNTIF(BasicInput!$B$22:$B$26,Validation!$A$33)>=1),5%,0),0) -> 0 | O48: =IFERROR(IF(AND(OR(BasicInput!$H$28="HL",BasicInput!$H$28="HLIns"),COUNTIF(BasicInput!$B$22:$B$26,Validation!$A$23)>=1,B48=Validation!$A$75),MIN(M48*N48,J48*(80%-IF(E48=Validation!$A$83,5%,0%)+IF(AND(BasicInput!$H$28<>"Ins",COUNTIF(BasicInput!$B$22:$B$26,Validation!$A$38)>=1),MIN(SUMIF(BasicInput!$B$22:$B$26,Validation!$A$38,BasicInput!$D$22:$D$26)/BasicInput!$J$40,5%),0%))),M48*N48)-G48,0) -> 0 | P48: =IF(AND(OR(BasicInput!$H$28="HL",BasicInput!$H$28="HLIns"),COUNTIF(BasicInput!$B$22:$B$26,Validation!$A$23)>=1,B48=Validation!$A$75),75%,IF(AND(OR(BasicInput!$H$28="HL",BasicInput!$H$28="HLIns"),BasicInput!$B$28>=1,OR(B48=Validation!$A$73,B48=Validation!$A$74)),IF((BasicInput!$D$28+BasicInput!$H$39)>7500000,75%,IF((BasicInput!$D$28+BasicInput!$H$39)>3000000,80%,90%)))) -> FALSE
A49: Total | G49: =SUM(G44:G48) -> 0 | M49: =SUM(M44:M48) -> 0 | O49: =SUM(O44:O48) -> 0

Sheet AffordConsolidated
A1: ADITYA BIRLA HOUSING FINANCE LIMITED
A3: Name of Group: | B3: =IF(Afford1!B1="","",CONCATENATE(Afford1!B1," & Group")) -> KANHAIYA BHARTI & Group
A5: Consolidated Financial Details (as considered)
B6: (Figures in Rs. Lacs)
A7: Profit & Loss Account | B7: =Afford1!B13 -> Provisionals | C7: =Afford1!C13 -> FY 2023-24 | D7: =Afford1!D13 -> FY 2022-23 | E7: =Afford1!E13 -> FY 2021-22 | F7: Inc/Dec (Latest Year) | G7: Inc/Dec (Previous Year)
A8: Operating Income:
A9: Gross Sales / Receipts | B9: =(IF(Afford1!$B$8="Y",Afford1!B15*Afford1!$B$9,0)+IF(Afford2!$B$8="Y",Afford2!B15*Afford2!$B$9,0)+IF(Afford3!$B$8="Y",Afford3!B15*Afford3!$B$9,0)+IF(Afford4!$B$8="Y",Afford4!B15*Afford4!$B$9,0)+IF(Afford5!$B$8="Y",Afford5!B15*Afford5!$B$9,0))/100000 -> 0 | C9: =(IF(Afford1!$B$8="Y",Afford1!C15*Afford1!$B$9,0)+IF(Afford2!$B$8="Y",Afford2!C15*Afford2!$B$9,0)+IF(Afford3!$B$8="Y",Afford3!C15*Afford3!$B$9,0)+IF(Afford4!$B$8="Y",Afford4!C15*Afford4!$B$9,0)+IF(Afford5!$B$8="Y",Afford5!C15*Afford5!$B$9,0))/100000 -> 0 | D9: =(IF(Afford1!$B$8="Y",Afford1!D15*Afford1!$B$9,0)+IF(Afford2!$B$8="Y",Afford2!D15*Afford2!$B$9,0)+IF(Afford3!$B$8="Y",Afford3!D15*Afford3!$B$9,0)+IF(Afford4!$B$8="Y",Afford4!D15*Afford4!$B$9,0)+IF(Afford5!$B$8="Y",Afford5!D15*Afford5!$B$9,0))/100000 -> 0 | E9: =(IF(Afford1!$B$8="Y",Afford1!E15*Afford1!$B$9,0)+IF(Afford2!$B$8="Y",Afford2!E15*Afford2!$B$9,0)+IF(Afford3!$B$8="Y",Afford3!E15*Afford3!$B$9,0)+IF(Afford4!$B$8="Y",Afford4!E15*Afford4!$B$9,0)+IF(Afford5!$B$8="Y",Afford5!E15*Afford5!$B$9,0))/100000 -> 0 | F9: =IFERROR((C9-D9)/D9,"-") -> - | G9: =IFERROR((D9-E9)/E9,"-") -> -
A10: Less: Excise Duty / Sales Tax, Other Indirect tax | B10: =(IF(Afford1!$B$8="Y",Afford1!B16*Afford1!$B$9,0)+IF(Afford2!$B$8="Y",Afford2!B16*Afford2!$B$9,0)+IF(Afford3!$B$8="Y",Afford3!B16*Afford3!$B$9,0)+IF(Afford4!$B$8="Y",Afford4!B16*Afford4!$B$9,0)+IF(Afford5!$B$8="Y",Afford5!B16*Afford5!$B$9,0))/100000 -> 0 | C10: =(IF(Afford1!$B$8="Y",Afford1!C16*Afford1!$B$9,0)+IF(Afford2!$B$8="Y",Afford2!C16*Afford2!$B$9,0)+IF(Afford3!$B$8="Y",Afford3!C16*Afford3!$B$9,0)+IF(Afford4!$B$8="Y",Afford4!C16*Afford4!$B$9,0)+IF(Afford5!$B$8="Y",Afford5!C16*Afford5!$B$9,0))/100000 -> 0 | D10: =(IF(Afford1!$B$8="Y",Afford1!D16*Afford1!$B$9,0)+IF(Afford2!$B$8="Y",Afford2!D16*Afford2!$B$9,0)+IF(Afford3!$B$8="Y",Afford3!D16*Afford3!$B$9,0)+IF(Afford4!$B$8="Y",Afford4!D16*Afford4!$B$9,0)+IF(Afford5!$B$8="Y",Afford5!D16*Afford5!$B$9,0))/100000 -> 0 | E10: =(IF(Afford1!$B$8="Y",Afford1!E16*Afford1!$B$9,0)+IF(Afford2!$B$8="Y",Afford2!E16*Afford2!$B$9,0)+IF(Afford3!$B$8="Y",Afford3!E16*Afford3!$B$9,0)+IF(Afford4!$B$8="Y",Afford4!E16*Afford4!$B$9,0)+IF(Afford5!$B$8="Y",Afford5!E16*Afford5!$B$9,0))/100000 -> 0 | F10: =IFERROR((C10-D10)/D10,"-") -> - | G10: =IFERROR((D10-E10)/E10,"-") -> -
A11: Net Sales | B11: =B9-B10 -> 0 | C11: =C9-C10 -> 0 | D11: =D9-D10 -> 0 | E11: =E9-E10 -> 0 | F11: =IFERROR((C11-D11)/D11,"-") -> - | G11: =IFERROR((D11-E11)/E11,"-") -> -
A12: Other Income (incidental to Business / Business income) | B12: =(IF(Afford1!$B$8="Y",Afford1!B18*Afford1!$B$9,0)+IF(Afford2!$B$8="Y",Afford2!B18*Afford2!$B$9,0)+IF(Afford3!$B$8="Y",Afford3!B18*Afford3!$B$9,0)+IF(Afford4!$B$8="Y",Afford4!B18*Afford4!$B$9,0)+IF(Afford5!$B$8="Y",Afford5!B18*Afford5!$B$9,0))/100000 -> 0 | C12: =(IF(Afford1!$B$8="Y",Afford1!C18*Afford1!$B$9,0)+IF(Afford2!$B$8="Y",Afford2!C18*Afford2!$B$9,0)+IF(Afford3!$B$8="Y",Afford3!C18*Afford3!$B$9,0)+IF(Afford4!$B$8="Y",Afford4!C18*Afford4!$B$9,0)+IF(Afford5!$B$8="Y",Afford5!C18*Afford5!$B$9,0))/100000 -> 0 | D12: =(IF(Afford1!$B$8="Y",Afford1!D18*Afford1!$B$9,0)+IF(Afford2!$B$8="Y",Afford2!D18*Afford2!$B$9,0)+IF(Afford3!$B$8="Y",Afford3!D18*Afford3!$B$9,0)+IF(Afford4!$B$8="Y",Afford4!D18*Afford4!$B$9,0)+IF(Afford5!$B$8="Y",Afford5!D18*Afford5!$B$9,0))/100000 -> 0 | E12: =(IF(Afford1!$B$8="Y",Afford1!E18*Afford1!$B$9,0)+IF(Afford2!$B$8="Y",Afford2!E18*Afford2!$B$9,0)+IF(Afford3!$B$8="Y",Afford3!E18*Afford3!$B$9,0)+IF(Afford4!$B$8="Y",Afford4!E18*Afford4!$B$9,0)+IF(Afford5!$B$8="Y",Afford5!E18*Afford5!$B$9,0))/100000 -> 0 | F12: =IFERROR((C12-D12)/D12,"-") -> - | G12: =IFERROR((D12-E12)/E12,"-") -> -
A13: Total Operating Income | B13: =SUM(B11:B12) -> 0 | C13: =SUM(C11:C12) -> 0 | D13: =SUM(D11:D12) -> 0 | E13: =SUM(E11:E12) -> 0 | F13: =IFERROR((C13-D13)/D13,"-") -> - | G13: =IFERROR((D13-E13)/E13,"-") -> -
A14: Cost of Goods Sold:
A15: Purchases (Opening Stock + Purchases - Closing Stock) | B15: =(IF(Afford1!$B$8="Y",Afford1!B21*Afford1!$B$9,0)+IF(Afford2!$B$8="Y",Afford2!B21*Afford2!$B$9,0)+IF(Afford3!$B$8="Y",Afford3!B21*Afford3!$B$9,0)+IF(Afford4!$B$8="Y",Afford4!B21*Afford4!$B$9,0)+IF(Afford5!$B$8="Y",Afford5!B21*Afford5!$B$9,0))/100000 -> 0 | C15: =(IF(Afford1!$B$8="Y",Afford1!C21*Afford1!$B$9,0)+IF(Afford2!$B$8="Y",Afford2!C21*Afford2!$B$9,0)+IF(Afford3!$B$8="Y",Afford3!C21*Afford3!$B$9,0)+IF(Afford4!$B$8="Y",Afford4!C21*Afford4!$B$9,0)+IF(Afford5!$B$8="Y",Afford5!C21*Afford5!$B$9,0))/100000 -> 0 | D15: =(IF(Afford1!$B$8="Y",Afford1!D21*Afford1!$B$9,0)+IF(Afford2!$B$8="Y",Afford2!D21*Afford2!$B$9,0)+IF(Afford3!$B$8="Y",Afford3!D21*Afford3!$B$9,0)+IF(Afford4!$B$8="Y",Afford4!D21*Afford4!$B$9,0)+IF(Afford5!$B$8="Y",Afford5!D21*Afford5!$B$9,0))/100000 -> 0 | E15: =(IF(Afford1!$B$8="Y",Afford1!E21*Afford1!$B$9,0)+IF(Afford2!$B$8="Y",Afford2!E21*Afford2!$B$9,0)+IF(Afford3!$B$8="Y",Afford3!E21*Afford3!$B$9,0)+IF(Afford4!$B$8="Y",Afford4!E21*Afford4!$B$9,0)+IF(Afford5!$B$8="Y",Afford5!E21*Afford5!$B$9,0))/100000 -> 0 | F15: =IFERROR((C15-D15)/D15,"-") -> - | G15: =IFERROR((D15-E15)/E15,"-") -> -
A16: Direct Expenses | B16: =(IF(Afford1!$B$8="Y",Afford1!B22*Afford1!$B$9,0)+IF(Afford2!$B$8="Y",Afford2!B22*Afford2!$B$9,0)+IF(Afford3!$B$8="Y",Afford3!B22*Afford3!$B$9,0)+IF(Afford4!$B$8="Y",Afford4!B22*Afford4!$B$9,0)+IF(Afford5!$B$8="Y",Afford5!B22*Afford5!$B$9,0))/100000 -> 0 | C16: =(IF(Afford1!$B$8="Y",Afford1!C22*Afford1!$B$9,0)+IF(Afford2!$B$8="Y",Afford2!C22*Afford2!$B$9,0)+IF(Afford3!$B$8="Y",Afford3!C22*Afford3!$B$9,0)+IF(Afford4!$B$8="Y",Afford4!C22*Afford4!$B$9,0)+IF(Afford5!$B$8="Y",Afford5!C22*Afford5!$B$9,0))/100000 -> 0 | D16: =(IF(Afford1!$B$8="Y",Afford1!D22*Afford1!$B$9,0)+IF(Afford2!$B$8="Y",Afford2!D22*Afford2!$B$9,0)+IF(Afford3!$B$8="Y",Afford3!D22*Afford3!$B$9,0)+IF(Afford4!$B$8="Y",Afford4!D22*Afford4!$B$9,0)+IF(Afford5!$B$8="Y",Afford5!D22*Afford5!$B$9,0))/100000 -> 0 | E16: =(IF(Afford1!$B$8="Y",Afford1!E22*Afford1!$B$9,0)+IF(Afford2!$B$8="Y",Afford2!E22*Afford2!$B$9,0)+IF(Afford3!$B$8="Y",Afford3!E22*Afford3!$B$9,0)+IF(Afford4!$B$8="Y",Afford4!E22*Afford4!$B$9,0)+IF(Afford5!$B$8="Y",Afford5!E22*Afford5!$B$9,0))/100000 -> 0 | F16: =IFERROR((C16-D16)/D16,"-") -> - | G16: =IFERROR((D16-E16)/E16,"-") -> -
A17: Total Cost of Goods Sold | B17: =SUM(B15:B16) -> 0 | C17: =SUM(C15:C16) -> 0 | D17: =SUM(D15:D16) -> 0 | E17: =SUM(E15:E16) -> 0 | F17: =IFERROR((C17-D17)/D17,"-") -> - | G17: =IFERROR((D17-E17)/E17,"-") -> -
A18: Indirect Expenses:
A19: Selling, General & Admin Expenses | B19: =(IF(Afford1!$B$8="Y",Afford1!B25*Afford1!$B$9,0)+IF(Afford2!$B$8="Y",Afford2!B25*Afford2!$B$9,0)+IF(Afford3!$B$8="Y",Afford3!B25*Afford3!$B$9,0)+IF(Afford4!$B$8="Y",Afford4!B25*Afford4!$B$9,0)+IF(Afford5!$B$8="Y",Afford5!B25*Afford5!$B$9,0))/100000 -> 0 | C19: =(IF(Afford1!$B$8="Y",Afford1!C25*Afford1!$B$9,0)+IF(Afford2!$B$8="Y",Afford2!C25*Afford2!$B$9,0)+IF(Afford3!$B$8="Y",Afford3!C25*Afford3!$B$9,0)+IF(Afford4!$B$8="Y",Afford4!C25*Afford4!$B$9,0)+IF(Afford5!$B$8="Y",Afford5!C25*Afford5!$B$9,0))/100000 -> 0 | D19: =(IF(Afford1!$B$8="Y",Afford1!D25*Afford1!$B$9,0)+IF(Afford2!$B$8="Y",Afford2!D25*Afford2!$B$9,0)+IF(Afford3!$B$8="Y",Afford3!D25*Afford3!$B$9,0)+IF(Afford4!$B$8="Y",Afford4!D25*Afford4!$B$9,0)+IF(Afford5!$B$8="Y",Afford5!D25*Afford5!$B$9,0))/100000 -> 0 | E19: =(IF(Afford1!$B$8="Y",Afford1!E25*Afford1!$B$9,0)+IF(Afford2!$B$8="Y",Afford2!E25*Afford2!$B$9,0)+IF(Afford3!$B$8="Y",Afford3!E25*Afford3!$B$9,0)+IF(Afford4!$B$8="Y",Afford4!E25*Afford4!$B$9,0)+IF(Afford5!$B$8="Y",Afford5!E25*Afford5!$B$9,0))/100000 -> 0 | F19: =IFERROR((C19-D19)/D19,"-") -> - | G19: =IFERROR((D19-E19)/E19,"-") -> -
A20: Miscellaneous / Deferred Revenue Expenses written off | B20: =(IF(Afford1!$B$8="Y",Afford1!B26*Afford1!$B$9,0)+IF(Afford2!$B$8="Y",Afford2!B26*Afford2!$B$9,0)+IF(Afford3!$B$8="Y",Afford3!B26*Afford3!$B$9,0)+IF(Afford4!$B$8="Y",Afford4!B26*Afford4!$B$9,0)+IF(Afford5!$B$8="Y",Afford5!B26*Afford5!$B$9,0))/100000 -> 0 | C20: =(IF(Afford1!$B$8="Y",Afford1!C26*Afford1!$B$9,0)+IF(Afford2!$B$8="Y",Afford2!C26*Afford2!$B$9,0)+IF(Afford3!$B$8="Y",Afford3!C26*Afford3!$B$9,0)+IF(Afford4!$B$8="Y",Afford4!C26*Afford4!$B$9,0)+IF(Afford5!$B$8="Y",Afford5!C26*Afford5!$B$9,0))/100000 -> 0 | D20: =(IF(Afford1!$B$8="Y",Afford1!D26*Afford1!$B$9,0)+IF(Afford2!$B$8="Y",Afford2!D26*Afford2!$B$9,0)+IF(Afford3!$B$8="Y",Afford3!D26*Afford3!$B$9,0)+IF(Afford4!$B$8="Y",Afford4!D26*Afford4!$B$9,0)+IF(Afford5!$B$8="Y",Afford5!D26*Afford5!$B$9,0))/100000 -> 0 | E20: =(IF(Afford1!$B$8="Y",Afford1!E26*Afford1!$B$9,0)+IF(Afford2!$B$8="Y",Afford2!E26*Afford2!$B$9,0)+IF(Afford3!$B$8="Y",Afford3!E26*Afford3!$B$9,0)+IF(Afford4!$B$8="Y",Afford4!E26*Afford4!$B$9,0)+IF(Afford5!$B$8="Y",Afford5!E26*Afford5!$B$9,0))/100000 -> 0 | F20: =IFERROR((C20-D20)/D20,"-") -> - | G20: =IFERROR((D20-E20)/E20,"-") -> -
A21: Total Indirect Expenses | B21: =SUM(B19:B20) -> 0 | C21: =SUM(C19:C20) -> 0 | D21: =SUM(D19:D20) -> 0 | E21: =SUM(E19:E20) -> 0 | F21: =IFERROR((C21-D21)/D21,"-") -> - | G21: =IFERROR((D21-E21)/E21,"-") -> -
A22: OPBDIT | B22: =B13-B17-B21 -> 0 | C22: =C13-C17-C21 -> 0 | D22: =D13-D17-D21 -> 0 | E22: =E13-E17-E21 -> 0 | F22: =IFERROR((C22-D22)/D22,"-") -> - | G22: =IFERROR((D22-E22)/E22,"-") -> -
A23: Depreciation and amortisation | B23: =(IF(Afford1!$B$8="Y",Afford1!B29*Afford1!$B$9,0)+IF(Afford2!$B$8="Y",Afford2!B29*Afford2!$B$9,0)+IF(Afford3!$B$8="Y",Afford3!B29*Afford3!$B$9,0)+IF(Afford4!$B$8="Y",Afford4!B29*Afford4!$B$9,0)+IF(Afford5!$B$8="Y",Afford5!B29*Afford5!$B$9,0))/100000 -> 0 | C23: =(IF(Afford1!$B$8="Y",Afford1!C29*Afford1!$B$9,0)+IF(Afford2!$B$8="Y",Afford2!C29*Afford2!$B$9,0)+IF(Afford3!$B$8="Y",Afford3!C29*Afford3!$B$9,0)+IF(Afford4!$B$8="Y",Afford4!C29*Afford4!$B$9,0)+IF(Afford5!$B$8="Y",Afford5!C29*Afford5!$B$9,0))/100000 -> 0 | D23: =(IF(Afford1!$B$8="Y",Afford1!D29*Afford1!$B$9,0)+IF(Afford2!$B$8="Y",Afford2!D29*Afford2!$B$9,0)+IF(Afford3!$B$8="Y",Afford3!D29*Afford3!$B$9,0)+IF(Afford4!$B$8="Y",Afford4!D29*Afford4!$B$9,0)+IF(Afford5!$B$8="Y",Afford5!D29*Afford5!$B$9,0))/100000 -> 0 | E23: =(IF(Afford1!$B$8="Y",Afford1!E29*Afford1!$B$9,0)+IF(Afford2!$B$8="Y",Afford2!E29*Afford2!$B$9,0)+IF(Afford3!$B$8="Y",Afford3!E29*Afford3!$B$9,0)+IF(Afford4!$B$8="Y",Afford4!E29*Afford4!$B$9,0)+IF(Afford5!$B$8="Y",Afford5!E29*Afford5!$B$9,0))/100000 -> 0 | F23: =IFERROR((C23-D23)/D23,"-") -> - | G23: =IFERROR((D23-E23)/E23,"-") -> -
A24: OPBIT | B24: =B22-B23 -> 0 | C24: =C22-C23 -> 0 | D24: =D22-D23 -> 0 | E24: =E22-E23 -> 0 | F24: =IFERROR((C24-D24)/D24,"-") -> - | G24: =IFERROR((D24-E24)/E24,"-") -> -
A25: Interest and finance charges | B25: =(IF(Afford1!$B$8="Y",Afford1!B31*Afford1!$B$9,0)+IF(Afford2!$B$8="Y",Afford2!B31*Afford2!$B$9,0)+IF(Afford3!$B$8="Y",Afford3!B31*Afford3!$B$9,0)+IF(Afford4!$B$8="Y",Afford4!B31*Afford4!$B$9,0)+IF(Afford5!$B$8="Y",Afford5!B31*Afford5!$B$9,0))/100000 -> 0 | C25: =(IF(Afford1!$B$8="Y",Afford1!C31*Afford1!$B$9,0)+IF(Afford2!$B$8="Y",Afford2!C31*Afford2!$B$9,0)+IF(Afford3!$B$8="Y",Afford3!C31*Afford3!$B$9,0)+IF(Afford4!$B$8="Y",Afford4!C31*Afford4!$B$9,0)+IF(Afford5!$B$8="Y",Afford5!C31*Afford5!$B$9,0))/100000 -> 0 | D25: =(IF(Afford1!$B$8="Y",Afford1!D31*Afford1!$B$9,0)+IF(Afford2!$B$8="Y",Afford2!D31*Afford2!$B$9,0)+IF(Afford3!$B$8="Y",Afford3!D31*Afford3!$B$9,0)+IF(Afford4!$B$8="Y",Afford4!D31*Afford4!$B$9,0)+IF(Afford5!$B$8="Y",Afford5!D31*Afford5!$B$9,0))/100000 -> 0 | E25: =(IF(Afford1!$B$8="Y",Afford1!E31*Afford1!$B$9,0)+IF(Afford2!$B$8="Y",Afford2!E31*Afford2!$B$9,0)+IF(Afford3!$B$8="Y",Afford3!E31*Afford3!$B$9,0)+IF(Afford4!$B$8="Y",Afford4!E31*Afford4!$B$9,0)+IF(Afford5!$B$8="Y",Afford5!E31*Afford5!$B$9,0))/100000 -> 0 | F25: =IFERROR((C25-D25)/D25,"-") -> - | G25: =IFERROR((D25-E25)/E25,"-") -> -
A26: OPBT | B26: =B24-B25 -> 0 | C26: =C24-C25 -> 0 | D26: =D24-D25 -> 0 | E26: =E24-E25 -> 0 | F26: =IFERROR((C26-D26)/D26,"-") -> - | G26: =IFERROR((D26-E26)/E26,"-") -> -
A27: Non Operating Income | B27: =(IF(Afford1!$B$8="Y",Afford1!B33*Afford1!$B$9,0)+IF(Afford2!$B$8="Y",Afford2!B33*Afford2!$B$9,0)+IF(Afford3!$B$8="Y",Afford3!B33*Afford3!$B$9,0)+IF(Afford4!$B$8="Y",Afford4!B33*Afford4!$B$9,0)+IF(Afford5!$B$8="Y",Afford5!B33*Afford5!$B$9,0))/100000 -> 0 | C27: =(IF(Afford1!$B$8="Y",Afford1!C33*Afford1!$B$9,0)+IF(Afford2!$B$8="Y",Afford2!C33*Afford2!$B$9,0)+IF(Afford3!$B$8="Y",Afford3!C33*Afford3!$B$9,0)+IF(Afford4!$B$8="Y",Afford4!C33*Afford4!$B$9,0)+IF(Afford5!$B$8="Y",Afford5!C33*Afford5!$B$9,0))/100000 -> 0 | D27: =(IF(Afford1!$B$8="Y",Afford1!D33*Afford1!$B$9,0)+IF(Afford2!$B$8="Y",Afford2!D33*Afford2!$B$9,0)+IF(Afford3!$B$8="Y",Afford3!D33*Afford3!$B$9,0)+IF(Afford4!$B$8="Y",Afford4!D33*Afford4!$B$9,0)+IF(Afford5!$B$8="Y",Afford5!D33*Afford5!$B$9,0))/100000 -> 0 | E27: =(IF(Afford1!$B$8="Y",Afford1!E33*Afford1!$B$9,0)+IF(Afford2!$B$8="Y",Afford2!E33*Afford2!$B$9,0)+IF(Afford3!$B$8="Y",Afford3!E33*Afford3!$B$9,0)+IF(Afford4!$B$8="Y",Afford4!E33*Afford4!$B$9,0)+IF(Afford5!$B$8="Y",Afford5!E33*Afford5!$B$9,0))/100000 -> 0 | F27: =IFERROR((C27-D27)/D27,"-") -> - | G27: =IFERROR((D27-E27)/E27,"-") -> -
A28: Less: Non Operating Expenses | B28: =(IF(Afford1!$B$8="Y",Afford1!B34*Afford1!$B$9,0)+IF(Afford2!$B$8="Y",Afford2!B34*Afford2!$B$9,0)+IF(Afford3!$B$8="Y",Afford3!B34*Afford3!$B$9,0)+IF(Afford4!$B$8="Y",Afford4!B34*Afford4!$B$9,0)+IF(Afford5!$B$8="Y",Afford5!B34*Afford5!$B$9,0))/100000 -> 0 | C28: =(IF(Afford1!$B$8="Y",Afford1!C34*Afford1!$B$9,0)+IF(Afford2!$B$8="Y",Afford2!C34*Afford2!$B$9,0)+IF(Afford3!$B$8="Y",Afford3!C34*Afford3!$B$9,0)+IF(Afford4!$B$8="Y",Afford4!C34*Afford4!$B$9,0)+IF(Afford5!$B$8="Y",Afford5!C34*Afford5!$B$9,0))/100000 -> 0 | D28: =(IF(Afford1!$B$8="Y",Afford1!D34*Afford1!$B$9,0)+IF(Afford2!$B$8="Y",Afford2!D34*Afford2!$B$9,0)+IF(Afford3!$B$8="Y",Afford3!D34*Afford3!$B$9,0)+IF(Afford4!$B$8="Y",Afford4!D34*Afford4!$B$9,0)+IF(Afford5!$B$8="Y",Afford5!D34*Afford5!$B$9,0))/100000 -> 0 | E28: =(IF(Afford1!$B$8="Y",Afford1!E34*Afford1!$B$9,0)+IF(Afford2!$B$8="Y",Afford2!E34*Afford2!$B$9,0)+IF(Afford3!$B$8="Y",Afford3!E34*Afford3!$B$9,0)+IF(Afford4!$B$8="Y",Afford4!E34*Afford4!$B$9,0)+IF(Afford5!$B$8="Y",Afford5!E34*Afford5!$B$9,0))/100000 -> 0 | F28: =IFERROR((C28-D28)/D28,"-") -> - | G28: =IFERROR((D28-E28)/E28,"-") -> -
A29: PBT | B29: =B26+B27-B28 -> 0 | C29: =C26+C27-C28 -> 0 | D29: =D26+D27-D28 -> 0 | E29: =E26+E27-E28 -> 0 | F29: =IFERROR((C29-D29)/D29,"-") -> - | G29: =IFERROR((D29-E29)/E29,"-") -> -
A30: Tax | B30: =(IF(Afford1!$B$8="Y",Afford1!B36*Afford1!$B$9,0)+IF(Afford2!$B$8="Y",Afford2!B36*Afford2!$B$9,0)+IF(Afford3!$B$8="Y",Afford3!B36*Afford3!$B$9,0)+IF(Afford4!$B$8="Y",Afford4!B36*Afford4!$B$9,0)+IF(Afford5!$B$8="Y",Afford5!B36*Afford5!$B$9,0))/100000 -> 0 | C30: =(IF(Afford1!$B$8="Y",Afford1!C36*Afford1!$B$9,0)+IF(Afford2!$B$8="Y",Afford2!C36*Afford2!$B$9,0)+IF(Afford3!$B$8="Y",Afford3!C36*Afford3!$B$9,0)+IF(Afford4!$B$8="Y",Afford4!C36*Afford4!$B$9,0)+IF(Afford5!$B$8="Y",Afford5!C36*Afford5!$B$9,0))/100000 -> 0 | D30: =(IF(Afford1!$B$8="Y",Afford1!D36*Afford1!$B$9,0)+IF(Afford2!$B$8="Y",Afford2!D36*Afford2!$B$9,0)+IF(Afford3!$B$8="Y",Afford3!D36*Afford3!$B$9,0)+IF(Afford4!$B$8="Y",Afford4!D36*Afford4!$B$9,0)+IF(Afford5!$B$8="Y",Afford5!D36*Afford5!$B$9,0))/100000 -> 0 | E30: =(IF(Afford1!$B$8="Y",Afford1!E36*Afford1!$B$9,0)+IF(Afford2!$B$8="Y",Afford2!E36*Afford2!$B$9,0)+IF(Afford3!$B$8="Y",Afford3!E36*Afford3!$B$9,0)+IF(Afford4!$B$8="Y",Afford4!E36*Afford4!$B$9,0)+IF(Afford5!$B$8="Y",Afford5!E36*Afford5!$B$9,0))/100000 -> 0 | F30: =IFERROR((C30-D30)/D30,"-") -> - | G30: =IFERROR((D30-E30)/E30,"-") -> -
A31: PAT | B31: =+B29-B30 -> 0 | C31: =+C29-C30 -> 0 | D31: =+D29-D30 -> 0 | E31: =+E29-E30 -> 0 | F31: =IFERROR((C31-D31)/D31,"-") -> - | G31: =IFERROR((D31-E31)/E31,"-") -> -
A32: Cash Profit | B32: =B31+B23+B20 -> 0 | C32: =C31+C23+C20 -> 0 | D32: =D31+D23+D20 -> 0 | E32: =E31+E23+E20 -> 0
A33: Dividend (Inclusive of dividend Tax) | B33: =(IF(Afford1!$B$8="Y",Afford1!B39*Afford1!$B$9,0)+IF(Afford2!$B$8="Y",Afford2!B39*Afford2!$B$9,0)+IF(Afford3!$B$8="Y",Afford3!B39*Afford3!$B$9,0)+IF(Afford4!$B$8="Y",Afford4!B39*Afford4!$B$9,0)+IF(Afford5!$B$8="Y",Afford5!B39*Afford5!$B$9,0))/100000 -> 0 | C33: =(IF(Afford1!$B$8="Y",Afford1!C39*Afford1!$B$9,0)+IF(Afford2!$B$8="Y",Afford2!C39*Afford2!$B$9,0)+IF(Afford3!$B$8="Y",Afford3!C39*Afford3!$B$9,0)+IF(Afford4!$B$8="Y",Afford4!C39*Afford4!$B$9,0)+IF(Afford5!$B$8="Y",Afford5!C39*Afford5!$B$9,0))/100000 -> 0 | D33: =(IF(Afford1!$B$8="Y",Afford1!D39*Afford1!$B$9,0)+IF(Afford2!$B$8="Y",Afford2!D39*Afford2!$B$9,0)+IF(Afford3!$B$8="Y",Afford3!D39*Afford3!$B$9,0)+IF(Afford4!$B$8="Y",Afford4!D39*Afford4!$B$9,0)+IF(Afford5!$B$8="Y",Afford5!D39*Afford5!$B$9,0))/100000 -> 0 | E33: =(IF(Afford1!$B$8="Y",Afford1!E39*Afford1!$B$9,0)+IF(Afford2!$B$8="Y",Afford2!E39*Afford2!$B$9,0)+IF(Afford3!$B$8="Y",Afford3!E39*Afford3!$B$9,0)+IF(Afford4!$B$8="Y",Afford4!E39*Afford4!$B$9,0)+IF(Afford5!$B$8="Y",Afford5!E39*Afford5!$B$9,0))/100000 -> 0 | F33: =IFERROR((C33-D33)/D33,"-") -> - | G33: =IFERROR((D33-E33)/E33,"-") -> -
A34: Salary to Partner/Director | B34: =(IF(Afford1!$B$8="Y",Afford1!B40*Afford1!$B$9,0)+IF(Afford2!$B$8="Y",Afford2!B40*Afford2!$B$9,0)+IF(Afford3!$B$8="Y",Afford3!B40*Afford3!$B$9,0)+IF(Afford4!$B$8="Y",Afford4!B40*Afford4!$B$9,0)+IF(Afford5!$B$8="Y",Afford5!B40*Afford5!$B$9,0))/100000 -> 0 | C34: =(IF(Afford1!$B$8="Y",Afford1!C40*Afford1!$B$9,0)+IF(Afford2!$B$8="Y",Afford2!C40*Afford2!$B$9,0)+IF(Afford3!$B$8="Y",Afford3!C40*Afford3!$B$9,0)+IF(Afford4!$B$8="Y",Afford4!C40*Afford4!$B$9,0)+IF(Afford5!$B$8="Y",Afford5!C40*Afford5!$B$9,0))/100000 -> 0 | D34: =(IF(Afford1!$B$8="Y",Afford1!D40*Afford1!$B$9,0)+IF(Afford2!$B$8="Y",Afford2!D40*Afford2!$B$9,0)+IF(Afford3!$B$8="Y",Afford3!D40*Afford3!$B$9,0)+IF(Afford4!$B$8="Y",Afford4!D40*Afford4!$B$9,0)+IF(Afford5!$B$8="Y",Afford5!D40*Afford5!$B$9,0))/100000 -> 0 | E34: =(IF(Afford1!$B$8="Y",Afford1!E40*Afford1!$B$9,0)+IF(Afford2!$B$8="Y",Afford2!E40*Afford2!$B$9,0)+IF(Afford3!$B$8="Y",Afford3!E40*Afford3!$B$9,0)+IF(Afford4!$B$8="Y",Afford4!E40*Afford4!$B$9,0)+IF(Afford5!$B$8="Y",Afford5!E40*Afford5!$B$9,0))/100000 -> 0 | F34: =IFERROR((C34-D34)/D34,"-") -> - | G34: =IFERROR((D34-E34)/E34,"-") -> -
A35: Interest Expenses paid to partners/director | B35: =(IF(Afford1!$B$8="Y",Afford1!B41*Afford1!$B$9,0)+IF(Afford2!$B$8="Y",Afford2!B41*Afford2!$B$9,0)+IF(Afford3!$B$8="Y",Afford3!B41*Afford3!$B$9,0)+IF(Afford4!$B$8="Y",Afford4!B41*Afford4!$B$9,0)+IF(Afford5!$B$8="Y",Afford5!B41*Afford5!$B$9,0))/100000 -> 0 | C35: =(IF(Afford1!$B$8="Y",Afford1!C41*Afford1!$B$9,0)+IF(Afford2!$B$8="Y",Afford2!C41*Afford2!$B$9,0)+IF(Afford3!$B$8="Y",Afford3!C41*Afford3!$B$9,0)+IF(Afford4!$B$8="Y",Afford4!C41*Afford4!$B$9,0)+IF(Afford5!$B$8="Y",Afford5!C41*Afford5!$B$9,0))/100000 -> 0 | D35: =(IF(Afford1!$B$8="Y",Afford1!D41*Afford1!$B$9,0)+IF(Afford2!$B$8="Y",Afford2!D41*Afford2!$B$9,0)+IF(Afford3!$B$8="Y",Afford3!D41*Afford3!$B$9,0)+IF(Afford4!$B$8="Y",Afford4!D41*Afford4!$B$9,0)+IF(Afford5!$B$8="Y",Afford5!D41*Afford5!$B$9,0))/100000 -> 0 | E35: =(IF(Afford1!$B$8="Y",Afford1!E41*Afford1!$B$9,0)+IF(Afford2!$B$8="Y",Afford2!E41*Afford2!$B$9,0)+IF(Afford3!$B$8="Y",Afford3!E41*Afford3!$B$9,0)+IF(Afford4!$B$8="Y",Afford4!E41*Afford4!$B$9,0)+IF(Afford5!$B$8="Y",Afford5!E41*Afford5!$B$9,0))/100000 -> 0 | F35: =IFERROR((C35-D35)/D35,"-") -> - | G35: =IFERROR((D35-E35)/E35,"-") -> -
A36: Transfer to Reserves | B36: =(IF(Afford1!$B$8="Y",Afford1!B42*Afford1!$B$9,0)+IF(Afford2!$B$8="Y",Afford2!B42*Afford2!$B$9,0)+IF(Afford3!$B$8="Y",Afford3!B42*Afford3!$B$9,0)+IF(Afford4!$B$8="Y",Afford4!B42*Afford4!$B$9,0)+IF(Afford5!$B$8="Y",Afford5!B42*Afford5!$B$9,0))/100000 -> 0 | C36: =(IF(Afford1!$B$8="Y",Afford1!C42*Afford1!$B$9,0)+IF(Afford2!$B$8="Y",Afford2!C42*Afford2!$B$9,0)+IF(Afford3!$B$8="Y",Afford3!C42*Afford3!$B$9,0)+IF(Afford4!$B$8="Y",Afford4!C42*Afford4!$B$9,0)+IF(Afford5!$B$8="Y",Afford5!C42*Afford5!$B$9,0))/100000 -> 0 | D36: =(IF(Afford1!$B$8="Y",Afford1!D42*Afford1!$B$9,0)+IF(Afford2!$B$8="Y",Afford2!D42*Afford2!$B$9,0)+IF(Afford3!$B$8="Y",Afford3!D42*Afford3!$B$9,0)+IF(Afford4!$B$8="Y",Afford4!D42*Afford4!$B$9,0)+IF(Afford5!$B$8="Y",Afford5!D42*Afford5!$B$9,0))/100000 -> 0 | E36: =(IF(Afford1!$B$8="Y",Afford1!E42*Afford1!$B$9,0)+IF(Afford2!$B$8="Y",Afford2!E42*Afford2!$B$9,0)+IF(Afford3!$B$8="Y",Afford3!E42*Afford3!$B$9,0)+IF(Afford4!$B$8="Y",Afford4!E42*Afford4!$B$9,0)+IF(Afford5!$B$8="Y",Afford5!E42*Afford5!$B$9,0))/100000 -> 0 | F36: =IFERROR((C36-D36)/D36,"-") -> - | G36: =IFERROR((D36-E36)/E36,"-") -> -
A37: Retained Profits | B37: =B32-B33-B34-B35 -> 0 | C37: =C32-C33-C34-C35 -> 0 | D37: =D32-D33-D34-D35 -> 0 | E37: =E32-E33-E34-E35 -> 0 | F37: =IFERROR((C37-D37)/D37,"-") -> - | G37: =IFERROR((D37-E37)/E37,"-") -> -
B38: (Figures in Rs. Lacs)
A39: Balance sheet | B39: =Afford1!B45 -> Provisionals | C39: =Afford1!C45 -> 31/03/2024 | D39: =Afford1!D45 -> 31/03/2023 | E39: =Afford1!E45 -> 31/03/2022 | F39: Inc/Dec (Latest Year) | G39: Inc/Dec (Previous Year)
A40: Equity Share Capital:
A41: Equity and Preference Share Capital | B41: =(IF(Afford1!$B$8="Y",Afford1!B47*Afford1!$B$9,0)+IF(Afford2!$B$8="Y",Afford2!B47*Afford2!$B$9,0)+IF(Afford3!$B$8="Y",Afford3!B47*Afford3!$B$9,0)+IF(Afford4!$B$8="Y",Afford4!B47*Afford4!$B$9,0)+IF(Afford5!$B$8="Y",Afford5!B47*Afford5!$B$9,0))/100000 -> 0 | C41: =(IF(Afford1!$B$8="Y",Afford1!C47*Afford1!$B$9,0)+IF(Afford2!$B$8="Y",Afford2!C47*Afford2!$B$9,0)+IF(Afford3!$B$8="Y",Afford3!C47*Afford3!$B$9,0)+IF(Afford4!$B$8="Y",Afford4!C47*Afford4!$B$9,0)+IF(Afford5!$B$8="Y",Afford5!C47*Afford5!$B$9,0))/100000 -> 0 | D41: =(IF(Afford1!$B$8="Y",Afford1!D47*Afford1!$B$9,0)+IF(Afford2!$B$8="Y",Afford2!D47*Afford2!$B$9,0)+IF(Afford3!$B$8="Y",Afford3!D47*Afford3!$B$9,0)+IF(Afford4!$B$8="Y",Afford4!D47*Afford4!$B$9,0)+IF(Afford5!$B$8="Y",Afford5!D47*Afford5!$B$9,0))/100000 -> 0 | E41: =(IF(Afford1!$B$8="Y",Afford1!E47*Afford1!$B$9,0)+IF(Afford2!$B$8="Y",Afford2!E47*Afford2!$B$9,0)+IF(Afford3!$B$8="Y",Afford3!E47*Afford3!$B$9,0)+IF(Afford4!$B$8="Y",Afford4!E47*Afford4!$B$9,0)+IF(Afford5!$B$8="Y",Afford5!E47*Afford5!$B$9,0))/100000 -> 0 | F41: =IFERROR((C41-D41)/D41,"-") -> - | G41: =IFERROR((D41-E41)/E41,"-") -> -
A42: Quasi Equity (Promoter Loans not entailing repayment) | B42: =(IF(Afford1!$B$8="Y",Afford1!B48*Afford1!$B$9,0)+IF(Afford2!$B$8="Y",Afford2!B48*Afford2!$B$9,0)+IF(Afford3!$B$8="Y",Afford3!B48*Afford3!$B$9,0)+IF(Afford4!$B$8="Y",Afford4!B48*Afford4!$B$9,0)+IF(Afford5!$B$8="Y",Afford5!B48*Afford5!$B$9,0))/100000 -> 0 | C42: =(IF(Afford1!$B$8="Y",Afford1!C48*Afford1!$B$9,0)+IF(Afford2!$B$8="Y",Afford2!C48*Afford2!$B$9,0)+IF(Afford3!$B$8="Y",Afford3!C48*Afford3!$B$9,0)+IF(Afford4!$B$8="Y",Afford4!C48*Afford4!$B$9,0)+IF(Afford5!$B$8="Y",Afford5!C48*Afford5!$B$9,0))/100000 -> 0 | D42: =(IF(Afford1!$B$8="Y",Afford1!D48*Afford1!$B$9,0)+IF(Afford2!$B$8="Y",Afford2!D48*Afford2!$B$9,0)+IF(Afford3!$B$8="Y",Afford3!D48*Afford3!$B$9,0)+IF(Afford4!$B$8="Y",Afford4!D48*Afford4!$B$9,0)+IF(Afford5!$B$8="Y",Afford5!D48*Afford5!$B$9,0))/100000 -> 0 | E42: =(IF(Afford1!$B$8="Y",Afford1!E48*Afford1!$B$9,0)+IF(Afford2!$B$8="Y",Afford2!E48*Afford2!$B$9,0)+IF(Afford3!$B$8="Y",Afford3!E48*Afford3!$B$9,0)+IF(Afford4!$B$8="Y",Afford4!E48*Afford4!$B$9,0)+IF(Afford5!$B$8="Y",Afford5!E48*Afford5!$B$9,0))/100000 -> 0 | F42: =IFERROR((C42-D42)/D42,"-") -> - | G42: =IFERROR((D42-E42)/E42,"-") -> -
